Workbook

Sheet 1
B2: CUENTAS POR COBRAR
B3: GESTION 2023 - 2024
C5: CLIENTE: | D5: Fabricio Tapia Castedo
C6: CELULAR: | D6: 67598385
C7: DESTINO: | D7: Cochabamba
C8: LINEA DE CREDITO: | D8: 120000
B10: NOTA DE VENTA | C10: NOTA DE ENTREGA | D10: FECHA DE DESPACHO | E10: MONTO P/COBRAR | F10: DEPÓSITO en Bs | G10: FECHA DE DEPÓSITO | H10: SALDO | I10: DIAS DE MORA | J10: OBSERVACION
B11: 220910 | D11: 44827 | E11: 763.8 | H11: =+E11-F11 -> 763.8
B12: 221011 | D12: 44859 | E12: 1087.43 | H12: =+H11+E12-F12 -> 1851.23
B13: 221102 | D13: 44872 | E13: 4715.4 | H13: =+H12+E13-F13 -> 6566.63
B14: 221106 | D14: 44880 | E14: 41504.2 | H14: =+H13+E14-F14 -> 48070.83
B15: 221123 | D15: 44895 | E15: 41223 | H15: =+H14+E15-F15 -> 89293.83
H16: =+H15+E16-F16 -> 89293.83
H17: =+H16+E17-F17 -> 89293.83
H18: =+H17+E18-F18 -> 89293.83
H19: =+H18+E19-F19 -> 89293.83
H20: =+H19+E20-F20 -> 89293.83
H21: =+H20+E21-F21 -> 89293.83
H22: =+H21+E22-F22 -> 89293.83
H23: =+H22+E23-F23 -> 89293.83
B24: TOTALES | E24: =SUM(E11:E23) -> 89293.83 | F24: =SUM(F11:F23) -> 0
F25: =+E24-F24 -> 89293.83
B28: Conductores de despachos a FABRICIO TAPIA
C29: JULIAN FLORES GONZALES | E29: Cel: | F29: 72898045
C30: JULIAN MARCANI CHUMACERO | E30: Cel:
C31: EDWIN BARRON DURAN | E31: Cel: | F31: 67620372
C32: FRANCISCO DIAS MAMANI | E32: Cel:
C33: FRANCISCO DIAS MAMANI | E33: Cel: | F33: 68623440
C35: Ya estan firmadas.

Sheet 2
B2: CUENTAS POR COBRAR
B3: GESTION 2023 - 2024
C5: CLIENTE: | D5: Edwin Fernandez Chirinos
C6: CELULAR: | D6: 70152337
C7: DESTINO: | D7: El Alto
C8: LINEA DE CREDITO:
B10: NOTA DE VENTA | C10: NOTA DE ENTREGA | D10: FECHA DE DESPACHO | E10: MONTO P/COBRAR | F10: DEPÓSITO en Bs | G10: FECHA DE DEPÓSITO | H10: SALDO | I10: DIAS DE MORA | J10: OBSERVACION
B11: 210731 | D11: 44406 | E11: 7798 | H11: =+E11-F11 -> 7798 | J11: En Proceso
B12: 210814 | D12: 44422 | E12: 39668.5 | H12: =+H11+E12-F12 -> 47466.5 | J12: En Proceso
B13: 210830 | D13: 44439 | E13: 41763.5 | H13: =+H12+E13-F13 -> 89230 | J13: En Proceso
H14: =+H13+E14-F14 -> 89230
H15: =+H14+E15-F15 -> 89230
H16: =+H15+E16-F16 -> 89230
H17: =+H16+E17-F17 -> 89230
H18: =+H17+E18-F18 -> 89230
H19: =+H18+E19-F19 -> 89230
H20: =+H19+E20-F20 -> 89230
H21: =+H20+E21-F21 -> 89230
B22: TOTALES | E22: =SUM(E11:E21) -> 89230 | F22: =SUM(F11:F21) -> 0

Sheet RECAU. JULIO 2025
A3: CUENTAS POR COBRAR A CLIENTES
A4: GESTION 2023 - 2024
A5: JUNIO - 2025
A6: Nº | B6: DISTRIBUIDOR | C6: DEPARTAMENTO | AI6: TOTAL MES
D7: 1 | E7: 2 | F7: 3 | G7: 4 | H7: Semana 1 | I7: 6 | J7: 7 | K7: 8 | L7: 9 | M7: 10 | N7: 11 | O7: Semana 2 | P7: 13 | Q7: 14 | R7: 15 | S7: 16 | T7: 17 | U7: 18 | V7: Semana 3 | W7: 20 | X7: 21 | Y7: 22 | Z7: 23 | AA7: 24 | AB7: 25 | AC7: Semana 4 | AD7: 27 | AE7: 28 | AF7: 29 | AG7: 28 | AH7: Semana 4
A8: 1 | B8: Fabricio Tapia Castedo | C8: Cochabamba | H8: =SUM(D8:G8) -> 0 | O8: =SUM(I8:N8) -> 0 | V8: =SUM(P8:U8) -> 0 | AC8: =SUM(W8:AB8) -> 0 | AH8: =SUM(AD8:AG8) -> 0 | AI8: =+H8+O8+V8+AH8 -> 0
A9: =1+A8 -> 2 | B9: Edwin Fernandez Chirinos | C9: El Alto | H9: =SUM(D9:G9) -> 0 | O9: =SUM(I9:N9) -> 0 | V9: =SUM(P9:U9) -> 0 | AC9: =SUM(W9:AB9) -> 0 | AH9: =SUM(AD9:AG9) -> 0 | AI9: =+H9+O9+V9+AH9 -> 0
A10: =1+A9 -> 3 | B10: Javier Caceres | C10: Cochabamba | H10: =SUM(D10:G10) -> 0 | O10: =SUM(I10:N10) -> 0 | V10: =SUM(P10:U10) -> 0 | AC10: =SUM(W10:AB10) -> 0 | AH10: =SUM(AD10:AG10) -> 0 | AI10: =+H10+O10+V10+AH10 -> 0
A11: =1+A10 -> 4 | B11: Juan Carlos Torrez Ayarde | C11: Tarija | H11: =SUM(D11:G11) -> 0 | O11: =SUM(I11:N11) -> 0 | V11: =SUM(P11:U11) -> 0 | AC11: =SUM(W11:AB11) -> 0 | AH11: =SUM(AD11:AG11) -> 0 | AI11: =+H11+O11+V11+AH11 -> 0
A12: =1+A11 -> 5 | B12: Carol Alejandra Noya | C12: Tarija | H12: =SUM(D12:G12) -> 0 | O12: =SUM(I12:N12) -> 0 | V12: =SUM(P12:U12) -> 0 | AC12: =SUM(W12:AB12) -> 0 | AH12: =SUM(AD12:AG12) -> 0 | AI12: =+H12+O12+V12+AH12 -> 0
A13: =1+A12 -> 6 | B13: Luis Alberto Chipana Peña | C13: Cochabamba | H13: =SUM(D13:G13) -> 0 | O13: =SUM(I13:N13) -> 0 | V13: =SUM(P13:U13) -> 0 | AC13: =SUM(W13:AB13) -> 0 | AH13: =SUM(AD13:AG13) -> 0 | AI13: =+H13+O13+V13+AH13 -> 0
A14: =1+A13 -> 7 | B14: Franz Carlos Alanez Flores | C14: El Alto | H14: =SUM(D14:G14) -> 0 | O14: =SUM(I14:N14) -> 0 | V14: =SUM(P14:U14) -> 0 | AC14: =SUM(W14:AB14) -> 0 | AH14: =SUM(AD14:AG14) -> 0 | AI14: =+H14+O14+V14+AH14 -> 0
A15: =1+A14 -> 8 | B15: Andrés Miguel Paniagua | C15: Oruro | H15: =SUM(D15:G15) -> 0 | O15: =SUM(I15:N15) -> 0 | V15: =SUM(P15:U15) -> 0 | AC15: =SUM(W15:AB15) -> 0 | AH15: =SUM(AD15:AG15) -> 0 | AI15: =+H15+O15+V15+AH15 -> 0
A16: =1+A15 -> 9 | B16: Alex Rolando Fernandez H. | C16: Oruro | H16: =SUM(D16:G16) -> 0 | O16: =SUM(I16:N16) -> 0 | V16: =SUM(P16:U16) -> 0 | AC16: =SUM(W16:AB16) -> 0 | AH16: =SUM(AD16:AG16) -> 0 | AI16: =+H16+O16+V16+AH16 -> 0
A17: =1+A16 -> 10 | B17: Franklin Ever Viveros | C17: Potosí | H17: =SUM(D17:G17) -> 0 | O17: =SUM(I17:N17) -> 0 | V17: =SUM(P17:U17) -> 0 | AC17: =SUM(W17:AB17) -> 0 | AH17: =SUM(AD17:AG17) -> 0 | AI17: =+H17+O17+V17+AH17 -> 0
A18: =1+A17 -> 11 | B18: Teofilo Ibañez Soliz | C18: Tarija | H18: =SUM(D18:G18) -> 0 | O18: =SUM(I18:N18) -> 0 | V18: =SUM(P18:U18) -> 0 | AC18: =SUM(W18:AB18) -> 0 | AH18: =SUM(AD18:AG18) -> 0 | AI18: =+H18+O18+V18+AH18 -> 0
A19: =1+A18 -> 12 | B19: Elsa Romay Padilla | C19: Uyuni | H19: =SUM(D19:G19) -> 0 | O19: =SUM(I19:N19) -> 0 | V19: =SUM(P19:U19) -> 0 | AC19: =SUM(W19:AB19) -> 0 | AH19: =SUM(AD19:AG19) -> 0 | AI19: =+H19+O19+V19+AH19 -> 0
A20: =1+A19 -> 13 | B20: Jorge Luis Vedia Arancibia | C20: Chuquisaca - Prov | H20: =SUM(D20:G20) -> 0 | O20: =SUM(I20:N20) -> 0 | V20: =SUM(P20:U20) -> 0 | AC20: =SUM(W20:AB20) -> 0 | AH20: =SUM(AD20:AG20) -> 0 | AI20: =+H20+O20+V20+AH20 -> 0
A21: =1+A20 -> 14 | B21: Celina Cruz Mendez | C21: Chuquisaca - Prov | H21: =SUM(D21:G21) -> 0 | O21: =SUM(I21:N21) -> 0 | V21: =SUM(P21:U21) -> 0 | AC21: =SUM(W21:AB21) -> 0 | AH21: =SUM(AD21:AG21) -> 0 | AI21: =+H21+O21+V21+AH21 -> 0
A22: =1+A28 -> 20 | B22: Marlene Paicho | C22: Ruta Colquechaca | H22: =SUM(D22:G22) -> 0 | O22: =SUM(I22:N22) -> 0 | V22: =SUM(P22:U22) -> 0 | AC22: =SUM(W22:AB22) -> 0 | AH22: =SUM(AD22:AG22) -> 0 | AI22: =H22+O22+V22+AH22 -> 0
A23: TOTAL CLIENTES MOROSOS | G23: =SUM(G8:G22) -> 0 | H23: =SUM(D23:G23) -> 0 | I23: =SUM(I8:I22) -> 0 | J23: =SUM(J8:J22) -> 0 | K23: =SUM(K8:K22) -> 0 | L23: =SUM(L8:L22) -> 0 | M23: =SUM(M8:M22) -> 0 | N23: =SUM(N8:N22) -> 0 | O23: =SUM(I23:N23) -> 0 | P23: =SUM(P8:P22) -> 0 | Q23: =SUM(Q8:Q22) -> 0 | R23: =SUM(R8:R22) -> 0 | S23: =SUM(S8:S22) -> 0 | T23: =SUM(T8:T22) -> 0 | U23: =SUM(U8:U22) -> 0 | V23: =SUM(P23:U23) -> 0 | W23: =SUM(W8:W22) -> 0 | X23: =SUM(X8:X22) -> 0 | Y23: =SUM(Y8:Y22) -> 0 | Z23: =SUM(Z8:Z22) -> 0 | AA23: =SUM(AA8:AA22) -> 0 | AB23: =SUM(AB8:AB22) -> 0 | AC23: =SUM(W23:AB23) -> 0 | AD23: =SUM(AD8:AD22) -> 0 | AG23: =SUM(AG8:AG22) -> 0 | AH23: =SUM(AD23:AG23) -> 0 | AI23: =SUM(AI8:AI22) -> 0
A24: =1+A21 -> 15 | B24: EMAPA NACIONAL | C24: NACIONAL | H24: =SUM(D24:G24) -> 0 | O24: =SUM(I24:N24) -> 0 | V24: =SUM(P24:U24) -> 0 | AC24: =SUM(W24:AB24) -> 0 | AH24: =SUM(AD24:AG24) -> 0 | AI24: =H24+O24+V24+AC24+AH24 -> 0
A25: =1+A24 -> 16 | B25: Gustavo Tellez Ugarte | C25: Santa Cruz | H25: =SUM(D25:G25) -> 0 | O25: =SUM(I25:N25) -> 0 | V25: =SUM(P25:U25) -> 0 | AC25: =SUM(W25:AB25) -> 0 | AH25: =SUM(AD25:AG25) -> 0 | AI25: =H25+O25+V25+AC25+AH25 -> 0
A26: =1+A25 -> 17 | B26: Cristhian Murillo | C26: Sucre | H26: =SUM(D26:G26) -> 0 | O26: =SUM(I26:N26) -> 0 | V26: =SUM(P26:U26) -> 0 | AC26: =SUM(W26:AB26) -> 0 | AG26: =+'Cristhian Murillo'!F43 -> 341500 | AH26: =SUM(AD26:AG26) -> 341500 | AI26: =H26+O26+V26+AC26+AH26 -> 341500
A27: =1+A26 -> 18 | B27: Sebastian Miranda | C27: Oruro | H27: =SUM(D27:G27) -> 0 | O27: =SUM(I27:N27) -> 0 | V27: =SUM(P27:U27) -> 0 | AC27: =SUM(W27:AB27) -> 0 | AH27: =SUM(AD27:AG27) -> 0 | AI27: =H27+O27+V27+AC27+AH27 -> 0
A28: =1+A27 -> 19 | B28: Norha Choque Talavera | C28: Potosí | H28: =SUM(D28:G28) -> 0 | O28: =SUM(I28:N28) -> 0 | V28: =SUM(P28:U28) -> 0 | AC28: =SUM(W28:AB28) -> 0 | AH28: =SUM(AD28:AG28) -> 0 | AI28: =H28+O28+V28+AC28+AH28 -> 0
A29: =1+A28 -> 20 | B29: Orlando Aldunate M. | C29: Tarija | H29: =SUM(D29:G29) -> 0 | O29: =SUM(I29:N29) -> 0 | V29: =SUM(P29:U29) -> 0 | AC29: =SUM(W29:AB29) -> 0 | AG29: =+'Orlando Aldunate'!L23 -> 136757.5 | AH29: =SUM(AD29:AG29) -> 136757.5 | AI29: =H29+O29+V29+AC29+AH29 -> 136757.5
A30: =1+A29 -> 21 | B30: Fausto Condori | C30: Cochabamba | H30: =SUM(D30:G30) -> 0 | O30: =SUM(I30:N30) -> 0 | V30: =SUM(P30:U30) -> 0 | AC30: =SUM(W30:AB30) -> 0 | AH30: =SUM(AD30:AG30) -> 0 | AI30: =H30+O30+V30+AC30+AH30 -> 0
A31: =1+A30 -> 22 | B31: Flora Yapuchura | C31: La Paz | H31: =SUM(D31:G31) -> 0 | O31: =SUM(I31:N31) -> 0 | V31: =SUM(P31:U31) -> 0 | AC31: =SUM(W31:AB31) -> 0 | AH31: =SUM(AD31:AG31) -> 0 | AI31: =H31+O31+V31+AC31+AH31 -> 0
A32: =1+A31 -> 23 | B32: Willy Quispe | C32: El Alto | H32: =SUM(D32:G32) -> 0 | O32: =SUM(I32:N32) -> 0 | V32: =SUM(P32:U32) -> 0 | AC32: =SUM(W32:AB32) -> 0 | AH32: =SUM(AD32:AG32) -> 0 | AI32: =H32+O32+V32+AC32+AH32 -> 0
A33: =1+A32 -> 24 | B33: Andrez Lopez | C33: Potosí | H33: =SUM(D33:G33) -> 0 | O33: =SUM(I33:N33) -> 0 | V33: =SUM(P33:U33) -> 0 | AC33: =SUM(W33:AB33) -> 0 | AH33: =SUM(AD33:AG33) -> 0 | AI33: =H33+O33+V33+AC33+AH33 -> 0
A34: =1+A33 -> 25 | B34: Miguel Angel Mora | C34: Potosí | H34: =SUM(D34:G34) -> 0 | O34: =SUM(I34:N34) -> 0 | V34: =SUM(P34:U34) -> 0 | AC34: =SUM(W34:AB34) -> 0 | AH34: =SUM(AD34:AG34) -> 0 | AI34: =H34+O34+V34+AC34+AH34 -> 0
A35: =1+A34 -> 26 | B35: GAMS Desarrollo Productivo | C35: Sucre | H35: =SUM(D35:G35) -> 0 | O35: =SUM(I35:N35) -> 0 | V35: =SUM(P35:U35) -> 0 | AC35: =SUM(W35:AB35) -> 0 | AG35: =+GAMS!F12 -> 11745 | AH35: =SUM(AD35:AG35) -> 11745 | AI35: =H35+O35+V35+AC35+AH35 -> 11745
A36: =1+A35 -> 27 | B36: GAMS Direccion Administrativa | C36: Sucre | H36: =SUM(D36:G36) -> 0 | O36: =SUM(I36:N36) -> 0 | V36: =SUM(P36:U36) -> 0 | AC36: =SUM(W36:AB36) -> 0 | AH36: =SUM(AD36:AG36) -> 0 | AI36: =H36+O36+V36+AC36+AH36 -> 0
A37: =1+A36 -> 28 | B37: Carmen Cruz | C37: Potosí | H37: =SUM(D37:G37) -> 0 | O37: =SUM(I37:N37) -> 0 | V37: =SUM(P37:U37) -> 0 | AC37: =SUM(W37:AB37) -> 0 | AG37: =+#REF! -> #REF! | AH37: =SUM(AD37:AG37) -> #REF! | AI37: =H37+O37+V37+AC37+AH37 -> #REF!
A38: =1+A37 -> 29 | B38: Judith | C38: Cochabamba | H38: =SUM(D38:G38) -> 0 | O38: =SUM(I38:N38) -> 0 | V38: =SUM(P38:U38) -> 0 | AC38: =SUM(W38:AB38) -> 0 | AH38: =SUM(AD38:AG38) -> 0 | AI38: =H38+O38+V38+AC38+AH38 -> 0
A39: =1+A38 -> 30 | B39: Kevin | C39: Oruro | H39: =SUM(D39:G39) -> 0 | O39: =SUM(I39:N39) -> 0 | V39: =SUM(P39:U39) -> 0 | AC39: =SUM(W39:AB39) -> 0 | AH39: =SUM(AD39:AG39) -> 0 | AI39: =H39+O39+V39+AC39+AH39 -> 0
A40: =1+A39 -> 31 | B40: Jorge Saavedra | C40: Tupiza | H40: =SUM(D40:G40) -> 0 | O40: =SUM(I40:N40) -> 0 | V40: =SUM(P40:U40) -> 0 | AC40: =SUM(W40:AB40) -> 0 | AG40: =+#REF! -> #REF! | AH40: =SUM(AD40:AG40) -> #REF! | AI40: =H40+O40+V40+AC40+AH40 -> #REF!
A41: =1+A40 -> 32 | B41: Jenrry | C41: Chile | H41: =SUM(D41:G41) -> 0 | O41: =SUM(I41:N41) -> 0 | V41: =SUM(P41:U41) -> 0 | AC41: =SUM(W41:AB41) -> 0 | AG41: =+#REF! -> #REF! | AH41: =SUM(AD41:AG41) -> #REF! | AI41: =H41+O41+V41+AC41+AH41 -> #REF!
A42: =1+A41 -> 33 | B42: Eddy | C42: Chile | H42: =SUM(D42:G42) -> 0 | O42: =SUM(I42:N42) -> 0 | V42: =SUM(P42:U42) -> 0 | AC42: =SUM(W42:AB42) -> 0 | AG42: =+#REF! -> #REF! | AH42: =SUM(AD42:AG42) -> #REF! | AI42: =H42+O42+V42+AC42+AH42 -> #REF!
A43: =1+A42 -> 34 | B43: Rene Cahuana | C43: La Paz | H43: =SUM(D43:G43) -> 0 | O43: =SUM(I43:N43) -> 0 | V43: =SUM(P43:U43) -> 0 | AC43: =SUM(W43:AB43) -> 0 | AG43: =+'Rene Cahuana'!L22 -> 206975 | AH43: =SUM(AD43:AG43) -> 206975 | AI43: =H43+O43+V43+AC43+AH43 -> 206975
A44: =1+A43 -> 35 | B44: Ines Aguirre | C44: Provincias Villazon | H44: =SUM(D44:G44) -> 0 | O44: =SUM(I44:N44) -> 0 | V44: =SUM(P44:U44) -> 0 | AC44: =SUM(W44:AB44) -> 0 | AG44: =+'Ines A - Villazon'!F11 -> 91740 | AH44: =SUM(AD44:AG44) -> 91740 | AI44: =H44+O44+V44+AC44+AH44 -> 91740
A45: =1+A44 -> 36 | B45: Yobana Llanos Cruz | C45: Ruta Chapare | H45: =SUM(D45:G45) -> 0 | O45: =SUM(I45:N45) -> 0 | V45: =SUM(P45:U45) -> 0 | AC45: =SUM(W45:AB45) -> 0 | AH45: =SUM(AD45:AG45) -> 0 | AI45: =H45+O45+V45+AC45+AH45 -> 0
A46: =1+A45 -> 37 | B46: Hernan Colque Cruz | C46: Pisiga | H46: =SUM(D46:G46) -> 0 | O46: =SUM(I46:N46) -> 0 | V46: =SUM(P46:U46) -> 0 | AC46: =SUM(W46:AB46) -> 0 | AG46: =+'Hernan - Pisiga'!L13 -> 76560 | AH46: =SUM(AD46:AG46) -> 76560 | AI46: =H46+O46+V46+AC46+AH46 -> 76560
A47: =1+A46 -> 38 | B47: Roxana Yanet Castrillo Vasco | C47: Bermejo | H47: =SUM(D47:G47) -> 0 | O47: =SUM(I47:N47) -> 0 | V47: =SUM(P47:U47) -> 0 | AC47: =SUM(W47:AB47) -> 0 | AH47: =SUM(AD47:AG47) -> 0 | AI47: =H47+O47+V47+AC47+AH47 -> 0
A48: =1+A47 -> 39 | B48: Ismael Marca | C48: Uyuni | H48: =SUM(D48:G48) -> 0 | O48: =SUM(I48:N48) -> 0 | V48: =SUM(P48:U48) -> 0 | AC48: =SUM(W48:AB48) -> 0 | AH48: =SUM(AD48:AG48) -> 0 | AI48: =H48+O48+V48+AC48+AH48 -> 0
A49: =1+A48 -> 40 | B49: Freddy Alcocer Mollo | C49: Oruro | H49: =SUM(D49:G49) -> 0 | AH49: =SUM(AD49:AG49) -> 0 | AI49: =H49+O49+V49+AC49+AH49 -> 0
A50: =1+A49 -> 41 | B50: David Choque - Katerine | C50: Oruro Provincia | H50: =SUM(D50:G50) -> 0 | AG50: =+'David Choque - Katerine'!L28 -> 123435 | AH50: =SUM(AD50:AG50) -> 123435 | AI50: =H50+O50+V50+AC50+AH50 -> 123435
A51: =1+A50 -> 42 | B51: Nilda | C51: CBBA Provincia | H51: =SUM(D51:G51) -> 0 | AH51: =SUM(AD51:AG51) -> 0 | AI51: =H51+O51+V51+AC51+AH51 -> 0
A52: =1+A51 -> 43 | B52: Divar Aranibar Plata | C52: Oruro | AH52: =SUM(AD52:AG52) -> 0 | AI52: =H52+O52+V52+AC52+AH52 -> 0
A53: =1+A52 -> 44 | B53: Ruth Gabriela | C53: Pando | AH53: =SUM(AD53:AG53) -> 0 | AI53: =H53+O53+V53+AC53+AH53 -> 0
A54: =1+A53 -> 45 | B54: Sergio Romero | C54: Sucre | AH54: =SUM(AD54:AG54) -> 0 | AI54: =H54+O54+V54+AC54+AH54 -> 0
A55: =1+A54 -> 46 | B55: Jorge Cruz | C55: Chile | H55: =SUM(D55:G55) -> 0 | O55: =SUM(I55:N55) -> 0 | V55: =SUM(P55:U55) -> 0 | AC55: =SUM(W55:AB55) -> 0 | AH55: =SUM(AD55:AG55) -> 0 | AI55: =H55+O55+V55+AC55+AH55 -> 0
A56: =1+A55 -> 47 | B56: Javier Mercado | C56: El Alto | AH56: =SUM(AD56:AG56) -> 0 | AI56: =H56+O56+V56+AC56+AH56 -> 0
A57: =1+A56 -> 48 | B57: Yaneth Miriam Toroya Gabriel | C57: Oruro | AG57: =+#REF! -> #REF! | AH57: =SUM(AD57:AG57) -> #REF! | AI57: =H57+O57+V57+AC57+AH57 -> #REF!
A58: =1+A57 -> 49 | B58: Patricia Romero | C58: Oruro | AH58: =SUM(AD58:AG58) -> 0 | AI58: =H58+O58+V58+AC58+AH58 -> 0
A59: =1+A58 -> 50 | B59: Miguel Calle | C59: Villazon | AH59: =SUM(AD59:AG59) -> 0 | AI59: =H59+O59+V59+AC59+AH59 -> 0
A60: =1+A59 -> 51 | B60: Paul Yamani | C60: Cochabamba | AG60: =+'Paul Yamani'!L16 -> 135234 | AH60: =SUM(AD60:AG60) -> 135234 | AI60: =H60+O60+V60+AC60+AH60 -> 135234
A61: =1+A60 -> 52 | B61: Silvia Gomez | C61: Huanuni | H61: =SUM(D61:G61) -> 0 | O61: =SUM(I61:N61) -> 0 | V61: =SUM(P61:U61) -> 0 | AC61: =SUM(W61:AB61) -> 0 | AH61: =SUM(AD61:AG61) -> 0 | AI61: =H61+O61+V61+AC61+AH61 -> 0
A62: =1+A61 -> 53 | B62: Alejandro Luna | C62: Chile | AH62: =SUM(AD62:AG62) -> 0 | AI62: =H62+O62+V62+AC62+AH62 -> 0
A63: =1+A62 -> 54 | B63: Sandra Gutierrez Quispe | C63: Chile | AH63: =SUM(AD63:AG63) -> 0 | AI63: =H63+O63+V63+AC63+AH63 -> 0
A64: =1+A63 -> 55 | B64: Venta colillas y otros | C64: Sucre | H64: =SUM(D64:G64) -> 0 | O64: =SUM(I64:N64) -> 0 | V64: =SUM(P64:U64) -> 0 | AC64: =SUM(W64:AB64) -> 0 | AH64: =SUM(AD64:AG64) -> 0 | AI64: =H64+O64+V64+AC64+AH64 -> 0
A65: =1+A64 -> 56 | B65: FEXPO 2025 | C65: Sucre | AH65: =SUM(AD65:AG65) -> 0 | AI65: =H65+O65+V65+AC65+AH65 -> 0
A66: =1+A64 -> 56 | B66: Ventas en FABRICA | C66: Sucre | H66: =SUM(D66:G66) -> 0 | O66: =SUM(I66:N66) -> 0 | V66: =SUM(P66:U66) -> 0 | AC66: =SUM(W66:AB66) -> 0 | AG66: 150295.5 | AH66: =SUM(AD66:AG66) -> 150295.5 | AI66: =H66+O66+V66+AC66+AH66 -> 150295.5
A67: TOTALE CLIENTES ACTIVOS | G67: =SUM(G24:G66) -> 0 | H67: =SUM(D67:G67) -> 0 | I67: =SUM(I24:I66) -> 0 | J67: =SUM(J24:J66) -> 0 | K67: =SUM(K24:K66) -> 0 | L67: =SUM(L24:L66) -> 0 | M67: =SUM(M24:M66) -> 0 | N67: =SUM(N24:N66) -> 0 | O67: =SUM(I67:N67) -> 0 | P67: =SUM(P24:P66) -> 0 | Q67: =SUM(Q24:Q66) -> 0 | R67: =SUM(R24:R66) -> 0 | S67: =SUM(S24:S66) -> 0 | T67: =SUM(T24:T66) -> 0 | U67: =SUM(U24:U66) -> 0 | V67: =SUM(P67:U67) -> 0 | W67: =SUM(W24:W66) -> 0 | X67: =SUM(X24:X66) -> 0 | Y67: =SUM(Y24:Y66) -> 0 | Z67: =SUM(Z24:Z66) -> 0 | AA67: =SUM(AA24:AA66) -> 0 | AB67: =SUM(AB24:AB66) -> 0 | AC67: =SUM(W67:AB67) -> 0 | AD67: =SUM(AD24:AD66) -> 0 | AE67: =SUM(AE24:AE66) -> 0 | AF67: =SUM(AF24:AF66) -> 0 | AG67: =SUM(AG24:AG66) -> #REF! | AH67: =SUM(AD67:AG67) -> #REF! | AI67: =SUM(AI24:AI66) -> #REF!
A68: TOTALE CLIENTES | D68: =+D23+D67 -> 0 | E68: =+E23+E67 -> 0 | F68: =+F23+F67 -> 0 | G68: =+G23+G67 -> 0 | H68: =SUM(D68:G68) -> 0 | I68: =+I23+I67 -> 0 | J68: =+J23+J67 -> 0 | K68: =+K23+K67 -> 0 | L68: =+L23+L67 -> 0 | M68: =+M23+M67 -> 0 | N68: =+N23+N67 -> 0 | O68: =SUM(I68:N68) -> 0 | P68: =+P23+P67 -> 0 | Q68: =+Q23+Q67 -> 0 | R68: =+R23+R67 -> 0 | S68: =+S23+S67 -> 0 | T68: =+T23+T67 -> 0 | U68: =+U23+U67 -> 0 | V68: =SUM(P68:U68) -> 0 | W68: =+W23+W67 -> 0 | X68: =+X23+X67 -> 0 | Y68: =+Y23+Y67 -> 0 | Z68: =+Z23+Z67 -> 0 | AA68: =+AA23+AA67 -> 0 | AB68: =+AB23+AB67 -> 0 | AC68: =SUM(W68:AB68) -> 0 | AD68: =+AD23+AD67 -> 0 | AH68: =SUM(AD68:AG68) -> 0 | AI68: =SUM(AI67,AI23) -> #REF!

Sheet 3-Fausto C
B2: CUENTAS POR COBRAR
B3: GESTION 2023 - 2024
C5: CLIENTE: | D5: Javier Caceres Parada
C6: CELULAR: | D6: 74333570
C7: DESTINO: | D7: Cochabamba
C8: LINEA DE CREDITO: | D8: 80000
B10: NOTA DE VENTA | C10: NOTA DE ENTREGA | D10: FECHA DE DESPACHO | E10: MONTO P/COBRAR | F10: DEPÓSITO en Bs | G10: FECHA DE DEPÓSITO | H10: SALDO | I10: DIAS DE MORA | J10: OBSERVACION
B11: 230328 | C11: - | D11: 45010 | E11: 9977.9 | H11: =+E11-F11 -> 9977.9
B12: 230511 | C12: 294 | D12: 45054 | E12: 39134 | H12: =+H11+E12-F12 -> 49111.9
B13: 230644 | C13: 370 | D13: 45106 | E13: 33574 | H13: =+H12+E13-F13 -> 82685.9
H14: =+H13+E14-F14 -> 82685.9
H15: =+H14+E15-F15 -> 82685.9
H16: =+H15+E16-F16 -> 82685.9
H17: =+H16+E17-F17 -> 82685.9
H18: =+H17+E18-F18 -> 82685.9
B19: TOTALES | E19: =SUM(E11:E18) -> 82685.9 | F19: =SUM(F11:F18) -> 0
F20: =+E19-F19 -> 82685.9
C23: CLIENTE: | D23: Fausto Condori
C24: CELULAR:
C25: DESTINO: | D25: Cochabamba
C26: LINEA DE CREDITO:
B28: NOTA DE VENTA | C28: NOTA DE ENTREGA | D28: FECHA DE DESPACHO | E28: MONTO P/COBRAR | F28: DEPÓSITO en Bs | G28: FECHA DE DEPÓSITO | H28: SALDO | I28: DIAS DE MORA | J28: OBSERVACION
B29: 230903 | C29: 479 | D29: 45173 | E29: 33522 | F29: 20000 | G29: 45171 | H29: =+E29-F29 -> 13522
B30: 230923 | C30: 505 | D30: 45178 | E30: 62755 | F30: 13522 | G30: 45175 | H30: =+H29+E30-F30 -> 62755
B31: 230958 | C31: 538 | D31: 45194 | E31: 30904.8 | F31: 25000 | G31: 45178 | H31: =+H30+E31-F31 -> 68659.8
B32: 231058 | C32: 618 | D32: 45229 | E32: 71602.8 | F32: 37755 | G32: 45182 | H32: =+H31+E32-F32 -> 102507.6
F33: 14224.5 | G33: 45194 | H33: =+H32+E33-F33 -> 88283.1
F34: 16680.3 | G34: 45197 | H34: =+H33+E34-F34 -> 71602.8
F35: 50000 | G35: 45230 | H35: =+H34+E35-F35 -> 21602.8
F36: 21600.8 | G36: 45246 | H36: =+H35+E36-F36 -> 2
B37: 240243 | C37: 863 | D37: 45346 | E37: 26400 | F37: 26400 | G37: 45348 | H37: =+H36+E37-F37 -> 2
B38: 240437 | C38: 981 | D38: 45399 | E38: 36800 | F38: 36800 | G38: 45399 | H38: =+H37+E38-F38 -> 2
B39: 240736 | C39: 1180 | D39: 45492 | E39: 36420 | F39: 36420 | G39: 45492 | H39: =+H38+E39-F39 -> 2 | J39: Marco Antonio Condori Flores | L39: BU
B40: 240751 | C40: 1195 | D40: 45498 | E40: 41646 | F40: 37930 | G40: 45498 | H40: =+H39+E40-F40 -> 3718 | J40: FAUSTO | L40: BNB
F41: 3650 | G41: 45498 | H41: =+H40+E41-F41 -> 68 | J41: ELIANA CONDORI | L41: BNB | M41: =SUM(F39:F41) -> 78000
B42: 240839 | C42: 1243 | D42: 45532 | E42: 38219 | F42: 23300 | G42: 45532 | H42: =+H41+E42-F42 -> 14987
F43: 20000 | G43: 45532 | H43: =+H42+E43-F43 -> -5013 | M43: =SUM(F42:F43) -> 43300
B44: 240905 | C44: 1260 | D44: 45539 | E44: 53566 | F44: 30000 | G44: 45539 | H44: =+H43+E44-F44 -> 18553
F45: 10000 | G45: 45539 | H45: =+H44+E45-F45 -> 8553
F46: 8485 | G46: 45540 | H46: =+H45+E46-F46 -> 68 | M46: =SUM(F44:F46) -> 48485
B47: 241015 | C47: 1346 | D47: 45572 | E47: 42940 | F47: 20940 | G47: 45572 | H47: =+H46+E47-F47 -> 22068
F48: 22000 | G48: 45572 | H48: =+H47+E48-F48 -> 68 | M48: =+F47+F48 -> 42940
B49: 241121 | C49: 1423 | D49: 45615 | E49: 50839 | F49: 23000 | G49: 45615 | H49: =+H48+E49-F49 -> 27907 | J49: Eliana Condori Flores | L49: BU
F50: 22000 | G50: 45615 | H50: =+H49+E50-F50 -> 5907 | J50: Marco Antonio Condori Flores | L50: BU
F51: 4000 | G51: 45616 | H51: =+H50+E51-F51 -> 1907 | J51: Eliana Condori Flores | L51: BNB
F52: 1839 | G52: 45616 | H52: =+H51+E52-F52 -> 68 | J52: Eliana Condori Flores | L52: BNB | M52: =SUM(F49:F52) -> 50839
B53: 250132 | C53: 1555 | D53: 45675 | E53: 48722.4 | F53: 39900 | G53: 45675 | H53: =+H52+E53-F53 -> 8890.4 | J53: Marco Antonio Condori Flores | L53: BU
F54: 8822.4 | G54: 45675 | H54: =+H53+E54-F54 -> 68 | J54: Transf. Eliana Condori Flores | L54: BNB | M54: =+F53+F54 -> 48722.4
B55: 250251 | C55: 1638 | D55: 45715 | E55: 55146 | F55: 20000 | G55: 45715 | H55: =+H54+E55-F55 -> 35214 | J55: Faustino Condori Villegas | L55: BU
F56: 23000 | G56: 45715 | H56: =+H55+E56-F56 -> 12214 | J56: Marco Antonio Condori Flores | L56: BU
F57: 12146 | G57: 45716 | H57: =+H56+E57-F57 -> 68 | J57: Transf. Eliana Condori Flores | L57: BNB | M57: =SUM(F55:F57) -> 55146
B58: 250904 | C58: 1880 | D58: 45910 | E58: 50640 | F58: 25000 | G58: 45911 | H58: =+H57+E58-F58 -> 25708 | J58: Faustino Condori Villegas | L58: BU
F59: 25640 | G59: 45911 | H59: =+H58+E59-F59 -> 68 | J59: Marco Antonio Condori Flores | M59: =SUM(F58:F59) -> 50640
H60: =+H59+E60-F60 -> 68
H61: =+H60+E61-F61 -> 68
H62: =+H61+E62-F62 -> 68
B63: TOTALES | E63: =SUM(E29:E62) -> 680123 | F63: =SUM(F29:F62) -> 680055
F64: =+E63-F63 -> 68

Sheet 4
B2: CUENTAS POR COBRAR
B3: GESTION 2023 - 2024
C5: CLIENTE: | D5: Juan Carlos Torrez Ayarde
C6: CELULAR: | D6: 78250301
C7: DESTINO: | D7: Tarija
C8: LINEA DE CREDITO: | D8: 80000
B10: NOTA DE VENTA | C10: NOTA DE ENTREGA | D10: FECHA DE DESPACHO | E10: MONTO P/COBRAR | F10: DEPÓSITO en Bs | G10: FECHA DE DEPÓSITO | H10: SALDO | I10: DIAS DE MORA | J10: OBSERVACION
B11: 220915 | D11: 44833 | E11: 22998.2 | H11: =+E11-F11 -> 22998.2
B12: 221005 | D12: 44851 | E12: 39971 | H12: =+H11+E12-F12 -> 62969.2
F13: 5000 | G13: 45603 | H13: =+H12+E13-F13 -> 57969.2 | I13: BNB | J13: CUIZA CAIGUARA ESPERANZA
F14: 5000 | G14: 45603 | H14: =+H13+E14-F14 -> 52969.2 | I14: BNB | J14: CUIZA CAIGUARA ESPERANZA
F15: 5000 | G15: 45608 | H15: =+H14+E15-F15 -> 47969.2 | I15: BNB | J15: CUIZA CAIGUARA ESPERANZA
F16: 10000 | G16: 45608 | H16: =+H15+E16-F16 -> 37969.2 | I16: BNB | J16: CUIZA CAIGUARA ESPERANZA
F17: 10000 | G17: 45609 | H17: =+H16+E17-F17 -> 27969.2 | I17: BNB | J17: CUIZA CAIGUARA ESPERANZA
F18: 15000 | G18: 45611 | H18: =+H17+E18-F18 -> 12969.2 | I18: BNB | J18: CUIZA CAIGUARA ESPERANZA
F19: 12969.2 | G19: - | H19: =+H18+E19-F19 -> 0 | J19: se perdono por cancelar bs50.000.-
H20: =+H19+E20-F20 -> 0
H21: =+H20+E21-F21 -> 0
H22: =+H21+E22-F22 -> 0
H23: =+H22+E23-F23 -> 0
B24: TOTALES | E24: =SUM(E11:E23) -> 62969.2 | F24: =SUM(F11:F23) -> 62969.2
F25: =+E24-F24 -> 0

Sheet 5
B2: CUENTAS POR COBRAR
B3: GESTION 2023 - 2024
C5: CLIENTE: | D5: Carol Alejandra Noya
C6: CELULAR:
C7: DESTINO: | D7: Tarija
C8: LINEA DE CREDITO: | D8: 80000
B10: NOTA DE VENTA | C10: NOTA DE ENTREGA | D10: FECHA DE DESPACHO | E10: MONTO P/COBRAR | F10: DEPÓSITO en Bs | G10: FECHA DE DEPÓSITO | H10: SALDO | I10: DIAS DE MORA | J10: OBSERVACION
B11: 210105 | D11: 44940 | E11: 41100.6 | H11: =+E11-F11 -> 41100.6
H12: =+H11+E12-F12 -> 41100.6
H13: =+H12+E13-F13 -> 41100.6
H14: =+H13+E14-F14 -> 41100.6
H15: =+H14+E15-F15 -> 41100.6
H16: =+H15+E16-F16 -> 41100.6
H17: =+H16+E17-F17 -> 41100.6
H18: =+H17+E18-F18 -> 41100.6
H19: =+H18+E19-F19 -> 41100.6
H20: =+H19+E20-F20 -> 41100.6
H21: =+H20+E21-F21 -> 41100.6
H22: =+H21+E22-F22 -> 41100.6
H23: =+H22+E23-F23 -> 41100.6
B24: TOTALES | E24: =SUM(E11:E23) -> 41100.6 | F24: =SUM(F11:F23) -> 0
F25: =+E24-F24 -> 41100.6

Sheet 6
B2: CUENTAS POR COBRAR
B3: GESTION 2023 - 2024
C5: CLIENTE: | D5: Luis Alberto Chipana Peña
C6: CELULAR: | D6: 79347671
C7: DESTINO: | D7: Cochabamba
C8: LINEA DE CREDITO:
B10: NOTA DE VENTA | C10: NOTA DE ENTREGA | D10: FECHA DE DESPACHO | E10: MONTO P/COBRAR | F10: DEPÓSITO en Bs | G10: FECHA DE DEPÓSITO | H10: SALDO | I10: DIAS DE MORA | J10: OBSERVACION
B11: 210902 | D11: 44440 | E11: 35550 | H11: =+E11-F11 -> 35550 | J11: Se comprometio a pagar cada mes Bs. 1000
H12: =+H11+E12-F12 -> 35550
H13: =+H12+E13-F13 -> 35550
H14: =+H13+E14-F14 -> 35550
H15: =+H14+E15-F15 -> 35550
H16: =+H15+E16-F16 -> 35550
H17: =+H16+E17-F17 -> 35550
H18: =+H17+E18-F18 -> 35550
H19: =+H18+E19-F19 -> 35550
H20: =+H19+E20-F20 -> 35550
H21: =+H20+E21-F21 -> 35550
B22: TOTALES | E22: =SUM(E11:E21) -> 35550 | F22: =SUM(F11:F21) -> 0

Sheet 7
B2: CUENTAS POR COBRAR
B3: GESTION 2023 - 2024
C5: CLIENTE: | D5: Franz Carlos Alanez Flores
C6: CELULAR:
C7: DESTINO: | D7: El Alto
C8: LINEA DE CREDITO:
B10: NOTA DE VENTA | C10: NOTA DE ENTREGA | D10: FECHA DE DESPACHO | E10: MONTO P/COBRAR | F10: DEPÓSITO en Bs | G10: FECHA DE DEPÓSITO | H10: SALDO | I10: DIAS DE MORA | J10: OBSERVACION
B11: 210118 | D11: 44953 | E11: 33500 | H11: =+E11-F11 -> 33500 | J11: En Proceso
H12: =+H11+E12-F12 -> 33500
H13: =+H12+E13-F13 -> 33500
H14: =+H13+E14-F14 -> 33500
H15: =+H14+E15-F15 -> 33500
H16: =+H15+E16-F16 -> 33500
H17: =+H16+E17-F17 -> 33500
H18: =+H17+E18-F18 -> 33500
H19: =+H18+E19-F19 -> 33500
H20: =+H19+E20-F20 -> 33500
H21: =+H20+E21-F21 -> 33500
E22: =SUM(E11:E21) -> 33500 | F22: =SUM(F11:F21) -> 0

Sheet 8
B2: CUENTAS POR COBRAR
B3: GESTION 2023 - 2024
C5: CLIENTE: | D5: Alvaro Choque Blanco
C6: CELULAR: | D6: 63568941
C7: DESTINO: | D7: ORURO
C8: LINEA DE CREDITO: | D8: 40000
B10: NOTA DE VENTA | C10: NOTA DE ENTREGA | D10: FECHA DE DESPACHO | E10: MONTO P/COBRAR | F10: DEPÓSITO en Bs | G10: FECHA DE DEPÓSITO | H10: SALDO | I10: DIAS DE MORA | J10: OBSERVACION
B11: 230205 | D11: 44966 | E11: 32664.2 | F11: 2800 | G11: 45142 | H11: =+E11-F11 -> 29864.2
F12: 10000 | G12: 45166 | H12: =+H11+E12-F12 -> 19864.2
F13: 19864.2 | G13: 45224 | H13: =+H12+E13-F13 -> 0
H14: =+H13+E14-F14 -> 0
H15: =+H14+E15-F15 -> 0
H16: =+H15+E16-F16 -> 0
H17: =+H16+E17-F17 -> 0
H18: =+H17+E18-F18 -> 0
H19: =+H18+E19-F19 -> 0
B20: TOTALES | E20: =SUM(E11:E19) -> 32664.2 | F20: =SUM(F11:F19) -> 32664.2
F21: =+E20-F20 -> 0

Sheet 9
B2: CUENTAS POR COBRAR
B3: GESTION 2023 - 2024
C5: CLIENTE: | D5: Andrés Miguel Paniagua
C6: CELULAR: | D6: 77145507
C7: DESTINO: | D7: ORURO
C8: LINEA DE CREDITO: | D8: 60000
B10: NOTA DE VENTA | C10: NOTA DE ENTREGA | D10: FECHA DE DESPACHO | E10: MONTO P/COBRAR | F10: DEPÓSITO en Bs | G10: FECHA DE DEPÓSITO | H10: SALDO | I10: DIAS DE MORA | J10: OBSERVACION
B11: 220916 | D11: 44834 | E11: 24351.9 | H11: =+E11-F11 -> 24351.9
H12: =+H11+E12-F12 -> 24351.9
H13: =+H12+E13-F13 -> 24351.9
H14: =+H13+E14-F14 -> 24351.9
H15: =+H14+E15-F15 -> 24351.9
H16: =+H15+E16-F16 -> 24351.9
H17: =+H16+E17-F17 -> 24351.9
H18: =+H17+E18-F18 -> 24351.9
H19: =+H18+E19-F19 -> 24351.9
B20: TOTALES | E20: =SUM(E11:E19) -> 24351.9 | F20: =SUM(F11:F19) -> 0
F21: =+E20-F20 -> 24351.9

Sheet 10
B2: CUENTAS POR COBRAR
B3: GESTION 2023 - 2024
C5: CLIENTE: | D5: Alex Rolando Fernandez H.
C6: CELULAR: | D6: 68320858
C7: DESTINO: | D7: Oruro
C8: LINEA DE CREDITO:
B10: NOTA DE VENTA | C10: NOTA DE ENTREGA | D10: FECHA DE DESPACHO | E10: MONTO P/COBRAR | F10: DEPÓSITO en Bs | G10: FECHA DE DEPÓSITO | H10: SALDO | I10: DIAS DE MORA | J10: OBSERVACION
B11: 211215 | D11: 44545 | E11: 23293 | H11: =+E11-F11 -> 23293 | J11: Se comprometio a pagar cada mes Bs. 5000
H12: =+H11+E12-F12 -> 23293
H13: =+H12+E13-F13 -> 23293
H14: =+H13+E14-F14 -> 23293
H15: =+H14+E15-F15 -> 23293
H16: =+H15+E16-F16 -> 23293
H17: =+H16+E17-F17 -> 23293
H18: =+H17+E18-F18 -> 23293
H19: =+H18+E19-F19 -> 23293
H20: =+H19+E20-F20 -> 23293
H21: =+H20+E21-F21 -> 23293
B22: TOTALES | E22: =SUM(E11:E21) -> 23293 | F22: =SUM(F11:F21) -> 0

Sheet 11
B2: CUENTAS POR COBRAR
B3: GESTION 2023 - 2024
C5: CLIENTE: | D5: Franklin Ever Viveros
C6: CELULAR: | D6: 68374333
C7: DESTINO: | D7: POTOSI
C8: LINEA DE CREDITO: | D8: 60000
B10: NOTA DE VENTA | C10: NOTA DE ENTREGA | D10: FECHA DE DESPACHO | E10: MONTO P/COBRAR | F10: DEPÓSITO en Bs | G10: FECHA DE DEPÓSITO | H10: SALDO | I10: DIAS DE MORA | J10: OBSERVACION
B11: 220913 | D11: 44832 | E11: 11132.55 | F11: 0 | G11: - | H11: =+E11-F11 -> 11132.55
H12: =+H11+E12-F12 -> 11132.55
H13: =+H12+E13-F13 -> 11132.55
H14: =+H13+E14-F14 -> 11132.55
H15: =+H14+E15-F15 -> 11132.55
H16: =+H15+E16-F16 -> 11132.55
H17: =+H16+E17-F17 -> 11132.55
H18: =+H17+E18-F18 -> 11132.55
H19: =+H18+E19-F19 -> 11132.55
H20: =+H19+E20-F20 -> 11132.55
H21: =+H20+E21-F21 -> 11132.55
H22: =+H21+E22-F22 -> 11132.55
H23: =+H22+E23-F23 -> 11132.55
B24: TOTALES | E24: =SUM(E11:E23) -> 11132.55 | F24: =SUM(F11:F23) -> 0
F25: =+E24-F24 -> 11132.55

Sheet 12
B2: CUENTAS POR COBRAR
B3: GESTION 2023 - 2024
C5: CLIENTE: | D5: Teofilo Ibañez Soliz
C6: CELULAR: | D6: 71861156
C7: DESTINO: | D7: Tarija
C8: LINEA DE CREDITO:
B10: NOTA DE VENTA | C10: NOTA DE ENTREGA | D10: FECHA DE DESPACHO | E10: MONTO P/COBRAR | F10: DEPÓSITO en Bs | G10: FECHA DE DEPÓSITO | H10: SALDO | I10: DIAS DE MORA | J10: OBSERVACION
B11: 210518 | D11: 44334 | E11: 7220.5 | H11: =+E11-F11 -> 7220.5 | J11: En Proceso
H12: =+H11+E12-F12 -> 7220.5
H13: =+H12+E13-F13 -> 7220.5
H14: =+H13+E14-F14 -> 7220.5
H15: =+H14+E15-F15 -> 7220.5
H16: =+H15+E16-F16 -> 7220.5
H17: =+H16+E17-F17 -> 7220.5
H18: =+H17+E18-F18 -> 7220.5
H19: =+H18+E19-F19 -> 7220.5
H20: =+H19+E20-F20 -> 7220.5
H21: =+H20+E21-F21 -> 7220.5
E22: =SUM(E11:E21) -> 7220.5 | F22: =SUM(F11:F21) -> 0

Sheet 13
B2: CUENTAS POR COBRAR
B3: GESTION 2023 - 2024
C5: CLIENTE: | D5: Elsa Romay Padilla
C6: CELULAR: | D6: 74282999
C7: DESTINO: | D7: UYUNI
C8: LINEA DE CREDITO: | D8: 30000
B10: NOTA DE VENTA | C10: NOTA DE ENTREGA | D10: FECHA DE DESPACHO | E10: MONTO P/COBRAR | F10: DEPÓSITO en Bs | G10: FECHA DE DEPÓSITO | H10: SALDO | I10: DIAS DE MORA | J10: OBSERVACION
B11: 220507 | D11: 44688 | E11: 6470 | F11: 0 | G11: - | H11: =+E11-F11 -> 6470
B12: 250112 | C12: 1538 | D12: 45666 | E12: 30305 | F12: 36775 | G12: 45654 | H12: =+H11+E12-F12 -> 0 | J12: Elsa Romay Padilla | K12: BU
H13: =+H12+E13-F13 -> 0
H14: =+H13+E14-F14 -> 0
H15: =+H14+E15-F15 -> 0
H16: =+H15+E16-F16 -> 0
H17: =+H16+E17-F17 -> 0
H18: =+H17+E18-F18 -> 0
B19: TOTALES | E19: =SUM(E11:E18) -> 36775 | F19: =SUM(F11:F18) -> 36775
F20: =+E19-F19 -> 0

Sheet 14
B2: CUENTAS POR COBRAR
B3: GESTION 2023 - 2024
C5: CLIENTE: | D5: Jorge Luis Vedia Arancibia
C6: CELULAR: | D6: 73476601
C7: DESTINO: | D7: Chuquisaca - Provincias
C8: LINEA DE CREDITO:
B10: NOTA DE VENTA | C10: NOTA DE ENTREGA | D10: FECHA DE DESPACHO | E10: MONTO P/COBRAR | F10: DEPÓSITO en Bs | G10: FECHA DE DEPÓSITO | H10: SALDO | I10: DIAS DE MORA | J10: OBSERVACION
B11: 210630 | D11: 44376 | E11: 3974.5 | H11: =+E11-F11 -> 3974.5 | J11: En Proceso
H12: =+H11+E12-F12 -> 3974.5
H13: =+H12+E13-F13 -> 3974.5
H14: =+H13+E14-F14 -> 3974.5
H15: =+H14+E15-F15 -> 3974.5
H16: =+H15+E16-F16 -> 3974.5
H17: =+H16+E17-F17 -> 3974.5
H18: =+H17+E18-F18 -> 3974.5
H19: =+H18+E19-F19 -> 3974.5
H20: =+H19+E20-F20 -> 3974.5
H21: =+H20+E21-F21 -> 3974.5
E22: =SUM(E11:E21) -> 3974.5 | F22: =SUM(F11:F21) -> 0

Sheet 15
B2: CUENTAS POR COBRAR
B3: GESTION 2023 - 2024
C5: CLIENTE: | D5: Celina Cruz Mendez
C6: CELULAR:
C7: DESTINO: | D7: Chuquisaca - Provincias
C8: LINEA DE CREDITO:
B10: NOTA DE VENTA | C10: NOTA DE ENTREGA | D10: FECHA DE DESPACHO | E10: MONTO P/COBRAR | F10: DEPÓSITO en Bs | G10: FECHA DE DEPÓSITO | H10: SALDO | I10: DIAS DE MORA | J10: OBSERVACION
B11: 210504 | D11: 44323 | E11: 3220 | H11: =+E11-F11 -> 3220 | J11: En Proceso
H12: =+H11+E12-F12 -> 3220
H13: =+H12+E13-F13 -> 3220
H14: =+H13+E14-F14 -> 3220
H15: =+H14+E15-F15 -> 3220
H16: =+H15+E16-F16 -> 3220
H17: =+H16+E17-F17 -> 3220
H18: =+H17+E18-F18 -> 3220
H19: =+H18+E19-F19 -> 3220
H20: =+H19+E20-F20 -> 3220
H21: =+H20+E21-F21 -> 3220
E22: =SUM(E11:E21) -> 3220 | F22: =SUM(F11:F21) -> 0

Sheet RECAU. ABRIL 2025
A3: CUENTAS POR COBRAR A CLIENTES
A4: GESTION 2023 - 2024
A5: MARZO - 2025
A6: Nº | B6: DISTRIBUIDOR | C6: DEPARTAMENTO | AI6: TOTAL MES
D7: 1 | E7: 2 | F7: 3 | G7: 4 | H7: Semana 1 | I7: 6 | J7: 7 | K7: 8 | L7: 9 | M7: 10 | N7: 11 | O7: Semana 2 | P7: 13 | Q7: 14 | R7: 15 | S7: 16 | T7: 17 | U7: 18 | V7: Semana 3 | W7: 20 | X7: 21 | Y7: 22 | Z7: 23 | AA7: 24 | AB7: 25 | AC7: Semana 4 | AD7: 27 | AE7: 28 | AF7: 29 | AG7: 28 | AH7: Semana 4
A8: 1 | B8: Fabricio Tapia Castedo | C8: Cochabamba | H8: =SUM(D8:G8) -> 0 | O8: =SUM(I8:N8) -> 0 | V8: =SUM(P8:U8) -> 0 | AC8: =SUM(W8:AB8) -> 0 | AH8: =SUM(AD8:AG8) -> 0 | AI8: =+H8+O8+V8+AH8 -> 0
A9: =1+A8 -> 2 | B9: Edwin Fernandez Chirinos | C9: El Alto | H9: =SUM(D9:G9) -> 0 | O9: =SUM(I9:N9) -> 0 | V9: =SUM(P9:U9) -> 0 | AC9: =SUM(W9:AB9) -> 0 | AH9: =SUM(AD9:AG9) -> 0 | AI9: =+H9+O9+V9+AH9 -> 0
A10: =1+A9 -> 3 | B10: Javier Caceres | C10: Cochabamba | H10: =SUM(D10:G10) -> 0 | O10: =SUM(I10:N10) -> 0 | V10: =SUM(P10:U10) -> 0 | AC10: =SUM(W10:AB10) -> 0 | AH10: =SUM(AD10:AG10) -> 0 | AI10: =+H10+O10+V10+AH10 -> 0
A11: =1+A10 -> 4 | B11: Juan Carlos Torrez Ayarde | C11: Tarija | H11: =SUM(D11:G11) -> 0 | O11: =SUM(I11:N11) -> 0 | V11: =SUM(P11:U11) -> 0 | AC11: =SUM(W11:AB11) -> 0 | AH11: =SUM(AD11:AG11) -> 0 | AI11: =+H11+O11+V11+AH11 -> 0
A12: =1+A11 -> 5 | B12: Carol Alejandra Noya | C12: Tarija | H12: =SUM(D12:G12) -> 0 | O12: =SUM(I12:N12) -> 0 | V12: =SUM(P12:U12) -> 0 | AC12: =SUM(W12:AB12) -> 0 | AH12: =SUM(AD12:AG12) -> 0 | AI12: =+H12+O12+V12+AH12 -> 0
A13: =1+A12 -> 6 | B13: Luis Alberto Chipana Peña | C13: Cochabamba | H13: =SUM(D13:G13) -> 0 | O13: =SUM(I13:N13) -> 0 | V13: =SUM(P13:U13) -> 0 | AC13: =SUM(W13:AB13) -> 0 | AH13: =SUM(AD13:AG13) -> 0 | AI13: =+H13+O13+V13+AH13 -> 0
A14: =1+A13 -> 7 | B14: Franz Carlos Alanez Flores | C14: El Alto | H14: =SUM(D14:G14) -> 0 | O14: =SUM(I14:N14) -> 0 | V14: =SUM(P14:U14) -> 0 | AC14: =SUM(W14:AB14) -> 0 | AH14: =SUM(AD14:AG14) -> 0 | AI14: =+H14+O14+V14+AH14 -> 0
A15: =1+A14 -> 8 | B15: Andrés Miguel Paniagua | C15: Oruro | H15: =SUM(D15:G15) -> 0 | O15: =SUM(I15:N15) -> 0 | V15: =SUM(P15:U15) -> 0 | AC15: =SUM(W15:AB15) -> 0 | AH15: =SUM(AD15:AG15) -> 0 | AI15: =+H15+O15+V15+AH15 -> 0
A16: =1+A15 -> 9 | B16: Alex Rolando Fernandez H. | C16: Oruro | H16: =SUM(D16:G16) -> 0 | O16: =SUM(I16:N16) -> 0 | V16: =SUM(P16:U16) -> 0 | AC16: =SUM(W16:AB16) -> 0 | AH16: =SUM(AD16:AG16) -> 0 | AI16: =+H16+O16+V16+AH16 -> 0
A17: =1+A16 -> 10 | B17: Franklin Ever Viveros | C17: Potosí | H17: =SUM(D17:G17) -> 0 | O17: =SUM(I17:N17) -> 0 | V17: =SUM(P17:U17) -> 0 | AC17: =SUM(W17:AB17) -> 0 | AH17: =SUM(AD17:AG17) -> 0 | AI17: =+H17+O17+V17+AH17 -> 0
A18: =1+A17 -> 11 | B18: Teofilo Ibañez Soliz | C18: Tarija | H18: =SUM(D18:G18) -> 0 | O18: =SUM(I18:N18) -> 0 | V18: =SUM(P18:U18) -> 0 | AC18: =SUM(W18:AB18) -> 0 | AH18: =SUM(AD18:AG18) -> 0 | AI18: =+H18+O18+V18+AH18 -> 0
A19: =1+A18 -> 12 | B19: Elsa Romay Padilla | C19: Uyuni | H19: =SUM(D19:G19) -> 0 | O19: =SUM(I19:N19) -> 0 | V19: =SUM(P19:U19) -> 0 | AC19: =SUM(W19:AB19) -> 0 | AH19: =SUM(AD19:AG19) -> 0 | AI19: =+H19+O19+V19+AH19 -> 0
A20: =1+A19 -> 13 | B20: Jorge Luis Vedia Arancibia | C20: Chuquisaca - Prov | H20: =SUM(D20:G20) -> 0 | O20: =SUM(I20:N20) -> 0 | V20: =SUM(P20:U20) -> 0 | AC20: =SUM(W20:AB20) -> 0 | AH20: =SUM(AD20:AG20) -> 0 | AI20: =+H20+O20+V20+AH20 -> 0
A21: =1+A20 -> 14 | B21: Celina Cruz Mendez | C21: Chuquisaca - Prov | H21: =SUM(D21:G21) -> 0 | O21: =SUM(I21:N21) -> 0 | V21: =SUM(P21:U21) -> 0 | AC21: =SUM(W21:AB21) -> 0 | AH21: =SUM(AD21:AG21) -> 0 | AI21: =+H21+O21+V21+AH21 -> 0
A22: =1+A28 -> 20 | B22: Marlene Paicho | C22: Ruta Colquechaca | H22: =SUM(D22:G22) -> 0 | O22: =SUM(I22:N22) -> 0 | V22: =SUM(P22:U22) -> 0 | AC22: =SUM(W22:AB22) -> 0 | AH22: =SUM(AD22:AG22) -> 0 | AI22: =H22+O22+V22+AH22 -> 0
A23: TOTAL CLIENTES MOROSOS | G23: =SUM(G8:G22) -> 0 | H23: =SUM(D23:G23) -> 0 | I23: =SUM(I8:I22) -> 0 | J23: =SUM(J8:J22) -> 0 | K23: =SUM(K8:K22) -> 0 | L23: =SUM(L8:L22) -> 0 | M23: =SUM(M8:M22) -> 0 | N23: =SUM(N8:N22) -> 0 | O23: =SUM(I23:N23) -> 0 | P23: =SUM(P8:P22) -> 0 | Q23: =SUM(Q8:Q22) -> 0 | R23: =SUM(R8:R22) -> 0 | S23: =SUM(S8:S22) -> 0 | T23: =SUM(T8:T22) -> 0 | U23: =SUM(U8:U22) -> 0 | V23: =SUM(P23:U23) -> 0 | W23: =SUM(W8:W22) -> 0 | X23: =SUM(X8:X22) -> 0 | Y23: =SUM(Y8:Y22) -> 0 | Z23: =SUM(Z8:Z22) -> 0 | AA23: =SUM(AA8:AA22) -> 0 | AB23: =SUM(AB8:AB22) -> 0 | AC23: =SUM(W23:AB23) -> 0 | AD23: =SUM(AD8:AD22) -> 0 | AG23: =SUM(AG8:AG22) -> 0 | AH23: =SUM(AD23:AG23) -> 0 | AI23: =SUM(AI8:AI22) -> 0
A24: =1+A21 -> 15 | B24: EMAPA NACIONAL | C24: NACIONAL | H24: =SUM(D24:G24) -> 0 | O24: =SUM(I24:N24) -> 0 | V24: =SUM(P24:U24) -> 0 | AC24: =SUM(W24:AB24) -> 0 | AH24: =SUM(AD24:AG24) -> 0 | AI24: =H24+O24+V24+AC24+AH24 -> 0
A25: =1+A24 -> 16 | B25: Gustavo Tellez Ugarte | C25: Santa Cruz | H25: =SUM(D25:G25) -> 0 | O25: =SUM(I25:N25) -> 0 | V25: =SUM(P25:U25) -> 0 | AC25: =SUM(W25:AB25) -> 0 | AH25: =SUM(AD25:AG25) -> 0 | AI25: =H25+O25+V25+AC25+AH25 -> 0
A26: =1+A25 -> 17 | B26: Cristhian Murillo | C26: Sucre | H26: =SUM(D26:G26) -> 0 | O26: =SUM(I26:N26) -> 0 | V26: =SUM(P26:U26) -> 0 | AC26: =SUM(W26:AB26) -> 0 | AG26: 241000 | AH26: =SUM(AD26:AG26) -> 241000 | AI26: =H26+O26+V26+AC26+AH26 -> 241000
A27: =1+A26 -> 18 | B27: Sebastian Miranda | C27: Oruro | H27: =SUM(D27:G27) -> 0 | O27: =SUM(I27:N27) -> 0 | V27: =SUM(P27:U27) -> 0 | AC27: =SUM(W27:AB27) -> 0 | AH27: =SUM(AD27:AG27) -> 0 | AI27: =H27+O27+V27+AC27+AH27 -> 0
A28: =1+A27 -> 19 | B28: Norha Choque Talavera | C28: Potosí | H28: =SUM(D28:G28) -> 0 | O28: =SUM(I28:N28) -> 0 | V28: =SUM(P28:U28) -> 0 | AC28: =SUM(W28:AB28) -> 0 | AH28: =SUM(AD28:AG28) -> 0 | AI28: =H28+O28+V28+AC28+AH28 -> 0
A29: =1+A28 -> 20 | B29: Orlando Aldunate M. | C29: Tarija | H29: =SUM(D29:G29) -> 0 | O29: =SUM(I29:N29) -> 0 | V29: =SUM(P29:U29) -> 0 | AC29: =SUM(W29:AB29) -> 0 | AG29: 128559.5 | AH29: =SUM(AD29:AG29) -> 128559.5 | AI29: =H29+O29+V29+AC29+AH29 -> 128559.5
A30: =1+A29 -> 21 | B30: Fausto Condori | C30: Cochabamba | H30: =SUM(D30:G30) -> 0 | O30: =SUM(I30:N30) -> 0 | V30: =SUM(P30:U30) -> 0 | AC30: =SUM(W30:AB30) -> 0 | AH30: =SUM(AD30:AG30) -> 0 | AI30: =H30+O30+V30+AC30+AH30 -> 0
A31: =1+A30 -> 22 | B31: Flora Yapuchura | C31: La Paz | H31: =SUM(D31:G31) -> 0 | O31: =SUM(I31:N31) -> 0 | V31: =SUM(P31:U31) -> 0 | AC31: =SUM(W31:AB31) -> 0 | AH31: =SUM(AD31:AG31) -> 0 | AI31: =H31+O31+V31+AC31+AH31 -> 0
A32: =1+A31 -> 23 | B32: Willy Quispe | C32: El Alto | H32: =SUM(D32:G32) -> 0 | O32: =SUM(I32:N32) -> 0 | V32: =SUM(P32:U32) -> 0 | AC32: =SUM(W32:AB32) -> 0 | AH32: =SUM(AD32:AG32) -> 0 | AI32: =H32+O32+V32+AC32+AH32 -> 0
A33: =1+A32 -> 24 | B33: Andrez Lopez | C33: Potosí | H33: =SUM(D33:G33) -> 0 | O33: =SUM(I33:N33) -> 0 | V33: =SUM(P33:U33) -> 0 | AC33: =SUM(W33:AB33) -> 0 | AH33: =SUM(AD33:AG33) -> 0 | AI33: =H33+O33+V33+AC33+AH33 -> 0
A34: =1+A33 -> 25 | B34: Miguel Angel Mora | C34: Potosí | H34: =SUM(D34:G34) -> 0 | O34: =SUM(I34:N34) -> 0 | V34: =SUM(P34:U34) -> 0 | AC34: =SUM(W34:AB34) -> 0 | AH34: =SUM(AD34:AG34) -> 0 | AI34: =H34+O34+V34+AC34+AH34 -> 0
A35: =1+A34 -> 26 | B35: GAMS Desarrollo Productivo | C35: Sucre | H35: =SUM(D35:G35) -> 0 | O35: =SUM(I35:N35) -> 0 | V35: =SUM(P35:U35) -> 0 | AC35: =SUM(W35:AB35) -> 0 | AH35: =SUM(AD35:AG35) -> 0 | AI35: =H35+O35+V35+AC35+AH35 -> 0
A36: =1+A35 -> 27 | B36: GAMS Direccion Administrativa | C36: Sucre | H36: =SUM(D36:G36) -> 0 | O36: =SUM(I36:N36) -> 0 | V36: =SUM(P36:U36) -> 0 | AC36: =SUM(W36:AB36) -> 0 | AH36: =SUM(AD36:AG36) -> 0 | AI36: =H36+O36+V36+AC36+AH36 -> 0
A37: =1+A36 -> 28 | B37: Carmen Cruz | C37: Potosí | H37: =SUM(D37:G37) -> 0 | O37: =SUM(I37:N37) -> 0 | V37: =SUM(P37:U37) -> 0 | AC37: =SUM(W37:AB37) -> 0 | AG37: 77074 | AH37: =SUM(AD37:AG37) -> 77074 | AI37: =H37+O37+V37+AC37+AH37 -> 77074
A38: =1+A37 -> 29 | B38: Judith | C38: Cochabamba | H38: =SUM(D38:G38) -> 0 | O38: =SUM(I38:N38) -> 0 | V38: =SUM(P38:U38) -> 0 | AC38: =SUM(W38:AB38) -> 0 | AH38: =SUM(AD38:AG38) -> 0 | AI38: =H38+O38+V38+AC38+AH38 -> 0
A39: =1+A38 -> 30 | B39: Kevin | C39: Oruro | H39: =SUM(D39:G39) -> 0 | O39: =SUM(I39:N39) -> 0 | V39: =SUM(P39:U39) -> 0 | AC39: =SUM(W39:AB39) -> 0 | AH39: =SUM(AD39:AG39) -> 0 | AI39: =H39+O39+V39+AC39+AH39 -> 0
A40: =1+A39 -> 31 | B40: Jorge Saavedra | C40: Tupiza | H40: =SUM(D40:G40) -> 0 | O40: =SUM(I40:N40) -> 0 | V40: =SUM(P40:U40) -> 0 | AC40: =SUM(W40:AB40) -> 0 | AH40: =SUM(AD40:AG40) -> 0 | AI40: =H40+O40+V40+AC40+AH40 -> 0
A41: =1+A40 -> 32 | B41: Jenrry | C41: Chile | H41: =SUM(D41:G41) -> 0 | O41: =SUM(I41:N41) -> 0 | V41: =SUM(P41:U41) -> 0 | AC41: =SUM(W41:AB41) -> 0 | AG41: 292565 | AH41: =SUM(AD41:AG41) -> 292565 | AI41: =H41+O41+V41+AC41+AH41 -> 292565
A42: =1+A41 -> 33 | B42: Eddy | C42: Chile | H42: =SUM(D42:G42) -> 0 | O42: =SUM(I42:N42) -> 0 | V42: =SUM(P42:U42) -> 0 | AC42: =SUM(W42:AB42) -> 0 | AH42: =SUM(AD42:AG42) -> 0 | AI42: =H42+O42+V42+AC42+AH42 -> 0
A43: =1+A42 -> 34 | B43: Rene Cahuana | C43: La Paz | H43: =SUM(D43:G43) -> 0 | O43: =SUM(I43:N43) -> 0 | V43: =SUM(P43:U43) -> 0 | AC43: =SUM(W43:AB43) -> 0 | AG43: 119492 | AH43: =SUM(AD43:AG43) -> 119492 | AI43: =H43+O43+V43+AC43+AH43 -> 119492
A44: =1+A43 -> 35 | B44: Ines Aguirre | C44: Provincias Villazon | H44: =SUM(D44:G44) -> 0 | O44: =SUM(I44:N44) -> 0 | V44: =SUM(P44:U44) -> 0 | AC44: =SUM(W44:AB44) -> 0 | AH44: =SUM(AD44:AG44) -> 0 | AI44: =H44+O44+V44+AC44+AH44 -> 0
A45: =1+A44 -> 36 | B45: Yobana Llanos Cruz | C45: Ruta Chapare | H45: =SUM(D45:G45) -> 0 | O45: =SUM(I45:N45) -> 0 | V45: =SUM(P45:U45) -> 0 | AC45: =SUM(W45:AB45) -> 0 | AH45: =SUM(AD45:AG45) -> 0 | AI45: =H45+O45+V45+AC45+AH45 -> 0
A46: =1+A45 -> 37 | B46: Hernan Colque Cruz | C46: Pisiga | H46: =SUM(D46:G46) -> 0 | O46: =SUM(I46:N46) -> 0 | V46: =SUM(P46:U46) -> 0 | AC46: =SUM(W46:AB46) -> 0 | AH46: =SUM(AD46:AG46) -> 0 | AI46: =H46+O46+V46+AC46+AH46 -> 0
A47: =1+A46 -> 38 | B47: Roxana Yanet Castrillo Vasco | C47: Bermejo | H47: =SUM(D47:G47) -> 0 | O47: =SUM(I47:N47) -> 0 | V47: =SUM(P47:U47) -> 0 | AC47: =SUM(W47:AB47) -> 0 | AH47: =SUM(AD47:AG47) -> 0 | AI47: =H47+O47+V47+AC47+AH47 -> 0
A48: =1+A47 -> 39 | B48: Ismael Marca | C48: Uyuni | H48: =SUM(D48:G48) -> 0 | O48: =SUM(I48:N48) -> 0 | V48: =SUM(P48:U48) -> 0 | AC48: =SUM(W48:AB48) -> 0 | AH48: =SUM(AD48:AG48) -> 0 | AI48: =H48+O48+V48+AC48+AH48 -> 0
A49: =1+A48 -> 40 | B49: Freddy Alcocer Mollo | C49: Oruro | H49: =SUM(D49:G49) -> 0 | AG49: 18522 | AH49: =SUM(AD49:AG49) -> 18522 | AI49: =H49+O49+V49+AC49+AH49 -> 18522
A50: =1+A49 -> 41 | B50: Katerine Soria Galvarro | C50: Oruro Provincia | H50: =SUM(D50:G50) -> 0 | AG50: 89150 | AH50: =SUM(AD50:AG50) -> 89150 | AI50: =H50+O50+V50+AC50+AH50 -> 89150
A51: =1+A50 -> 42 | B51: Nilda | C51: CBBA Provincia | H51: =SUM(D51:G51) -> 0 | AH51: =SUM(AD51:AG51) -> 0 | AI51: =H51+O51+V51+AC51+AH51 -> 0
A52: =1+A51 -> 43 | B52: Divar Aranibar Plata | C52: Oruro | AH52: =SUM(AD52:AG52) -> 0 | AI52: =H52+O52+V52+AC52+AH52 -> 0
A53: =1+A52 -> 44 | B53: Ruth Gabriela | C53: Pando | AH53: =SUM(AD53:AG53) -> 0 | AI53: =H53+O53+V53+AC53+AH53 -> 0
A54: =1+A53 -> 45 | B54: Sergio Romero | C54: Sucre | AH54: =SUM(AD54:AG54) -> 0 | AI54: =H54+O54+V54+AC54+AH54 -> 0
A55: =1+A54 -> 46 | B55: Jorge Cruz | C55: Chile | H55: =SUM(D55:G55) -> 0 | O55: =SUM(I55:N55) -> 0 | V55: =SUM(P55:U55) -> 0 | AC55: =SUM(W55:AB55) -> 0 | AH55: =SUM(AD55:AG55) -> 0 | AI55: =H55+O55+V55+AC55+AH55 -> 0
A56: =1+A55 -> 47 | B56: Javier Mercado | C56: El Alto | AH56: =SUM(AD56:AG56) -> 0 | AI56: =H56+O56+V56+AC56+AH56 -> 0
A57: =1+A56 -> 48 | B57: Yaneth Miriam Toroya Gabriel | C57: Oruro | AG57: 119170 | AH57: =SUM(AD57:AG57) -> 119170 | AI57: =H57+O57+V57+AC57+AH57 -> 119170
A58: =1+A57 -> 49 | B58: Patricia Romero | C58: Oruro | AH58: =SUM(AD58:AG58) -> 0 | AI58: =H58+O58+V58+AC58+AH58 -> 0
A59: =1+A58 -> 50 | B59: Miguel Calle | C59: Villazon | AH59: =SUM(AD59:AG59) -> 0 | AI59: =H59+O59+V59+AC59+AH59 -> 0
A60: =1+A59 -> 51 | B60: Paul Yamani | C60: Cochabamba | AG60: 48500 | AH60: =SUM(AD60:AG60) -> 48500 | AI60: =H60+O60+V60+AC60+AH60 -> 48500
A61: =1+A60 -> 52 | B61: Silvia Gomez | C61: Huanuni | H61: =SUM(D61:G61) -> 0 | O61: =SUM(I61:N61) -> 0 | V61: =SUM(P61:U61) -> 0 | AC61: =SUM(W61:AB61) -> 0 | AH61: =SUM(AD61:AG61) -> 0 | AI61: =H61+O61+V61+AC61+AH61 -> 0
A62: =1+A61 -> 53 | B62: Venta colillas | C62: Sucre | H62: =SUM(D62:G62) -> 0 | O62: =SUM(I62:N62) -> 0 | V62: =SUM(P62:U62) -> 0 | AC62: =SUM(W62:AB62) -> 0 | AG62: 13318.2 | AH62: =SUM(AD62:AG62) -> 13318.2 | AI62: =H62+O62+V62+AC62+AH62 -> 13318.2
A63: =1+A62 -> 54 | B63: Ventas en FABRICA | C63: Sucre | H63: =SUM(D63:G63) -> 0 | O63: =SUM(I63:N63) -> 0 | V63: =SUM(P63:U63) -> 0 | AC63: =SUM(W63:AB63) -> 0 | AG63: 21459 | AH63: =SUM(AD63:AG63) -> 21459 | AI63: =H63+O63+V63+AC63+AH63 -> 21459
A64: TOTALE CLIENTES ACTIVOS | G64: =SUM(G24:G63) -> 0 | H64: =SUM(D64:G64) -> 0 | I64: =SUM(I24:I63) -> 0 | J64: =SUM(J24:J63) -> 0 | K64: =SUM(K24:K63) -> 0 | L64: =SUM(L24:L63) -> 0 | M64: =SUM(M24:M63) -> 0 | N64: =SUM(N24:N63) -> 0 | O64: =SUM(I64:N64) -> 0 | P64: =SUM(P24:P63) -> 0 | Q64: =SUM(Q24:Q63) -> 0 | R64: =SUM(R24:R63) -> 0 | S64: =SUM(S24:S63) -> 0 | T64: =SUM(T24:T63) -> 0 | U64: =SUM(U24:U63) -> 0 | V64: =SUM(P64:U64) -> 0 | W64: =SUM(W24:W63) -> 0 | X64: =SUM(X24:X63) -> 0 | Y64: =SUM(Y24:Y63) -> 0 | Z64: =SUM(Z24:Z63) -> 0 | AA64: =SUM(AA24:AA63) -> 0 | AB64: =SUM(AB24:AB63) -> 0 | AC64: =SUM(W64:AB64) -> 0 | AD64: =SUM(AD24:AD63) -> 0 | AE64: =SUM(AE24:AE63) -> 0 | AF64: =SUM(AF24:AF63) -> 0 | AG64: =SUM(AG24:AG63) -> 1168809.7 | AH64: =SUM(AD64:AG64) -> 1168809.7 | AI64: =SUM(AI24:AI63) -> 1168809.7
A65: TOTALE CLIENTES | D65: =+D23+D64 -> 0 | E65: =+E23+E64 -> 0 | F65: =+F23+F64 -> 0 | G65: =+G23+G64 -> 0 | H65: =SUM(D65:G65) -> 0 | I65: =+I23+I64 -> 0 | J65: =+J23+J64 -> 0 | K65: =+K23+K64 -> 0 | L65: =+L23+L64 -> 0 | M65: =+M23+M64 -> 0 | N65: =+N23+N64 -> 0 | O65: =SUM(I65:N65) -> 0 | P65: =+P23+P64 -> 0 | Q65: =+Q23+Q64 -> 0 | R65: =+R23+R64 -> 0 | S65: =+S23+S64 -> 0 | T65: =+T23+T64 -> 0 | U65: =+U23+U64 -> 0 | V65: =SUM(P65:U65) -> 0 | W65: =+W23+W64 -> 0 | X65: =+X23+X64 -> 0 | Y65: =+Y23+Y64 -> 0 | Z65: =+Z23+Z64 -> 0 | AA65: =+AA23+AA64 -> 0 | AB65: =+AB23+AB64 -> 0 | AC65: =SUM(W65:AB65) -> 0 | AD65: =+AD23+AD64 -> 0 | AH65: =SUM(AD65:AG65) -> 0 | AI65: =SUM(AI64,AI23) -> 1168809.7

Sheet RECAU. MAYO 2025
A3: CUENTAS POR COBRAR A CLIENTES
A4: GESTION 2023 - 2024
A5: MAYO - 2025
A6: Nº | B6: DISTRIBUIDOR | C6: DEPARTAMENTO | AI6: TOTAL MES
D7: 1 | E7: 2 | F7: 3 | G7: 4 | H7: Semana 1 | I7: 6 | J7: 7 | K7: 8 | L7: 9 | M7: 10 | N7: 11 | O7: Semana 2 | P7: 13 | Q7: 14 | R7: 15 | S7: 16 | T7: 17 | U7: 18 | V7: Semana 3 | W7: 20 | X7: 21 | Y7: 22 | Z7: 23 | AA7: 24 | AB7: 25 | AC7: Semana 4 | AD7: 27 | AE7: 28 | AF7: 29 | AG7: 28 | AH7: Semana 4
A8: 1 | B8: Fabricio Tapia Castedo | C8: Cochabamba | H8: =SUM(D8:G8) -> 0 | O8: =SUM(I8:N8) -> 0 | V8: =SUM(P8:U8) -> 0 | AC8: =SUM(W8:AB8) -> 0 | AH8: =SUM(AD8:AG8) -> 0 | AI8: =+H8+O8+V8+AH8 -> 0
A9: =1+A8 -> 2 | B9: Edwin Fernandez Chirinos | C9: El Alto | H9: =SUM(D9:G9) -> 0 | O9: =SUM(I9:N9) -> 0 | V9: =SUM(P9:U9) -> 0 | AC9: =SUM(W9:AB9) -> 0 | AH9: =SUM(AD9:AG9) -> 0 | AI9: =+H9+O9+V9+AH9 -> 0
A10: =1+A9 -> 3 | B10: Javier Caceres | C10: Cochabamba | H10: =SUM(D10:G10) -> 0 | O10: =SUM(I10:N10) -> 0 | V10: =SUM(P10:U10) -> 0 | AC10: =SUM(W10:AB10) -> 0 | AH10: =SUM(AD10:AG10) -> 0 | AI10: =+H10+O10+V10+AH10 -> 0
A11: =1+A10 -> 4 | B11: Juan Carlos Torrez Ayarde | C11: Tarija | H11: =SUM(D11:G11) -> 0 | O11: =SUM(I11:N11) -> 0 | V11: =SUM(P11:U11) -> 0 | AC11: =SUM(W11:AB11) -> 0 | AH11: =SUM(AD11:AG11) -> 0 | AI11: =+H11+O11+V11+AH11 -> 0
A12: =1+A11 -> 5 | B12: Carol Alejandra Noya | C12: Tarija | H12: =SUM(D12:G12) -> 0 | O12: =SUM(I12:N12) -> 0 | V12: =SUM(P12:U12) -> 0 | AC12: =SUM(W12:AB12) -> 0 | AH12: =SUM(AD12:AG12) -> 0 | AI12: =+H12+O12+V12+AH12 -> 0
A13: =1+A12 -> 6 | B13: Luis Alberto Chipana Peña | C13: Cochabamba | H13: =SUM(D13:G13) -> 0 | O13: =SUM(I13:N13) -> 0 | V13: =SUM(P13:U13) -> 0 | AC13: =SUM(W13:AB13) -> 0 | AH13: =SUM(AD13:AG13) -> 0 | AI13: =+H13+O13+V13+AH13 -> 0
A14: =1+A13 -> 7 | B14: Franz Carlos Alanez Flores | C14: El Alto | H14: =SUM(D14:G14) -> 0 | O14: =SUM(I14:N14) -> 0 | V14: =SUM(P14:U14) -> 0 | AC14: =SUM(W14:AB14) -> 0 | AH14: =SUM(AD14:AG14) -> 0 | AI14: =+H14+O14+V14+AH14 -> 0
A15: =1+A14 -> 8 | B15: Andrés Miguel Paniagua | C15: Oruro | H15: =SUM(D15:G15) -> 0 | O15: =SUM(I15:N15) -> 0 | V15: =SUM(P15:U15) -> 0 | AC15: =SUM(W15:AB15) -> 0 | AH15: =SUM(AD15:AG15) -> 0 | AI15: =+H15+O15+V15+AH15 -> 0
A16: =1+A15 -> 9 | B16: Alex Rolando Fernandez H. | C16: Oruro | H16: =SUM(D16:G16) -> 0 | O16: =SUM(I16:N16) -> 0 | V16: =SUM(P16:U16) -> 0 | AC16: =SUM(W16:AB16) -> 0 | AH16: =SUM(AD16:AG16) -> 0 | AI16: =+H16+O16+V16+AH16 -> 0
A17: =1+A16 -> 10 | B17: Franklin Ever Viveros | C17: Potosí | H17: =SUM(D17:G17) -> 0 | O17: =SUM(I17:N17) -> 0 | V17: =SUM(P17:U17) -> 0 | AC17: =SUM(W17:AB17) -> 0 | AH17: =SUM(AD17:AG17) -> 0 | AI17: =+H17+O17+V17+AH17 -> 0
A18: =1+A17 -> 11 | B18: Teofilo Ibañez Soliz | C18: Tarija | H18: =SUM(D18:G18) -> 0 | O18: =SUM(I18:N18) -> 0 | V18: =SUM(P18:U18) -> 0 | AC18: =SUM(W18:AB18) -> 0 | AH18: =SUM(AD18:AG18) -> 0 | AI18: =+H18+O18+V18+AH18 -> 0
A19: =1+A18 -> 12 | B19: Elsa Romay Padilla | C19: Uyuni | H19: =SUM(D19:G19) -> 0 | O19: =SUM(I19:N19) -> 0 | V19: =SUM(P19:U19) -> 0 | AC19: =SUM(W19:AB19) -> 0 | AH19: =SUM(AD19:AG19) -> 0 | AI19: =+H19+O19+V19+AH19 -> 0
A20: =1+A19 -> 13 | B20: Jorge Luis Vedia Arancibia | C20: Chuquisaca - Prov | H20: =SUM(D20:G20) -> 0 | O20: =SUM(I20:N20) -> 0 | V20: =SUM(P20:U20) -> 0 | AC20: =SUM(W20:AB20) -> 0 | AH20: =SUM(AD20:AG20) -> 0 | AI20: =+H20+O20+V20+AH20 -> 0
A21: =1+A20 -> 14 | B21: Celina Cruz Mendez | C21: Chuquisaca - Prov | H21: =SUM(D21:G21) -> 0 | O21: =SUM(I21:N21) -> 0 | V21: =SUM(P21:U21) -> 0 | AC21: =SUM(W21:AB21) -> 0 | AH21: =SUM(AD21:AG21) -> 0 | AI21: =+H21+O21+V21+AH21 -> 0
A22: =1+A28 -> 20 | B22: Marlene Paicho | C22: Ruta Colquechaca | H22: =SUM(D22:G22) -> 0 | O22: =SUM(I22:N22) -> 0 | V22: =SUM(P22:U22) -> 0 | AC22: =SUM(W22:AB22) -> 0 | AH22: =SUM(AD22:AG22) -> 0 | AI22: =H22+O22+V22+AH22 -> 0
A23: TOTAL CLIENTES MOROSOS | G23: =SUM(G8:G22) -> 0 | H23: =SUM(D23:G23) -> 0 | I23: =SUM(I8:I22) -> 0 | J23: =SUM(J8:J22) -> 0 | K23: =SUM(K8:K22) -> 0 | L23: =SUM(L8:L22) -> 0 | M23: =SUM(M8:M22) -> 0 | N23: =SUM(N8:N22) -> 0 | O23: =SUM(I23:N23) -> 0 | P23: =SUM(P8:P22) -> 0 | Q23: =SUM(Q8:Q22) -> 0 | R23: =SUM(R8:R22) -> 0 | S23: =SUM(S8:S22) -> 0 | T23: =SUM(T8:T22) -> 0 | U23: =SUM(U8:U22) -> 0 | V23: =SUM(P23:U23) -> 0 | W23: =SUM(W8:W22) -> 0 | X23: =SUM(X8:X22) -> 0 | Y23: =SUM(Y8:Y22) -> 0 | Z23: =SUM(Z8:Z22) -> 0 | AA23: =SUM(AA8:AA22) -> 0 | AB23: =SUM(AB8:AB22) -> 0 | AC23: =SUM(W23:AB23) -> 0 | AD23: =SUM(AD8:AD22) -> 0 | AG23: =SUM(AG8:AG22) -> 0 | AH23: =SUM(AD23:AG23) -> 0 | AI23: =SUM(AI8:AI22) -> 0
A24: =1+A21 -> 15 | B24: EMAPA NACIONAL | C24: NACIONAL | H24: =SUM(D24:G24) -> 0 | O24: =SUM(I24:N24) -> 0 | V24: =SUM(P24:U24) -> 0 | AC24: =SUM(W24:AB24) -> 0 | AH24: =SUM(AD24:AG24) -> 0 | AI24: =H24+O24+V24+AC24+AH24 -> 0
A25: =1+A24 -> 16 | B25: Gustavo Tellez Ugarte | C25: Santa Cruz | H25: =SUM(D25:G25) -> 0 | O25: =SUM(I25:N25) -> 0 | V25: =SUM(P25:U25) -> 0 | AC25: =SUM(W25:AB25) -> 0 | AH25: =SUM(AD25:AG25) -> 0 | AI25: =H25+O25+V25+AC25+AH25 -> 0
A26: =1+A25 -> 17 | B26: Cristhian Murillo | C26: Sucre | H26: =SUM(D26:G26) -> 0 | O26: =SUM(I26:N26) -> 0 | V26: =SUM(P26:U26) -> 0 | AC26: =SUM(W26:AB26) -> 0 | AG26: =+'Cristhian Murillo'!L27 -> 205000 | AH26: =SUM(AD26:AG26) -> 205000 | AI26: =H26+O26+V26+AC26+AH26 -> 205000
A27: =1+A26 -> 18 | B27: Sebastian Miranda | C27: Oruro | H27: =SUM(D27:G27) -> 0 | O27: =SUM(I27:N27) -> 0 | V27: =SUM(P27:U27) -> 0 | AC27: =SUM(W27:AB27) -> 0 | AH27: =SUM(AD27:AG27) -> 0 | AI27: =H27+O27+V27+AC27+AH27 -> 0
A28: =1+A27 -> 19 | B28: Norha Choque Talavera | C28: Potosí | H28: =SUM(D28:G28) -> 0 | O28: =SUM(I28:N28) -> 0 | V28: =SUM(P28:U28) -> 0 | AC28: =SUM(W28:AB28) -> 0 | AH28: =SUM(AD28:AG28) -> 0 | AI28: =H28+O28+V28+AC28+AH28 -> 0
A29: =1+A28 -> 20 | B29: Orlando Aldunate M. | C29: Tarija | H29: =SUM(D29:G29) -> 0 | O29: =SUM(I29:N29) -> 0 | V29: =SUM(P29:U29) -> 0 | AC29: =SUM(W29:AB29) -> 0 | AG29: =+'Orlando Aldunate'!L19 -> 138108.5 | AH29: =SUM(AD29:AG29) -> 138108.5 | AI29: =H29+O29+V29+AC29+AH29 -> 138108.5
A30: =1+A29 -> 21 | B30: Fausto Condori | C30: Cochabamba | H30: =SUM(D30:G30) -> 0 | O30: =SUM(I30:N30) -> 0 | V30: =SUM(P30:U30) -> 0 | AC30: =SUM(W30:AB30) -> 0 | AH30: =SUM(AD30:AG30) -> 0 | AI30: =H30+O30+V30+AC30+AH30 -> 0
A31: =1+A30 -> 22 | B31: Flora Yapuchura | C31: La Paz | H31: =SUM(D31:G31) -> 0 | O31: =SUM(I31:N31) -> 0 | V31: =SUM(P31:U31) -> 0 | AC31: =SUM(W31:AB31) -> 0 | AH31: =SUM(AD31:AG31) -> 0 | AI31: =H31+O31+V31+AC31+AH31 -> 0
A32: =1+A31 -> 23 | B32: Willy Quispe | C32: El Alto | H32: =SUM(D32:G32) -> 0 | O32: =SUM(I32:N32) -> 0 | V32: =SUM(P32:U32) -> 0 | AC32: =SUM(W32:AB32) -> 0 | AH32: =SUM(AD32:AG32) -> 0 | AI32: =H32+O32+V32+AC32+AH32 -> 0
A33: =1+A32 -> 24 | B33: Andrez Lopez | C33: Potosí | H33: =SUM(D33:G33) -> 0 | O33: =SUM(I33:N33) -> 0 | V33: =SUM(P33:U33) -> 0 | AC33: =SUM(W33:AB33) -> 0 | AH33: =SUM(AD33:AG33) -> 0 | AI33: =H33+O33+V33+AC33+AH33 -> 0
A34: =1+A33 -> 25 | B34: Miguel Angel Mora | C34: Potosí | H34: =SUM(D34:G34) -> 0 | O34: =SUM(I34:N34) -> 0 | V34: =SUM(P34:U34) -> 0 | AC34: =SUM(W34:AB34) -> 0 | AH34: =SUM(AD34:AG34) -> 0 | AI34: =H34+O34+V34+AC34+AH34 -> 0
A35: =1+A34 -> 26 | B35: GAMS Desarrollo Productivo | C35: Sucre | H35: =SUM(D35:G35) -> 0 | O35: =SUM(I35:N35) -> 0 | V35: =SUM(P35:U35) -> 0 | AC35: =SUM(W35:AB35) -> 0 | AH35: =SUM(AD35:AG35) -> 0 | AI35: =H35+O35+V35+AC35+AH35 -> 0
A36: =1+A35 -> 27 | B36: GAMS Direccion Administrativa | C36: Sucre | H36: =SUM(D36:G36) -> 0 | O36: =SUM(I36:N36) -> 0 | V36: =SUM(P36:U36) -> 0 | AC36: =SUM(W36:AB36) -> 0 | AH36: =SUM(AD36:AG36) -> 0 | AI36: =H36+O36+V36+AC36+AH36 -> 0
A37: =1+A36 -> 28 | B37: Carmen Cruz | C37: Potosí | H37: =SUM(D37:G37) -> 0 | O37: =SUM(I37:N37) -> 0 | V37: =SUM(P37:U37) -> 0 | AC37: =SUM(W37:AB37) -> 0 | AG37: =+#REF! -> #REF! | AH37: =SUM(AD37:AG37) -> #REF! | AI37: =H37+O37+V37+AC37+AH37 -> #REF!
A38: =1+A37 -> 29 | B38: Judith | C38: Cochabamba | H38: =SUM(D38:G38) -> 0 | O38: =SUM(I38:N38) -> 0 | V38: =SUM(P38:U38) -> 0 | AC38: =SUM(W38:AB38) -> 0 | AH38: =SUM(AD38:AG38) -> 0 | AI38: =H38+O38+V38+AC38+AH38 -> 0
A39: =1+A38 -> 30 | B39: Kevin | C39: Oruro | H39: =SUM(D39:G39) -> 0 | O39: =SUM(I39:N39) -> 0 | V39: =SUM(P39:U39) -> 0 | AC39: =SUM(W39:AB39) -> 0 | AH39: =SUM(AD39:AG39) -> 0 | AI39: =H39+O39+V39+AC39+AH39 -> 0
A40: =1+A39 -> 31 | B40: Jorge Saavedra | C40: Tupiza | H40: =SUM(D40:G40) -> 0 | O40: =SUM(I40:N40) -> 0 | V40: =SUM(P40:U40) -> 0 | AC40: =SUM(W40:AB40) -> 0 | AH40: =SUM(AD40:AG40) -> 0 | AI40: =H40+O40+V40+AC40+AH40 -> 0
A41: =1+A40 -> 32 | B41: Jenrry | C41: Chile | H41: =SUM(D41:G41) -> 0 | O41: =SUM(I41:N41) -> 0 | V41: =SUM(P41:U41) -> 0 | AC41: =SUM(W41:AB41) -> 0 | AH41: =SUM(AD41:AG41) -> 0 | AI41: =H41+O41+V41+AC41+AH41 -> 0
A42: =1+A41 -> 33 | B42: Eddy | C42: Chile | H42: =SUM(D42:G42) -> 0 | O42: =SUM(I42:N42) -> 0 | V42: =SUM(P42:U42) -> 0 | AC42: =SUM(W42:AB42) -> 0 | AH42: =SUM(AD42:AG42) -> 0 | AI42: =H42+O42+V42+AC42+AH42 -> 0
A43: =1+A42 -> 34 | B43: Rene Cahuana | C43: La Paz | H43: =SUM(D43:G43) -> 0 | O43: =SUM(I43:N43) -> 0 | V43: =SUM(P43:U43) -> 0 | AC43: =SUM(W43:AB43) -> 0 | AH43: =SUM(AD43:AG43) -> 0 | AI43: =H43+O43+V43+AC43+AH43 -> 0
A44: =1+A43 -> 35 | B44: Ines Aguirre | C44: Provincias Villazon | H44: =SUM(D44:G44) -> 0 | O44: =SUM(I44:N44) -> 0 | V44: =SUM(P44:U44) -> 0 | AC44: =SUM(W44:AB44) -> 0 | AH44: =SUM(AD44:AG44) -> 0 | AI44: =H44+O44+V44+AC44+AH44 -> 0
A45: =1+A44 -> 36 | B45: Yobana Llanos Cruz | C45: Ruta Chapare | H45: =SUM(D45:G45) -> 0 | O45: =SUM(I45:N45) -> 0 | V45: =SUM(P45:U45) -> 0 | AC45: =SUM(W45:AB45) -> 0 | AH45: =SUM(AD45:AG45) -> 0 | AI45: =H45+O45+V45+AC45+AH45 -> 0
A46: =1+A45 -> 37 | B46: Hernan Colque Cruz | C46: Pisiga | H46: =SUM(D46:G46) -> 0 | O46: =SUM(I46:N46) -> 0 | V46: =SUM(P46:U46) -> 0 | AC46: =SUM(W46:AB46) -> 0 | AH46: =SUM(AD46:AG46) -> 0 | AI46: =H46+O46+V46+AC46+AH46 -> 0
A47: =1+A46 -> 38 | B47: Roxana Yanet Castrillo Vasco | C47: Bermejo | H47: =SUM(D47:G47) -> 0 | O47: =SUM(I47:N47) -> 0 | V47: =SUM(P47:U47) -> 0 | AC47: =SUM(W47:AB47) -> 0 | AH47: =SUM(AD47:AG47) -> 0 | AI47: =H47+O47+V47+AC47+AH47 -> 0
A48: =1+A47 -> 39 | B48: Ismael Marca | C48: Uyuni | H48: =SUM(D48:G48) -> 0 | O48: =SUM(I48:N48) -> 0 | V48: =SUM(P48:U48) -> 0 | AC48: =SUM(W48:AB48) -> 0 | AH48: =SUM(AD48:AG48) -> 0 | AI48: =H48+O48+V48+AC48+AH48 -> 0
A49: =1+A48 -> 40 | B49: Freddy Alcocer Mollo | C49: Oruro | H49: =SUM(D49:G49) -> 0 | AH49: =SUM(AD49:AG49) -> 0 | AI49: =H49+O49+V49+AC49+AH49 -> 0
A50: =1+A49 -> 41 | B50: Katerine Soria Galvarro | C50: Oruro Provincia | H50: =SUM(D50:G50) -> 0 | AH50: =SUM(AD50:AG50) -> 0 | AI50: =H50+O50+V50+AC50+AH50 -> 0
A51: =1+A50 -> 42 | B51: Nilda | C51: CBBA Provincia | H51: =SUM(D51:G51) -> 0 | AH51: =SUM(AD51:AG51) -> 0 | AI51: =H51+O51+V51+AC51+AH51 -> 0
A52: =1+A51 -> 43 | B52: Divar Aranibar Plata | C52: Oruro | AH52: =SUM(AD52:AG52) -> 0 | AI52: =H52+O52+V52+AC52+AH52 -> 0
A53: =1+A52 -> 44 | B53: Ruth Gabriela | C53: Pando | AH53: =SUM(AD53:AG53) -> 0 | AI53: =H53+O53+V53+AC53+AH53 -> 0
A54: =1+A53 -> 45 | B54: Sergio Romero | C54: Sucre | AH54: =SUM(AD54:AG54) -> 0 | AI54: =H54+O54+V54+AC54+AH54 -> 0
A55: =1+A54 -> 46 | B55: Jorge Cruz | C55: Chile | H55: =SUM(D55:G55) -> 0 | O55: =SUM(I55:N55) -> 0 | V55: =SUM(P55:U55) -> 0 | AC55: =SUM(W55:AB55) -> 0 | AH55: =SUM(AD55:AG55) -> 0 | AI55: =H55+O55+V55+AC55+AH55 -> 0
A56: =1+A55 -> 47 | B56: Javier Mercado | C56: El Alto | AH56: =SUM(AD56:AG56) -> 0 | AI56: =H56+O56+V56+AC56+AH56 -> 0
A57: =1+A56 -> 48 | B57: Yaneth Miriam Toroya Gabriel | C57: Oruro | AG57: =+#REF! -> #REF! | AH57: =SUM(AD57:AG57) -> #REF! | AI57: =H57+O57+V57+AC57+AH57 -> #REF!
A58: =1+A57 -> 49 | B58: Patricia Romero | C58: Oruro | AH58: =SUM(AD58:AG58) -> 0 | AI58: =H58+O58+V58+AC58+AH58 -> 0
A59: =1+A58 -> 50 | B59: Miguel Calle | C59: Villazon | AH59: =SUM(AD59:AG59) -> 0 | AI59: =H59+O59+V59+AC59+AH59 -> 0
A60: =1+A59 -> 51 | B60: Paul Yamani | C60: Cochabamba | AH60: =SUM(AD60:AG60) -> 0 | AI60: =H60+O60+V60+AC60+AH60 -> 0
A61: =1+A60 -> 52 | B61: Silvia Gomez | C61: Huanuni | H61: =SUM(D61:G61) -> 0 | O61: =SUM(I61:N61) -> 0 | V61: =SUM(P61:U61) -> 0 | AC61: =SUM(W61:AB61) -> 0 | AH61: =SUM(AD61:AG61) -> 0 | AI61: =H61+O61+V61+AC61+AH61 -> 0
A62: =1+A61 -> 53 | B62: Alejandro Luna | C62: Chile | AG62: =+'ALEJANDRO CHILE'!F34 -> 169400 | AH62: =SUM(AD62:AG62) -> 169400 | AI62: =H62+O62+V62+AC62+AH62 -> 169400
A63: =1+A62 -> 54 | B63: Sandra Gutierrez Quispe | C63: Chile | AG63: =+'SANDRA CHILE'!F34 -> 165733.48 | AH63: =SUM(AD63:AG63) -> 165733.48 | AI63: =H63+O63+V63+AC63+AH63 -> 165733.48
A64: =1+A63 -> 55 | B64: Venta colillas | C64: Sucre | H64: =SUM(D64:G64) -> 0 | O64: =SUM(I64:N64) -> 0 | V64: =SUM(P64:U64) -> 0 | AC64: =SUM(W64:AB64) -> 0 | AH64: =SUM(AD64:AG64) -> 0 | AI64: =H64+O64+V64+AC64+AH64 -> 0
A65: =1+A64 -> 56 | B65: FEXPO 2025 | C65: Sucre | AG65: 44735 | AH65: =SUM(AD65:AG65) -> 44735 | AI65: =H65+O65+V65+AC65+AH65 -> 44735
A66: =1+A64 -> 56 | B66: Ventas en FABRICA | C66: Sucre | H66: =SUM(D66:G66) -> 0 | O66: =SUM(I66:N66) -> 0 | V66: =SUM(P66:U66) -> 0 | AC66: =SUM(W66:AB66) -> 0 | AG66: 26024 | AH66: =SUM(AD66:AG66) -> 26024 | AI66: =H66+O66+V66+AC66+AH66 -> 26024
A67: TOTALE CLIENTES ACTIVOS | G67: =SUM(G24:G66) -> 0 | H67: =SUM(D67:G67) -> 0 | I67: =SUM(I24:I66) -> 0 | J67: =SUM(J24:J66) -> 0 | K67: =SUM(K24:K66) -> 0 | L67: =SUM(L24:L66) -> 0 | M67: =SUM(M24:M66) -> 0 | N67: =SUM(N24:N66) -> 0 | O67: =SUM(I67:N67) -> 0 | P67: =SUM(P24:P66) -> 0 | Q67: =SUM(Q24:Q66) -> 0 | R67: =SUM(R24:R66) -> 0 | S67: =SUM(S24:S66) -> 0 | T67: =SUM(T24:T66) -> 0 | U67: =SUM(U24:U66) -> 0 | V67: =SUM(P67:U67) -> 0 | W67: =SUM(W24:W66) -> 0 | X67: =SUM(X24:X66) -> 0 | Y67: =SUM(Y24:Y66) -> 0 | Z67: =SUM(Z24:Z66) -> 0 | AA67: =SUM(AA24:AA66) -> 0 | AB67: =SUM(AB24:AB66) -> 0 | AC67: =SUM(W67:AB67) -> 0 | AD67: =SUM(AD24:AD66) -> 0 | AE67: =SUM(AE24:AE66) -> 0 | AF67: =SUM(AF24:AF66) -> 0 | AG67: =SUM(AG24:AG66) -> #REF! | AH67: =SUM(AD67:AG67) -> #REF! | AI67: =SUM(AI24:AI66) -> #REF!
A68: TOTALE CLIENTES | D68: =+D23+D67 -> 0 | E68: =+E23+E67 -> 0 | F68: =+F23+F67 -> 0 | G68: =+G23+G67 -> 0 | H68: =SUM(D68:G68) -> 0 | I68: =+I23+I67 -> 0 | J68: =+J23+J67 -> 0 | K68: =+K23+K67 -> 0 | L68: =+L23+L67 -> 0 | M68: =+M23+M67 -> 0 | N68: =+N23+N67 -> 0 | O68: =SUM(I68:N68) -> 0 | P68: =+P23+P67 -> 0 | Q68: =+Q23+Q67 -> 0 | R68: =+R23+R67 -> 0 | S68: =+S23+S67 -> 0 | T68: =+T23+T67 -> 0 | U68: =+U23+U67 -> 0 | V68: =SUM(P68:U68) -> 0 | W68: =+W23+W67 -> 0 | X68: =+X23+X67 -> 0 | Y68: =+Y23+Y67 -> 0 | Z68: =+Z23+Z67 -> 0 | AA68: =+AA23+AA67 -> 0 | AB68: =+AB23+AB67 -> 0 | AC68: =SUM(W68:AB68) -> 0 | AD68: =+AD23+AD67 -> 0 | AH68: =SUM(AD68:AG68) -> 0 | AI68: =SUM(AI67,AI23) -> #REF!

Sheet RECAU. JUNIO 2025
A3: CUENTAS POR COBRAR A CLIENTES
A4: GESTION 2023 - 2024
A5: JUNIO - 2025
A6: Nº | B6: DISTRIBUIDOR | C6: DEPARTAMENTO | AI6: TOTAL MES
D7: 1 | E7: 2 | F7: 3 | G7: 4 | H7: Semana 1 | I7: 6 | J7: 7 | K7: 8 | L7: 9 | M7: 10 | N7: 11 | O7: Semana 2 | P7: 13 | Q7: 14 | R7: 15 | S7: 16 | T7: 17 | U7: 18 | V7: Semana 3 | W7: 20 | X7: 21 | Y7: 22 | Z7: 23 | AA7: 24 | AB7: 25 | AC7: Semana 4 | AD7: 27 | AE7: 28 | AF7: 29 | AG7: 28 | AH7: Semana 4
A8: 1 | B8: Fabricio Tapia Castedo | C8: Cochabamba | H8: =SUM(D8:G8) -> 0 | O8: =SUM(I8:N8) -> 0 | V8: =SUM(P8:U8) -> 0 | AC8: =SUM(W8:AB8) -> 0 | AH8: =SUM(AD8:AG8) -> 0 | AI8: =+H8+O8+V8+AH8 -> 0
A9: =1+A8 -> 2 | B9: Edwin Fernandez Chirinos | C9: El Alto | H9: =SUM(D9:G9) -> 0 | O9: =SUM(I9:N9) -> 0 | V9: =SUM(P9:U9) -> 0 | AC9: =SUM(W9:AB9) -> 0 | AH9: =SUM(AD9:AG9) -> 0 | AI9: =+H9+O9+V9+AH9 -> 0
A10: =1+A9 -> 3 | B10: Javier Caceres | C10: Cochabamba | H10: =SUM(D10:G10) -> 0 | O10: =SUM(I10:N10) -> 0 | V10: =SUM(P10:U10) -> 0 | AC10: =SUM(W10:AB10) -> 0 | AH10: =SUM(AD10:AG10) -> 0 | AI10: =+H10+O10+V10+AH10 -> 0
A11: =1+A10 -> 4 | B11: Juan Carlos Torrez Ayarde | C11: Tarija | H11: =SUM(D11:G11) -> 0 | O11: =SUM(I11:N11) -> 0 | V11: =SUM(P11:U11) -> 0 | AC11: =SUM(W11:AB11) -> 0 | AH11: =SUM(AD11:AG11) -> 0 | AI11: =+H11+O11+V11+AH11 -> 0
A12: =1+A11 -> 5 | B12: Carol Alejandra Noya | C12: Tarija | H12: =SUM(D12:G12) -> 0 | O12: =SUM(I12:N12) -> 0 | V12: =SUM(P12:U12) -> 0 | AC12: =SUM(W12:AB12) -> 0 | AH12: =SUM(AD12:AG12) -> 0 | AI12: =+H12+O12+V12+AH12 -> 0
A13: =1+A12 -> 6 | B13: Luis Alberto Chipana Peña | C13: Cochabamba | H13: =SUM(D13:G13) -> 0 | O13: =SUM(I13:N13) -> 0 | V13: =SUM(P13:U13) -> 0 | AC13: =SUM(W13:AB13) -> 0 | AH13: =SUM(AD13:AG13) -> 0 | AI13: =+H13+O13+V13+AH13 -> 0
A14: =1+A13 -> 7 | B14: Franz Carlos Alanez Flores | C14: El Alto | H14: =SUM(D14:G14) -> 0 | O14: =SUM(I14:N14) -> 0 | V14: =SUM(P14:U14) -> 0 | AC14: =SUM(W14:AB14) -> 0 | AH14: =SUM(AD14:AG14) -> 0 | AI14: =+H14+O14+V14+AH14 -> 0
A15: =1+A14 -> 8 | B15: Andrés Miguel Paniagua | C15: Oruro | H15: =SUM(D15:G15) -> 0 | O15: =SUM(I15:N15) -> 0 | V15: =SUM(P15:U15) -> 0 | AC15: =SUM(W15:AB15) -> 0 | AH15: =SUM(AD15:AG15) -> 0 | AI15: =+H15+O15+V15+AH15 -> 0
A16: =1+A15 -> 9 | B16: Alex Rolando Fernandez H. | C16: Oruro | H16: =SUM(D16:G16) -> 0 | O16: =SUM(I16:N16) -> 0 | V16: =SUM(P16:U16) -> 0 | AC16: =SUM(W16:AB16) -> 0 | AH16: =SUM(AD16:AG16) -> 0 | AI16: =+H16+O16+V16+AH16 -> 0
A17: =1+A16 -> 10 | B17: Franklin Ever Viveros | C17: Potosí | H17: =SUM(D17:G17) -> 0 | O17: =SUM(I17:N17) -> 0 | V17: =SUM(P17:U17) -> 0 | AC17: =SUM(W17:AB17) -> 0 | AH17: =SUM(AD17:AG17) -> 0 | AI17: =+H17+O17+V17+AH17 -> 0
A18: =1+A17 -> 11 | B18: Teofilo Ibañez Soliz | C18: Tarija | H18: =SUM(D18:G18) -> 0 | O18: =SUM(I18:N18) -> 0 | V18: =SUM(P18:U18) -> 0 | AC18: =SUM(W18:AB18) -> 0 | AH18: =SUM(AD18:AG18) -> 0 | AI18: =+H18+O18+V18+AH18 -> 0
A19: =1+A18 -> 12 | B19: Elsa Romay Padilla | C19: Uyuni | H19: =SUM(D19:G19) -> 0 | O19: =SUM(I19:N19) -> 0 | V19: =SUM(P19:U19) -> 0 | AC19: =SUM(W19:AB19) -> 0 | AH19: =SUM(AD19:AG19) -> 0 | AI19: =+H19+O19+V19+AH19 -> 0
A20: =1+A19 -> 13 | B20: Jorge Luis Vedia Arancibia | C20: Chuquisaca - Prov | H20: =SUM(D20:G20) -> 0 | O20: =SUM(I20:N20) -> 0 | V20: =SUM(P20:U20) -> 0 | AC20: =SUM(W20:AB20) -> 0 | AH20: =SUM(AD20:AG20) -> 0 | AI20: =+H20+O20+V20+AH20 -> 0
A21: =1+A20 -> 14 | B21: Celina Cruz Mendez | C21: Chuquisaca - Prov | H21: =SUM(D21:G21) -> 0 | O21: =SUM(I21:N21) -> 0 | V21: =SUM(P21:U21) -> 0 | AC21: =SUM(W21:AB21) -> 0 | AH21: =SUM(AD21:AG21) -> 0 | AI21: =+H21+O21+V21+AH21 -> 0
A22: =1+A28 -> 20 | B22: Marlene Paicho | C22: Ruta Colquechaca | H22: =SUM(D22:G22) -> 0 | O22: =SUM(I22:N22) -> 0 | V22: =SUM(P22:U22) -> 0 | AC22: =SUM(W22:AB22) -> 0 | AH22: =SUM(AD22:AG22) -> 0 | AI22: =H22+O22+V22+AH22 -> 0
A23: TOTAL CLIENTES MOROSOS | G23: =SUM(G8:G22) -> 0 | H23: =SUM(D23:G23) -> 0 | I23: =SUM(I8:I22) -> 0 | J23: =SUM(J8:J22) -> 0 | K23: =SUM(K8:K22) -> 0 | L23: =SUM(L8:L22) -> 0 | M23: =SUM(M8:M22) -> 0 | N23: =SUM(N8:N22) -> 0 | O23: =SUM(I23:N23) -> 0 | P23: =SUM(P8:P22) -> 0 | Q23: =SUM(Q8:Q22) -> 0 | R23: =SUM(R8:R22) -> 0 | S23: =SUM(S8:S22) -> 0 | T23: =SUM(T8:T22) -> 0 | U23: =SUM(U8:U22) -> 0 | V23: =SUM(P23:U23) -> 0 | W23: =SUM(W8:W22) -> 0 | X23: =SUM(X8:X22) -> 0 | Y23: =SUM(Y8:Y22) -> 0 | Z23: =SUM(Z8:Z22) -> 0 | AA23: =SUM(AA8:AA22) -> 0 | AB23: =SUM(AB8:AB22) -> 0 | AC23: =SUM(W23:AB23) -> 0 | AD23: =SUM(AD8:AD22) -> 0 | AG23: =SUM(AG8:AG22) -> 0 | AH23: =SUM(AD23:AG23) -> 0 | AI23: =SUM(AI8:AI22) -> 0
A24: =1+A21 -> 15 | B24: EMAPA NACIONAL | C24: NACIONAL | H24: =SUM(D24:G24) -> 0 | O24: =SUM(I24:N24) -> 0 | V24: =SUM(P24:U24) -> 0 | AC24: =SUM(W24:AB24) -> 0 | AH24: =SUM(AD24:AG24) -> 0 | AI24: =H24+O24+V24+AC24+AH24 -> 0
A25: =1+A24 -> 16 | B25: Gustavo Tellez Ugarte | C25: Santa Cruz | H25: =SUM(D25:G25) -> 0 | O25: =SUM(I25:N25) -> 0 | V25: =SUM(P25:U25) -> 0 | AC25: =SUM(W25:AB25) -> 0 | AG25: 85974 | AH25: =SUM(AD25:AG25) -> 85974 | AI25: =H25+O25+V25+AC25+AH25 -> 85974
A26: =1+A25 -> 17 | B26: Cristhian Murillo | C26: Sucre | H26: =SUM(D26:G26) -> 0 | O26: =SUM(I26:N26) -> 0 | V26: =SUM(P26:U26) -> 0 | AC26: =SUM(W26:AB26) -> 0 | AG26: 100000 | AH26: =SUM(AD26:AG26) -> 100000 | AI26: =H26+O26+V26+AC26+AH26 -> 100000
A27: =1+A26 -> 18 | B27: Sebastian Miranda | C27: Oruro | H27: =SUM(D27:G27) -> 0 | O27: =SUM(I27:N27) -> 0 | V27: =SUM(P27:U27) -> 0 | AC27: =SUM(W27:AB27) -> 0 | AH27: =SUM(AD27:AG27) -> 0 | AI27: =H27+O27+V27+AC27+AH27 -> 0
A28: =1+A27 -> 19 | B28: Norha Choque Talavera | C28: Potosí | H28: =SUM(D28:G28) -> 0 | O28: =SUM(I28:N28) -> 0 | V28: =SUM(P28:U28) -> 0 | AC28: =SUM(W28:AB28) -> 0 | AH28: =SUM(AD28:AG28) -> 0 | AI28: =H28+O28+V28+AC28+AH28 -> 0
A29: =1+A28 -> 20 | B29: Orlando Aldunate M. | C29: Tarija | H29: =SUM(D29:G29) -> 0 | O29: =SUM(I29:N29) -> 0 | V29: =SUM(P29:U29) -> 0 | AC29: =SUM(W29:AB29) -> 0 | AH29: =SUM(AD29:AG29) -> 0 | AI29: =H29+O29+V29+AC29+AH29 -> 0
A30: =1+A29 -> 21 | B30: Fausto Condori | C30: Cochabamba | H30: =SUM(D30:G30) -> 0 | O30: =SUM(I30:N30) -> 0 | V30: =SUM(P30:U30) -> 0 | AC30: =SUM(W30:AB30) -> 0 | AH30: =SUM(AD30:AG30) -> 0 | AI30: =H30+O30+V30+AC30+AH30 -> 0
A31: =1+A30 -> 22 | B31: Flora Yapuchura | C31: La Paz | H31: =SUM(D31:G31) -> 0 | O31: =SUM(I31:N31) -> 0 | V31: =SUM(P31:U31) -> 0 | AC31: =SUM(W31:AB31) -> 0 | AH31: =SUM(AD31:AG31) -> 0 | AI31: =H31+O31+V31+AC31+AH31 -> 0
A32: =1+A31 -> 23 | B32: Willy Quispe | C32: El Alto | H32: =SUM(D32:G32) -> 0 | O32: =SUM(I32:N32) -> 0 | V32: =SUM(P32:U32) -> 0 | AC32: =SUM(W32:AB32) -> 0 | AH32: =SUM(AD32:AG32) -> 0 | AI32: =H32+O32+V32+AC32+AH32 -> 0
A33: =1+A32 -> 24 | B33: Andrez Lopez | C33: Potosí | H33: =SUM(D33:G33) -> 0 | O33: =SUM(I33:N33) -> 0 | V33: =SUM(P33:U33) -> 0 | AC33: =SUM(W33:AB33) -> 0 | AH33: =SUM(AD33:AG33) -> 0 | AI33: =H33+O33+V33+AC33+AH33 -> 0
A34: =1+A33 -> 25 | B34: Miguel Angel Mora | C34: Potosí | H34: =SUM(D34:G34) -> 0 | O34: =SUM(I34:N34) -> 0 | V34: =SUM(P34:U34) -> 0 | AC34: =SUM(W34:AB34) -> 0 | AH34: =SUM(AD34:AG34) -> 0 | AI34: =H34+O34+V34+AC34+AH34 -> 0
A35: =1+A34 -> 26 | B35: GAMS Desarrollo Productivo | C35: Sucre | H35: =SUM(D35:G35) -> 0 | O35: =SUM(I35:N35) -> 0 | V35: =SUM(P35:U35) -> 0 | AC35: =SUM(W35:AB35) -> 0 | AH35: =SUM(AD35:AG35) -> 0 | AI35: =H35+O35+V35+AC35+AH35 -> 0
A36: =1+A35 -> 27 | B36: GAMS Direccion Administrativa | C36: Sucre | H36: =SUM(D36:G36) -> 0 | O36: =SUM(I36:N36) -> 0 | V36: =SUM(P36:U36) -> 0 | AC36: =SUM(W36:AB36) -> 0 | AH36: =SUM(AD36:AG36) -> 0 | AI36: =H36+O36+V36+AC36+AH36 -> 0
A37: =1+A36 -> 28 | B37: Carmen Cruz | C37: Potosí | H37: =SUM(D37:G37) -> 0 | O37: =SUM(I37:N37) -> 0 | V37: =SUM(P37:U37) -> 0 | AC37: =SUM(W37:AB37) -> 0 | AG37: 148090 | AH37: =SUM(AD37:AG37) -> 148090 | AI37: =H37+O37+V37+AC37+AH37 -> 148090
A38: =1+A37 -> 29 | B38: Judith | C38: Cochabamba | H38: =SUM(D38:G38) -> 0 | O38: =SUM(I38:N38) -> 0 | V38: =SUM(P38:U38) -> 0 | AC38: =SUM(W38:AB38) -> 0 | AH38: =SUM(AD38:AG38) -> 0 | AI38: =H38+O38+V38+AC38+AH38 -> 0
A39: =1+A38 -> 30 | B39: Kevin | C39: Oruro | H39: =SUM(D39:G39) -> 0 | O39: =SUM(I39:N39) -> 0 | V39: =SUM(P39:U39) -> 0 | AC39: =SUM(W39:AB39) -> 0 | AH39: =SUM(AD39:AG39) -> 0 | AI39: =H39+O39+V39+AC39+AH39 -> 0
A40: =1+A39 -> 31 | B40: Jorge Saavedra | C40: Tupiza | H40: =SUM(D40:G40) -> 0 | O40: =SUM(I40:N40) -> 0 | V40: =SUM(P40:U40) -> 0 | AC40: =SUM(W40:AB40) -> 0 | AH40: =SUM(AD40:AG40) -> 0 | AI40: =H40+O40+V40+AC40+AH40 -> 0
A41: =1+A40 -> 32 | B41: Jenrry | C41: Chile | H41: =SUM(D41:G41) -> 0 | O41: =SUM(I41:N41) -> 0 | V41: =SUM(P41:U41) -> 0 | AC41: =SUM(W41:AB41) -> 0 | AG41: 200633.6 | AH41: =SUM(AD41:AG41) -> 200633.6 | AI41: =H41+O41+V41+AC41+AH41 -> 200633.6
A42: =1+A41 -> 33 | B42: Eddy | C42: Chile | H42: =SUM(D42:G42) -> 0 | O42: =SUM(I42:N42) -> 0 | V42: =SUM(P42:U42) -> 0 | AC42: =SUM(W42:AB42) -> 0 | AG42: 436247 | AH42: =SUM(AD42:AG42) -> 436247 | AI42: =H42+O42+V42+AC42+AH42 -> 436247
A43: =1+A42 -> 34 | B43: Rene Cahuana | C43: La Paz | H43: =SUM(D43:G43) -> 0 | O43: =SUM(I43:N43) -> 0 | V43: =SUM(P43:U43) -> 0 | AC43: =SUM(W43:AB43) -> 0 | AH43: =SUM(AD43:AG43) -> 0 | AI43: =H43+O43+V43+AC43+AH43 -> 0
A44: =1+A43 -> 35 | B44: Ines Aguirre | C44: Provincias Villazon | H44: =SUM(D44:G44) -> 0 | O44: =SUM(I44:N44) -> 0 | V44: =SUM(P44:U44) -> 0 | AC44: =SUM(W44:AB44) -> 0 | AH44: =SUM(AD44:AG44) -> 0 | AI44: =H44+O44+V44+AC44+AH44 -> 0
A45: =1+A44 -> 36 | B45: Yobana Llanos Cruz | C45: Ruta Chapare | H45: =SUM(D45:G45) -> 0 | O45: =SUM(I45:N45) -> 0 | V45: =SUM(P45:U45) -> 0 | AC45: =SUM(W45:AB45) -> 0 | AH45: =SUM(AD45:AG45) -> 0 | AI45: =H45+O45+V45+AC45+AH45 -> 0
A46: =1+A45 -> 37 | B46: Hernan Colque Cruz | C46: Pisiga | H46: =SUM(D46:G46) -> 0 | O46: =SUM(I46:N46) -> 0 | V46: =SUM(P46:U46) -> 0 | AC46: =SUM(W46:AB46) -> 0 | AH46: =SUM(AD46:AG46) -> 0 | AI46: =H46+O46+V46+AC46+AH46 -> 0
A47: =1+A46 -> 38 | B47: Roxana Yanet Castrillo Vasco | C47: Bermejo | H47: =SUM(D47:G47) -> 0 | O47: =SUM(I47:N47) -> 0 | V47: =SUM(P47:U47) -> 0 | AC47: =SUM(W47:AB47) -> 0 | AH47: =SUM(AD47:AG47) -> 0 | AI47: =H47+O47+V47+AC47+AH47 -> 0
A48: =1+A47 -> 39 | B48: Ismael Marca | C48: Uyuni | H48: =SUM(D48:G48) -> 0 | O48: =SUM(I48:N48) -> 0 | V48: =SUM(P48:U48) -> 0 | AC48: =SUM(W48:AB48) -> 0 | AH48: =SUM(AD48:AG48) -> 0 | AI48: =H48+O48+V48+AC48+AH48 -> 0
A49: =1+A48 -> 40 | B49: Freddy Alcocer Mollo | C49: Oruro | H49: =SUM(D49:G49) -> 0 | AH49: =SUM(AD49:AG49) -> 0 | AI49: =H49+O49+V49+AC49+AH49 -> 0
A50: =1+A49 -> 41 | B50: Katerine Soria Galvarro | C50: Oruro Provincia | H50: =SUM(D50:G50) -> 0 | AG50: 26000 | AH50: =SUM(AD50:AG50) -> 26000 | AI50: =H50+O50+V50+AC50+AH50 -> 26000
A51: =1+A50 -> 42 | B51: Nilda | C51: CBBA Provincia | H51: =SUM(D51:G51) -> 0 | AH51: =SUM(AD51:AG51) -> 0 | AI51: =H51+O51+V51+AC51+AH51 -> 0
A52: =1+A51 -> 43 | B52: Divar Aranibar Plata | C52: Oruro | AH52: =SUM(AD52:AG52) -> 0 | AI52: =H52+O52+V52+AC52+AH52 -> 0
A53: =1+A52 -> 44 | B53: Ruth Gabriela | C53: Pando | AH53: =SUM(AD53:AG53) -> 0 | AI53: =H53+O53+V53+AC53+AH53 -> 0
A54: =1+A53 -> 45 | B54: Sergio Romero | C54: Sucre | AH54: =SUM(AD54:AG54) -> 0 | AI54: =H54+O54+V54+AC54+AH54 -> 0
A55: =1+A54 -> 46 | B55: Jorge Cruz | C55: Chile | H55: =SUM(D55:G55) -> 0 | O55: =SUM(I55:N55) -> 0 | V55: =SUM(P55:U55) -> 0 | AC55: =SUM(W55:AB55) -> 0 | AH55: =SUM(AD55:AG55) -> 0 | AI55: =H55+O55+V55+AC55+AH55 -> 0
A56: =1+A55 -> 47 | B56: Javier Mercado | C56: El Alto | AH56: =SUM(AD56:AG56) -> 0 | AI56: =H56+O56+V56+AC56+AH56 -> 0
A57: =1+A56 -> 48 | B57: Yaneth Miriam Toroya Gabriel | C57: Oruro | AH57: =SUM(AD57:AG57) -> 0 | AI57: =H57+O57+V57+AC57+AH57 -> 0
A58: =1+A57 -> 49 | B58: Patricia Romero | C58: Oruro | AH58: =SUM(AD58:AG58) -> 0 | AI58: =H58+O58+V58+AC58+AH58 -> 0
A59: =1+A58 -> 50 | B59: Miguel Calle | C59: Villazon | AH59: =SUM(AD59:AG59) -> 0 | AI59: =H59+O59+V59+AC59+AH59 -> 0
A60: =1+A59 -> 51 | B60: Paul Yamani | C60: Cochabamba | AH60: =SUM(AD60:AG60) -> 0 | AI60: =H60+O60+V60+AC60+AH60 -> 0
A61: =1+A60 -> 52 | B61: Silvia Gomez | C61: Huanuni | H61: =SUM(D61:G61) -> 0 | O61: =SUM(I61:N61) -> 0 | V61: =SUM(P61:U61) -> 0 | AC61: =SUM(W61:AB61) -> 0 | AH61: =SUM(AD61:AG61) -> 0 | AI61: =H61+O61+V61+AC61+AH61 -> 0
A62: =1+A61 -> 53 | B62: Alejandro Luna | C62: Chile | AH62: =SUM(AD62:AG62) -> 0 | AI62: =H62+O62+V62+AC62+AH62 -> 0
A63: =1+A62 -> 54 | B63: Sandra Gutierrez Quispe | C63: Chile | AH63: =SUM(AD63:AG63) -> 0 | AI63: =H63+O63+V63+AC63+AH63 -> 0
A64: =1+A63 -> 55 | B64: Venta colillas y otros | C64: Sucre | H64: =SUM(D64:G64) -> 0 | O64: =SUM(I64:N64) -> 0 | V64: =SUM(P64:U64) -> 0 | AC64: =SUM(W64:AB64) -> 0 | AG64: 1552.1 | AH64: =SUM(AD64:AG64) -> 1552.1 | AI64: =H64+O64+V64+AC64+AH64 -> 1552.1
A65: =1+A64 -> 56 | B65: FEXPO 2025 | C65: Sucre | AH65: =SUM(AD65:AG65) -> 0 | AI65: =H65+O65+V65+AC65+AH65 -> 0
A66: =1+A64 -> 56 | B66: Ventas en FABRICA | C66: Sucre | H66: =SUM(D66:G66) -> 0 | O66: =SUM(I66:N66) -> 0 | V66: =SUM(P66:U66) -> 0 | AC66: =SUM(W66:AB66) -> 0 | AG66: 25530 | AH66: =SUM(AD66:AG66) -> 25530 | AI66: =H66+O66+V66+AC66+AH66 -> 25530
A67: TOTALE CLIENTES ACTIVOS | G67: =SUM(G24:G66) -> 0 | H67: =SUM(D67:G67) -> 0 | I67: =SUM(I24:I66) -> 0 | J67: =SUM(J24:J66) -> 0 | K67: =SUM(K24:K66) -> 0 | L67: =SUM(L24:L66) -> 0 | M67: =SUM(M24:M66) -> 0 | N67: =SUM(N24:N66) -> 0 | O67: =SUM(I67:N67) -> 0 | P67: =SUM(P24:P66) -> 0 | Q67: =SUM(Q24:Q66) -> 0 | R67: =SUM(R24:R66) -> 0 | S67: =SUM(S24:S66) -> 0 | T67: =SUM(T24:T66) -> 0 | U67: =SUM(U24:U66) -> 0 | V67: =SUM(P67:U67) -> 0 | W67: =SUM(W24:W66) -> 0 | X67: =SUM(X24:X66) -> 0 | Y67: =SUM(Y24:Y66) -> 0 | Z67: =SUM(Z24:Z66) -> 0 | AA67: =SUM(AA24:AA66) -> 0 | AB67: =SUM(AB24:AB66) -> 0 | AC67: =SUM(W67:AB67) -> 0 | AD67: =SUM(AD24:AD66) -> 0 | AE67: =SUM(AE24:AE66) -> 0 | AF67: =SUM(AF24:AF66) -> 0 | AG67: =SUM(AG24:AG66) -> 1024026.7 | AH67: =SUM(AD67:AG67) -> 1024026.7 | AI67: =SUM(AI24:AI66) -> 1024026.7
A68: TOTALE CLIENTES | D68: =+D23+D67 -> 0 | E68: =+E23+E67 -> 0 | F68: =+F23+F67 -> 0 | G68: =+G23+G67 -> 0 | H68: =SUM(D68:G68) -> 0 | I68: =+I23+I67 -> 0 | J68: =+J23+J67 -> 0 | K68: =+K23+K67 -> 0 | L68: =+L23+L67 -> 0 | M68: =+M23+M67 -> 0 | N68: =+N23+N67 -> 0 | O68: =SUM(I68:N68) -> 0 | P68: =+P23+P67 -> 0 | Q68: =+Q23+Q67 -> 0 | R68: =+R23+R67 -> 0 | S68: =+S23+S67 -> 0 | T68: =+T23+T67 -> 0 | U68: =+U23+U67 -> 0 | V68: =SUM(P68:U68) -> 0 | W68: =+W23+W67 -> 0 | X68: =+X23+X67 -> 0 | Y68: =+Y23+Y67 -> 0 | Z68: =+Z23+Z67 -> 0 | AA68: =+AA23+AA67 -> 0 | AB68: =+AB23+AB67 -> 0 | AC68: =SUM(W68:AB68) -> 0 | AD68: =+AD23+AD67 -> 0 | AH68: =SUM(AD68:AG68) -> 0 | AI68: =SUM(AI67,AI23) -> 1024026.7

Sheet EMAPA
B2: CUENTAS POR COBRAR
B3: GESTION 2025 - 2026
C5: CLIENTE: | D5: EMAPA NACIONAL
C6: CELULAR:
C7: DESTINO: | D7: TODAS LAS REGIONALES
C8: LINEA DE CREDITO:
B10: NOTA DE VENTA | C10: NOTA DE ENTREGA | D10: FECHA DE DESPACHO | E10: MONTO P/COBRAR | F10: DESTINO | G10: DEPÓSITO en Bs | H10: FECHA DE DEPÓSITO | I10: SALDO | J10: N° FACTURA | K10: OBSERVACION
I11: =+E11-G11 -> 0
I12: =+I11+E12-G12 -> 0
I13: =+I12+E13-G13 -> 0
I14: =+I13+E14-G14 -> 0
I15: =+I14+E15-G15 -> 0
I16: =+I15+E16-G16 -> 0
I17: =+I16+E17-G17 -> 0
I18: =+I17+E18-G18 -> 0
I19: =+I18+E19-G19 -> 0
I20: =+I19+E20-G20 -> 0
I21: =+I20+E21-G21 -> 0
I22: =+I21+E22-G22 -> 0
I23: =+I22+E23-G23 -> 0
... I138: =+I137+E138-G138 -> 0
B139: TOTALES | E139: =SUM(E11:E138) -> 0 | G139: =SUM(G11:G138) -> 0
C140: SALDO POR COBRAR | G140: =+E139-G139 -> 0
C141: LINEA DE CREDITO | G141: 0
C142: SALDO DESPUES DE LA LINEA DE CREDITO | G142: =+G140-G141 -> 0

Sheet RECAU. AGOSTO 2025
A3: CUENTAS POR COBRAR A CLIENTES
A4: GESTION 2023 - 2024
A5: JULIO - 2025
A6: Nº | B6: DISTRIBUIDOR | C6: DEPARTAMENTO | AI6: TOTAL MES
D7: 1 | E7: 2 | F7: 3 | G7: 4 | H7: Semana 1 | I7: 6 | J7: 7 | K7: 8 | L7: 9 | M7: 10 | N7: 11 | O7: Semana 2 | P7: 13 | Q7: 14 | R7: 15 | S7: 16 | T7: 17 | U7: 18 | V7: Semana 3 | W7: 20 | X7: 21 | Y7: 22 | Z7: 23 | AA7: 24 | AB7: 25 | AC7: Semana 4 | AD7: 27 | AE7: 28 | AF7: 29 | AG7: 31 | AH7: Semana 4
A8: 1 | B8: Fabricio Tapia Castedo | C8: Cochabamba | H8: =SUM(D8:G8) -> 0 | O8: =SUM(I8:N8) -> 0 | V8: =SUM(P8:U8) -> 0 | AC8: =SUM(W8:AB8) -> 0 | AH8: =SUM(AD8:AG8) -> 0 | AI8: =+H8+O8+V8+AH8 -> 0
A9: =1+A8 -> 2 | B9: Edwin Fernandez Chirinos | C9: El Alto | H9: =SUM(D9:G9) -> 0 | O9: =SUM(I9:N9) -> 0 | V9: =SUM(P9:U9) -> 0 | AC9: =SUM(W9:AB9) -> 0 | AH9: =SUM(AD9:AG9) -> 0 | AI9: =+H9+O9+V9+AH9 -> 0
A10: =1+A9 -> 3 | B10: Javier Caceres | C10: Cochabamba | H10: =SUM(D10:G10) -> 0 | O10: =SUM(I10:N10) -> 0 | V10: =SUM(P10:U10) -> 0 | AC10: =SUM(W10:AB10) -> 0 | AH10: =SUM(AD10:AG10) -> 0 | AI10: =+H10+O10+V10+AH10 -> 0
A11: =1+A10 -> 4 | B11: Juan Carlos Torrez Ayarde | C11: Tarija | H11: =SUM(D11:G11) -> 0 | O11: =SUM(I11:N11) -> 0 | V11: =SUM(P11:U11) -> 0 | AC11: =SUM(W11:AB11) -> 0 | AH11: =SUM(AD11:AG11) -> 0 | AI11: =+H11+O11+V11+AH11 -> 0
A12: =1+A11 -> 5 | B12: Carol Alejandra Noya | C12: Tarija | H12: =SUM(D12:G12) -> 0 | O12: =SUM(I12:N12) -> 0 | V12: =SUM(P12:U12) -> 0 | AC12: =SUM(W12:AB12) -> 0 | AH12: =SUM(AD12:AG12) -> 0 | AI12: =+H12+O12+V12+AH12 -> 0
A13: =1+A12 -> 6 | B13: Luis Alberto Chipana Peña | C13: Cochabamba | H13: =SUM(D13:G13) -> 0 | O13: =SUM(I13:N13) -> 0 | V13: =SUM(P13:U13) -> 0 | AC13: =SUM(W13:AB13) -> 0 | AH13: =SUM(AD13:AG13) -> 0 | AI13: =+H13+O13+V13+AH13 -> 0
A14: =1+A13 -> 7 | B14: Franz Carlos Alanez Flores | C14: El Alto | H14: =SUM(D14:G14) -> 0 | O14: =SUM(I14:N14) -> 0 | V14: =SUM(P14:U14) -> 0 | AC14: =SUM(W14:AB14) -> 0 | AH14: =SUM(AD14:AG14) -> 0 | AI14: =+H14+O14+V14+AH14 -> 0
A15: =1+A14 -> 8 | B15: Andrés Miguel Paniagua | C15: Oruro | H15: =SUM(D15:G15) -> 0 | O15: =SUM(I15:N15) -> 0 | V15: =SUM(P15:U15) -> 0 | AC15: =SUM(W15:AB15) -> 0 | AH15: =SUM(AD15:AG15) -> 0 | AI15: =+H15+O15+V15+AH15 -> 0
A16: =1+A15 -> 9 | B16: Alex Rolando Fernandez H. | C16: Oruro | H16: =SUM(D16:G16) -> 0 | O16: =SUM(I16:N16) -> 0 | V16: =SUM(P16:U16) -> 0 | AC16: =SUM(W16:AB16) -> 0 | AH16: =SUM(AD16:AG16) -> 0 | AI16: =+H16+O16+V16+AH16 -> 0
A17: =1+A16 -> 10 | B17: Franklin Ever Viveros | C17: Potosí | H17: =SUM(D17:G17) -> 0 | O17: =SUM(I17:N17) -> 0 | V17: =SUM(P17:U17) -> 0 | AC17: =SUM(W17:AB17) -> 0 | AH17: =SUM(AD17:AG17) -> 0 | AI17: =+H17+O17+V17+AH17 -> 0
A18: =1+A17 -> 11 | B18: Teofilo Ibañez Soliz | C18: Tarija | H18: =SUM(D18:G18) -> 0 | O18: =SUM(I18:N18) -> 0 | V18: =SUM(P18:U18) -> 0 | AC18: =SUM(W18:AB18) -> 0 | AH18: =SUM(AD18:AG18) -> 0 | AI18: =+H18+O18+V18+AH18 -> 0
A19: =1+A18 -> 12 | B19: Elsa Romay Padilla | C19: Uyuni | H19: =SUM(D19:G19) -> 0 | O19: =SUM(I19:N19) -> 0 | V19: =SUM(P19:U19) -> 0 | AC19: =SUM(W19:AB19) -> 0 | AH19: =SUM(AD19:AG19) -> 0 | AI19: =+H19+O19+V19+AH19 -> 0
A20: =1+A19 -> 13 | B20: Jorge Luis Vedia Arancibia | C20: Chuquisaca - Prov | H20: =SUM(D20:G20) -> 0 | O20: =SUM(I20:N20) -> 0 | V20: =SUM(P20:U20) -> 0 | AC20: =SUM(W20:AB20) -> 0 | AH20: =SUM(AD20:AG20) -> 0 | AI20: =+H20+O20+V20+AH20 -> 0
A21: =1+A20 -> 14 | B21: Celina Cruz Mendez | C21: Chuquisaca - Prov | H21: =SUM(D21:G21) -> 0 | O21: =SUM(I21:N21) -> 0 | V21: =SUM(P21:U21) -> 0 | AC21: =SUM(W21:AB21) -> 0 | AH21: =SUM(AD21:AG21) -> 0 | AI21: =+H21+O21+V21+AH21 -> 0
A22: =1+A28 -> 20 | B22: Marlene Paicho | C22: Ruta Colquechaca | H22: =SUM(D22:G22) -> 0 | O22: =SUM(I22:N22) -> 0 | V22: =SUM(P22:U22) -> 0 | AC22: =SUM(W22:AB22) -> 0 | AH22: =SUM(AD22:AG22) -> 0 | AI22: =H22+O22+V22+AH22 -> 0
A23: TOTAL CLIENTES MOROSOS | G23: =SUM(G8:G22) -> 0 | H23: =SUM(D23:G23) -> 0 | I23: =SUM(I8:I22) -> 0 | J23: =SUM(J8:J22) -> 0 | K23: =SUM(K8:K22) -> 0 | L23: =SUM(L8:L22) -> 0 | M23: =SUM(M8:M22) -> 0 | N23: =SUM(N8:N22) -> 0 | O23: =SUM(I23:N23) -> 0 | P23: =SUM(P8:P22) -> 0 | Q23: =SUM(Q8:Q22) -> 0 | R23: =SUM(R8:R22) -> 0 | S23: =SUM(S8:S22) -> 0 | T23: =SUM(T8:T22) -> 0 | U23: =SUM(U8:U22) -> 0 | V23: =SUM(P23:U23) -> 0 | W23: =SUM(W8:W22) -> 0 | X23: =SUM(X8:X22) -> 0 | Y23: =SUM(Y8:Y22) -> 0 | Z23: =SUM(Z8:Z22) -> 0 | AA23: =SUM(AA8:AA22) -> 0 | AB23: =SUM(AB8:AB22) -> 0 | AC23: =SUM(W23:AB23) -> 0 | AD23: =SUM(AD8:AD22) -> 0 | AG23: =SUM(AG8:AG22) -> 0 | AH23: =SUM(AD23:AG23) -> 0 | AI23: =SUM(AI8:AI22) -> 0
A24: =1+A21 -> 15 | B24: EMAPA NACIONAL | C24: NACIONAL | H24: =SUM(D24:G24) -> 0 | O24: =SUM(I24:N24) -> 0 | V24: =SUM(P24:U24) -> 0 | AC24: =SUM(W24:AB24) -> 0 | AH24: =SUM(AD24:AG24) -> 0 | AI24: =H24+O24+V24+AC24+AH24 -> 0
A25: =1+A24 -> 16 | B25: Gustavo Tellez Ugarte | C25: Santa Cruz | H25: =SUM(D25:G25) -> 0 | O25: =SUM(I25:N25) -> 0 | V25: =SUM(P25:U25) -> 0 | AC25: =SUM(W25:AB25) -> 0 | AG25: 84701 | AH25: =SUM(AD25:AG25) -> 84701 | AI25: =H25+O25+V25+AC25+AH25 -> 84701
A26: =1+A25 -> 17 | B26: Cristhian Murillo | C26: Sucre | H26: =SUM(D26:G26) -> 0 | O26: =SUM(I26:N26) -> 0 | V26: =SUM(P26:U26) -> 0 | AC26: =SUM(W26:AB26) -> 0 | AG26: 325114.12 | AH26: =SUM(AD26:AG26) -> 325114.12 | AI26: =H26+O26+V26+AC26+AH26 -> 325114.12
A27: =1+A26 -> 18 | B27: Sebastian Miranda | C27: Oruro | H27: =SUM(D27:G27) -> 0 | O27: =SUM(I27:N27) -> 0 | V27: =SUM(P27:U27) -> 0 | AC27: =SUM(W27:AB27) -> 0 | AH27: =SUM(AD27:AG27) -> 0 | AI27: =H27+O27+V27+AC27+AH27 -> 0
A28: =1+A27 -> 19 | B28: Norha Choque Talavera | C28: Potosí | H28: =SUM(D28:G28) -> 0 | O28: =SUM(I28:N28) -> 0 | V28: =SUM(P28:U28) -> 0 | AC28: =SUM(W28:AB28) -> 0 | AH28: =SUM(AD28:AG28) -> 0 | AI28: =H28+O28+V28+AC28+AH28 -> 0
A29: =1+A28 -> 20 | B29: Orlando Aldunate M. | C29: Tarija | H29: =SUM(D29:G29) -> 0 | O29: =SUM(I29:N29) -> 0 | V29: =SUM(P29:U29) -> 0 | AC29: =SUM(W29:AB29) -> 0 | AH29: =SUM(AD29:AG29) -> 0 | AI29: =H29+O29+V29+AC29+AH29 -> 0
A30: =1+A29 -> 21 | B30: Fausto Condori | C30: Cochabamba | H30: =SUM(D30:G30) -> 0 | O30: =SUM(I30:N30) -> 0 | V30: =SUM(P30:U30) -> 0 | AC30: =SUM(W30:AB30) -> 0 | AH30: =SUM(AD30:AG30) -> 0 | AI30: =H30+O30+V30+AC30+AH30 -> 0
A31: =1+A30 -> 22 | B31: Flora Yapuchura | C31: La Paz | H31: =SUM(D31:G31) -> 0 | O31: =SUM(I31:N31) -> 0 | V31: =SUM(P31:U31) -> 0 | AC31: =SUM(W31:AB31) -> 0 | AH31: =SUM(AD31:AG31) -> 0 | AI31: =H31+O31+V31+AC31+AH31 -> 0
A32: =1+A31 -> 23 | B32: Willy Quispe | C32: El Alto | H32: =SUM(D32:G32) -> 0 | O32: =SUM(I32:N32) -> 0 | V32: =SUM(P32:U32) -> 0 | AC32: =SUM(W32:AB32) -> 0 | AH32: =SUM(AD32:AG32) -> 0 | AI32: =H32+O32+V32+AC32+AH32 -> 0
A33: =1+A32 -> 24 | B33: Andrez Lopez | C33: Potosí | H33: =SUM(D33:G33) -> 0 | O33: =SUM(I33:N33) -> 0 | V33: =SUM(P33:U33) -> 0 | AC33: =SUM(W33:AB33) -> 0 | AH33: =SUM(AD33:AG33) -> 0 | AI33: =H33+O33+V33+AC33+AH33 -> 0
A34: =1+A33 -> 25 | B34: Miguel Angel Mora | C34: Potosí | H34: =SUM(D34:G34) -> 0 | O34: =SUM(I34:N34) -> 0 | V34: =SUM(P34:U34) -> 0 | AC34: =SUM(W34:AB34) -> 0 | AH34: =SUM(AD34:AG34) -> 0 | AI34: =H34+O34+V34+AC34+AH34 -> 0
A35: =1+A34 -> 26 | B35: GAMS Desarrollo Productivo | C35: Sucre | H35: =SUM(D35:G35) -> 0 | O35: =SUM(I35:N35) -> 0 | V35: =SUM(P35:U35) -> 0 | AC35: =SUM(W35:AB35) -> 0 | AH35: =SUM(AD35:AG35) -> 0 | AI35: =H35+O35+V35+AC35+AH35 -> 0
A36: =1+A35 -> 27 | B36: GAMS Direccion Administrativa | C36: Sucre | H36: =SUM(D36:G36) -> 0 | O36: =SUM(I36:N36) -> 0 | V36: =SUM(P36:U36) -> 0 | AC36: =SUM(W36:AB36) -> 0 | AH36: =SUM(AD36:AG36) -> 0 | AI36: =H36+O36+V36+AC36+AH36 -> 0
A37: =1+A36 -> 28 | B37: Carmen Cruz | C37: Potosí | H37: =SUM(D37:G37) -> 0 | O37: =SUM(I37:N37) -> 0 | V37: =SUM(P37:U37) -> 0 | AC37: =SUM(W37:AB37) -> 0 | AG37: 210671 | AH37: =SUM(AD37:AG37) -> 210671 | AI37: =H37+O37+V37+AC37+AH37 -> 210671
A38: =1+A37 -> 29 | B38: Judith | C38: Cochabamba | H38: =SUM(D38:G38) -> 0 | O38: =SUM(I38:N38) -> 0 | V38: =SUM(P38:U38) -> 0 | AC38: =SUM(W38:AB38) -> 0 | AH38: =SUM(AD38:AG38) -> 0 | AI38: =H38+O38+V38+AC38+AH38 -> 0
A39: =1+A38 -> 30 | B39: Kevin | C39: Oruro | H39: =SUM(D39:G39) -> 0 | O39: =SUM(I39:N39) -> 0 | V39: =SUM(P39:U39) -> 0 | AC39: =SUM(W39:AB39) -> 0 | AH39: =SUM(AD39:AG39) -> 0 | AI39: =H39+O39+V39+AC39+AH39 -> 0
A40: =1+A39 -> 31 | B40: Jorge Saavedra | C40: Tupiza | H40: =SUM(D40:G40) -> 0 | O40: =SUM(I40:N40) -> 0 | V40: =SUM(P40:U40) -> 0 | AC40: =SUM(W40:AB40) -> 0 | AH40: =SUM(AD40:AG40) -> 0 | AI40: =H40+O40+V40+AC40+AH40 -> 0
A41: =1+A40 -> 32 | B41: Jenrry | C41: Chile | H41: =SUM(D41:G41) -> 0 | O41: =SUM(I41:N41) -> 0 | V41: =SUM(P41:U41) -> 0 | AC41: =SUM(W41:AB41) -> 0 | AH41: =SUM(AD41:AG41) -> 0 | AI41: =H41+O41+V41+AC41+AH41 -> 0
A42: =1+A41 -> 33 | B42: Eddy | C42: Chile | H42: =SUM(D42:G42) -> 0 | O42: =SUM(I42:N42) -> 0 | V42: =SUM(P42:U42) -> 0 | AC42: =SUM(W42:AB42) -> 0 | AH42: =SUM(AD42:AG42) -> 0 | AI42: =H42+O42+V42+AC42+AH42 -> 0
A43: =1+A42 -> 34 | B43: Rene Cahuana | C43: La Paz | H43: =SUM(D43:G43) -> 0 | O43: =SUM(I43:N43) -> 0 | V43: =SUM(P43:U43) -> 0 | AC43: =SUM(W43:AB43) -> 0 | AG43: 136062 | AH43: =SUM(AD43:AG43) -> 136062 | AI43: =H43+O43+V43+AC43+AH43 -> 136062
A44: =1+A43 -> 35 | B44: Ines Aguirre | C44: Provincias Villazon | H44: =SUM(D44:G44) -> 0 | O44: =SUM(I44:N44) -> 0 | V44: =SUM(P44:U44) -> 0 | AC44: =SUM(W44:AB44) -> 0 | AH44: =SUM(AD44:AG44) -> 0 | AI44: =H44+O44+V44+AC44+AH44 -> 0
A45: =1+A44 -> 36 | B45: Yobana Llanos Cruz | C45: Ruta Chapare | H45: =SUM(D45:G45) -> 0 | O45: =SUM(I45:N45) -> 0 | V45: =SUM(P45:U45) -> 0 | AC45: =SUM(W45:AB45) -> 0 | AH45: =SUM(AD45:AG45) -> 0 | AI45: =H45+O45+V45+AC45+AH45 -> 0
A46: =1+A45 -> 37 | B46: Hernan Colque Cruz | C46: Pisiga | H46: =SUM(D46:G46) -> 0 | O46: =SUM(I46:N46) -> 0 | V46: =SUM(P46:U46) -> 0 | AC46: =SUM(W46:AB46) -> 0 | AG46: 41323 | AH46: =SUM(AD46:AG46) -> 41323 | AI46: =H46+O46+V46+AC46+AH46 -> 41323
A47: =1+A46 -> 38 | B47: Roxana Yanet Castrillo Vasco | C47: Bermejo | H47: =SUM(D47:G47) -> 0 | O47: =SUM(I47:N47) -> 0 | V47: =SUM(P47:U47) -> 0 | AC47: =SUM(W47:AB47) -> 0 | AH47: =SUM(AD47:AG47) -> 0 | AI47: =H47+O47+V47+AC47+AH47 -> 0
A48: =1+A47 -> 39 | B48: Ismael Marca | C48: Uyuni | H48: =SUM(D48:G48) -> 0 | O48: =SUM(I48:N48) -> 0 | V48: =SUM(P48:U48) -> 0 | AC48: =SUM(W48:AB48) -> 0 | AG48: 65100 | AH48: =SUM(AD48:AG48) -> 65100 | AI48: =H48+O48+V48+AC48+AH48 -> 65100
A49: =1+A48 -> 40 | B49: Freddy Alcocer Mollo | C49: Oruro | H49: =SUM(D49:G49) -> 0 | AH49: =SUM(AD49:AG49) -> 0 | AI49: =H49+O49+V49+AC49+AH49 -> 0
A50: =1+A49 -> 41 | B50: David Choque - Katerine | C50: Oruro Provincia | H50: =SUM(D50:G50) -> 0 | AG50: 85050 | AH50: =SUM(AD50:AG50) -> 85050 | AI50: =H50+O50+V50+AC50+AH50 -> 85050
A51: =1+A50 -> 42 | B51: Nilda | C51: CBBA Provincia | H51: =SUM(D51:G51) -> 0 | AH51: =SUM(AD51:AG51) -> 0 | AI51: =H51+O51+V51+AC51+AH51 -> 0
A52: =1+A51 -> 43 | B52: Divar Aranibar Plata | C52: Oruro | AH52: =SUM(AD52:AG52) -> 0 | AI52: =H52+O52+V52+AC52+AH52 -> 0
A53: =1+A52 -> 44 | B53: Ruth Gabriela | C53: Pando | AH53: =SUM(AD53:AG53) -> 0 | AI53: =H53+O53+V53+AC53+AH53 -> 0
A54: =1+A53 -> 45 | B54: Sergio Romero | C54: Sucre | AH54: =SUM(AD54:AG54) -> 0 | AI54: =H54+O54+V54+AC54+AH54 -> 0
A55: =1+A54 -> 46 | B55: Jorge Cruz | C55: Chile | H55: =SUM(D55:G55) -> 0 | O55: =SUM(I55:N55) -> 0 | V55: =SUM(P55:U55) -> 0 | AC55: =SUM(W55:AB55) -> 0 | AH55: =SUM(AD55:AG55) -> 0 | AI55: =H55+O55+V55+AC55+AH55 -> 0
A56: =1+A55 -> 47 | B56: Javier Mercado | C56: El Alto | AH56: =SUM(AD56:AG56) -> 0 | AI56: =H56+O56+V56+AC56+AH56 -> 0
A57: =1+A56 -> 48 | B57: Yaneth Miriam Toroya Gabriel | C57: Oruro | AG57: 199709 | AH57: =SUM(AD57:AG57) -> 199709 | AI57: =H57+O57+V57+AC57+AH57 -> 199709
A58: =1+A57 -> 49 | B58: Grupo ULTRA Sta Cruz | C58: Santa Cruz | AG58: 273000 | AH58: =SUM(AD58:AG58) -> 273000 | AI58: =H58+O58+V58+AC58+AH58 -> 273000
A59: =1+A58 -> 50 | B59: Alexander Vides | C59: Tarija | AG59: 146450 | AH59: =SUM(AD59:AG59) -> 146450 | AI59: =H59+O59+V59+AC59+AH59 -> 146450
A60: =1+A59 -> 51 | B60: Paul Yamani | C60: Cochabamba | AH60: =SUM(AD60:AG60) -> 0 | AI60: =H60+O60+V60+AC60+AH60 -> 0
A61: =1+A60 -> 52 | B61: Silvia Gomez | C61: Huanuni | H61: =SUM(D61:G61) -> 0 | O61: =SUM(I61:N61) -> 0 | V61: =SUM(P61:U61) -> 0 | AC61: =SUM(W61:AB61) -> 0 | AH61: =SUM(AD61:AG61) -> 0 | AI61: =H61+O61+V61+AC61+AH61 -> 0
A62: =1+A61 -> 53 | B62: Alejandro Luna | C62: Chile | AH62: =SUM(AD62:AG62) -> 0 | AI62: =H62+O62+V62+AC62+AH62 -> 0
A63: =1+A62 -> 54 | B63: Sandra Gutierrez Quispe | C63: Chile | AH63: =SUM(AD63:AG63) -> 0 | AI63: =H63+O63+V63+AC63+AH63 -> 0
A64: =1+A63 -> 55 | B64: Venta colillas y otros | C64: Sucre | H64: =SUM(D64:G64) -> 0 | O64: =SUM(I64:N64) -> 0 | V64: =SUM(P64:U64) -> 0 | AC64: =SUM(W64:AB64) -> 0 | AG64: 14129.52 | AH64: =SUM(AD64:AG64) -> 14129.52 | AI64: =H64+O64+V64+AC64+AH64 -> 14129.52
A65: =1+A64 -> 56 | B65: FEXPO 2025 | C65: Sucre | AH65: =SUM(AD65:AG65) -> 0 | AI65: =H65+O65+V65+AC65+AH65 -> 0
A66: =1+A64 -> 56 | B66: Ventas en FABRICA | C66: Sucre | H66: =SUM(D66:G66) -> 0 | O66: =SUM(I66:N66) -> 0 | V66: =SUM(P66:U66) -> 0 | AC66: =SUM(W66:AB66) -> 0 | AG66: 11353 | AH66: =SUM(AD66:AG66) -> 11353 | AI66: =H66+O66+V66+AC66+AH66 -> 11353
A67: TOTALE CLIENTES ACTIVOS | G67: =SUM(G24:G66) -> 0 | H67: =SUM(D67:G67) -> 0 | I67: =SUM(I24:I66) -> 0 | J67: =SUM(J24:J66) -> 0 | K67: =SUM(K24:K66) -> 0 | L67: =SUM(L24:L66) -> 0 | M67: =SUM(M24:M66) -> 0 | N67: =SUM(N24:N66) -> 0 | O67: =SUM(I67:N67) -> 0 | P67: =SUM(P24:P66) -> 0 | Q67: =SUM(Q24:Q66) -> 0 | R67: =SUM(R24:R66) -> 0 | S67: =SUM(S24:S66) -> 0 | T67: =SUM(T24:T66) -> 0 | U67: =SUM(U24:U66) -> 0 | V67: =SUM(P67:U67) -> 0 | W67: =SUM(W24:W66) -> 0 | X67: =SUM(X24:X66) -> 0 | Y67: =SUM(Y24:Y66) -> 0 | Z67: =SUM(Z24:Z66) -> 0 | AA67: =SUM(AA24:AA66) -> 0 | AB67: =SUM(AB24:AB66) -> 0 | AC67: =SUM(W67:AB67) -> 0 | AD67: =SUM(AD24:AD66) -> 0 | AE67: =SUM(AE24:AE66) -> 0 | AF67: =SUM(AF24:AF66) -> 0 | AG67: =SUM(AG24:AG66) -> 1592662.6 | AH67: =SUM(AD67:AG67) -> 1592662.6 | AI67: =SUM(AI24:AI66) -> 1592662.6
A68: TOTALE CLIENTES | D68: =+D23+D67 -> 0 | E68: =+E23+E67 -> 0 | F68: =+F23+F67 -> 0 | G68: =+G23+G67 -> 0 | H68: =SUM(D68:G68) -> 0 | I68: =+I23+I67 -> 0 | J68: =+J23+J67 -> 0 | K68: =+K23+K67 -> 0 | L68: =+L23+L67 -> 0 | M68: =+M23+M67 -> 0 | N68: =+N23+N67 -> 0 | O68: =SUM(I68:N68) -> 0 | P68: =+P23+P67 -> 0 | Q68: =+Q23+Q67 -> 0 | R68: =+R23+R67 -> 0 | S68: =+S23+S67 -> 0 | T68: =+T23+T67 -> 0 | U68: =+U23+U67 -> 0 | V68: =SUM(P68:U68) -> 0 | W68: =+W23+W67 -> 0 | X68: =+X23+X67 -> 0 | Y68: =+Y23+Y67 -> 0 | Z68: =+Z23+Z67 -> 0 | AA68: =+AA23+AA67 -> 0 | AB68: =+AB23+AB67 -> 0 | AC68: =SUM(W68:AB68) -> 0 | AD68: =+AD23+AD67 -> 0 | AH68: =SUM(AD68:AG68) -> 0 | AI68: =SUM(AI67,AI23) -> 1592662.6

Sheet CXC
A3: CUENTAS POR COBRAR A CLIENTES
A4: GESTION 2023 - 2024
A6: Nº | B6: DISTRIBUIDOR | C6: DEPARTAMENTO | D6: MONTO DE DESPACHO | E6: DEPOSITOS | F6: SALDO POR COBRAR | G6: OBSERVACION
A7: =1+#REF! -> #REF! | B7: Gustavo Tellez Ugarte | C7: Santa Cruz | D7: =+'Gustavo Tellez'!E69 -> 170675 | E7: =+'Gustavo Tellez'!F69 -> 170675 | F7: =+D7-E7 -> 0
A8: =1+A7 -> #REF! | B8: Cristhian Murillo | C8: Sucre | D8: =+'Cristhian Murillo'!E166 -> 1827705.1 | E8: =+'Cristhian Murillo'!F166 -> 1827705.1 | F8: =+D8-E8 -> 0
A9: 1 | B9: Oscar Hugo Garzofino Catacora (Paceña) | C9: Sucre | D9: =+'Oscar G. Paceña SUCRE'!E24 -> 17400 | E9: =+'Oscar G. Paceña SUCRE'!F24 -> 17400 | F9: =+D9-E9 -> 0
A10: 2 | B10: Carlos Eduardo Gutierrez - Ambulante | C10: Sucre | D10: =+'Ambulante EDUARDO'!E50 -> 25014 | E10: =+'Ambulante EDUARDO'!F50 -> 24474 | F10: =+D10-E10 -> 540
A11: 3 | B11: Supermercado SAS | C11: Sucre | D11: =+'Supermencado SAS'!E61 -> 160473 | E11: =+'Supermencado SAS'!F61 -> 150005 | F11: =+D11-E11 -> 10468
A12: 4 | B12: SOLAR Supermercado | C12: Sucre | D12: =+'SOLAR Supermercado'!E24 -> 27886 | E12: =+'SOLAR Supermercado'!F24 -> 24586 | F12: =+D12-E12 -> 3300
A13: 5 | B13: LIDER Supermercado | C13: Sucre | D13: =+'LIDER Supermercado'!E24 -> 4086 | E13: =+'LIDER Supermercado'!F24 -> 4086 | F13: =+D13-E13 -> 0
A14: 6 | B14: MERCAMAX S.R.L. | C14: Sucre | D14: =+'MERCAMAX SRL'!E24 -> 15940 | E14: =+'MERCAMAX SRL'!F24 -> 13396 | F14: =+D14-E14 -> 2544
A15: 7 | B15: Farmacia San Agustin | C15: Sucre | D15: =+'FARMACIA SAN AGUSTIN'!E25 -> 11632 | E15: =+'FARMACIA SAN AGUSTIN'!F25 -> 11632 | F15: =+D15-E15 -> 0
A16: 8 | B16: Supermercado POMPEYA | C16: Sucre | D16: =+'Supermercado POMPEYA'!E24 -> 43864 | E16: =+'Supermercado POMPEYA'!F24 -> 43864 | F16: =+D16-E16 -> 0
A17: 9 | B17: Pulperia San Francisco | C17: Sucre | D17: =+'Pulperia USFX'!E24 -> 10805 | E17: =+'Pulperia USFX'!F24 -> 10805 | F17: =+D17-E17 -> 0
A18: 10 | B18: GAMS | C18: Sucre | D18: =+GAMS!E30 -> 99410 | E18: =+GAMS!F30 -> 99410 | F18: =+D18-E18 -> 0
A19: TOTAL CLIENTES ACTIVOS | D19: =SUM(D9:D18) -> 416510 | E19: =SUM(E9:E18) -> 399658 | F19: =SUM(F9:F18) -> 16852
E22: POR COBRAR | F22: =+F19 -> 16852

Sheet RECAU. Diciembre 2025
A3: CUENTAS POR COBRAR A CLIENTES
A4: GESTION 2023 - 2024
A5: DICIEMBRE- 2025
A6: Nº | B6: DISTRIBUIDOR | C6: DEPARTAMENTO | AI6: TOTAL MES
D7: 1 | E7: 2 | F7: 3 | G7: 4 | H7: Semana 1 | I7: 6 | J7: 7 | K7: 8 | L7: 9 | M7: 10 | N7: 11 | O7: Semana 2 | P7: 13 | Q7: 14 | R7: 15 | S7: 16 | T7: 17 | U7: 18 | V7: Semana 3 | W7: 20 | X7: 21 | Y7: 22 | Z7: 23 | AA7: 24 | AB7: 25 | AC7: Semana 4 | AD7: 27 | AE7: 28 | AF7: 29 | AG7: 31 | AH7: Semana 4
A8: 1 | B8: Fabricio Tapia Castedo | C8: Cochabamba | H8: =SUM(D8:G8) -> 0 | O8: =SUM(I8:N8) -> 0 | V8: =SUM(P8:U8) -> 0 | AC8: =SUM(W8:AB8) -> 0 | AH8: =SUM(AD8:AG8) -> 0 | AI8: =+H8+O8+V8+AH8 -> 0
A9: =1+A8 -> 2 | B9: Edwin Fernandez Chirinos | C9: El Alto | H9: =SUM(D9:G9) -> 0 | O9: =SUM(I9:N9) -> 0 | V9: =SUM(P9:U9) -> 0 | AC9: =SUM(W9:AB9) -> 0 | AH9: =SUM(AD9:AG9) -> 0 | AI9: =+H9+O9+V9+AH9 -> 0
A10: =1+A9 -> 3 | B10: Javier Caceres | C10: Cochabamba | H10: =SUM(D10:G10) -> 0 | O10: =SUM(I10:N10) -> 0 | V10: =SUM(P10:U10) -> 0 | AC10: =SUM(W10:AB10) -> 0 | AH10: =SUM(AD10:AG10) -> 0 | AI10: =+H10+O10+V10+AH10 -> 0
A11: =1+A10 -> 4 | B11: Juan Carlos Torrez Ayarde | C11: Tarija | H11: =SUM(D11:G11) -> 0 | O11: =SUM(I11:N11) -> 0 | V11: =SUM(P11:U11) -> 0 | AC11: =SUM(W11:AB11) -> 0 | AH11: =SUM(AD11:AG11) -> 0 | AI11: =+H11+O11+V11+AH11 -> 0
A12: =1+A11 -> 5 | B12: Carol Alejandra Noya | C12: Tarija | H12: =SUM(D12:G12) -> 0 | O12: =SUM(I12:N12) -> 0 | V12: =SUM(P12:U12) -> 0 | AC12: =SUM(W12:AB12) -> 0 | AH12: =SUM(AD12:AG12) -> 0 | AI12: =+H12+O12+V12+AH12 -> 0
A13: =1+A12 -> 6 | B13: Luis Alberto Chipana Peña | C13: Cochabamba | H13: =SUM(D13:G13) -> 0 | O13: =SUM(I13:N13) -> 0 | V13: =SUM(P13:U13) -> 0 | AC13: =SUM(W13:AB13) -> 0 | AH13: =SUM(AD13:AG13) -> 0 | AI13: =+H13+O13+V13+AH13 -> 0
A14: =1+A13 -> 7 | B14: Franz Carlos Alanez Flores | C14: El Alto | H14: =SUM(D14:G14) -> 0 | O14: =SUM(I14:N14) -> 0 | V14: =SUM(P14:U14) -> 0 | AC14: =SUM(W14:AB14) -> 0 | AH14: =SUM(AD14:AG14) -> 0 | AI14: =+H14+O14+V14+AH14 -> 0
A15: =1+A14 -> 8 | B15: Andrés Miguel Paniagua | C15: Oruro | H15: =SUM(D15:G15) -> 0 | O15: =SUM(I15:N15) -> 0 | V15: =SUM(P15:U15) -> 0 | AC15: =SUM(W15:AB15) -> 0 | AH15: =SUM(AD15:AG15) -> 0 | AI15: =+H15+O15+V15+AH15 -> 0
A16: =1+A15 -> 9 | B16: Alex Rolando Fernandez H. | C16: Oruro | H16: =SUM(D16:G16) -> 0 | O16: =SUM(I16:N16) -> 0 | V16: =SUM(P16:U16) -> 0 | AC16: =SUM(W16:AB16) -> 0 | AH16: =SUM(AD16:AG16) -> 0 | AI16: =+H16+O16+V16+AH16 -> 0
A17: =1+A16 -> 10 | B17: Franklin Ever Viveros | C17: Potosí | H17: =SUM(D17:G17) -> 0 | O17: =SUM(I17:N17) -> 0 | V17: =SUM(P17:U17) -> 0 | AC17: =SUM(W17:AB17) -> 0 | AH17: =SUM(AD17:AG17) -> 0 | AI17: =+H17+O17+V17+AH17 -> 0
A18: =1+A17 -> 11 | B18: Teofilo Ibañez Soliz | C18: Tarija | H18: =SUM(D18:G18) -> 0 | O18: =SUM(I18:N18) -> 0 | V18: =SUM(P18:U18) -> 0 | AC18: =SUM(W18:AB18) -> 0 | AH18: =SUM(AD18:AG18) -> 0 | AI18: =+H18+O18+V18+AH18 -> 0
A19: =1+A18 -> 12 | B19: Elsa Romay Padilla | C19: Uyuni | H19: =SUM(D19:G19) -> 0 | O19: =SUM(I19:N19) -> 0 | V19: =SUM(P19:U19) -> 0 | AC19: =SUM(W19:AB19) -> 0 | AH19: =SUM(AD19:AG19) -> 0 | AI19: =+H19+O19+V19+AH19 -> 0
A20: =1+A19 -> 13 | B20: Jorge Luis Vedia Arancibia | C20: Chuquisaca - Prov | H20: =SUM(D20:G20) -> 0 | O20: =SUM(I20:N20) -> 0 | V20: =SUM(P20:U20) -> 0 | AC20: =SUM(W20:AB20) -> 0 | AH20: =SUM(AD20:AG20) -> 0 | AI20: =+H20+O20+V20+AH20 -> 0
A21: =1+A20 -> 14 | B21: Celina Cruz Mendez | C21: Chuquisaca - Prov | H21: =SUM(D21:G21) -> 0 | O21: =SUM(I21:N21) -> 0 | V21: =SUM(P21:U21) -> 0 | AC21: =SUM(W21:AB21) -> 0 | AH21: =SUM(AD21:AG21) -> 0 | AI21: =+H21+O21+V21+AH21 -> 0
A22: 15 | B22: Marlene Paicho | C22: Ruta Colquechaca | H22: =SUM(D22:G22) -> 0 | O22: =SUM(I22:N22) -> 0 | V22: =SUM(P22:U22) -> 0 | AC22: =SUM(W22:AB22) -> 0 | AH22: =SUM(AD22:AG22) -> 0 | AI22: =H22+O22+V22+AH22 -> 0
A23: TOTAL CLIENTES MOROSOS | G23: =SUM(G8:G22) -> 0 | H23: =SUM(D23:G23) -> 0 | I23: =SUM(I8:I22) -> 0 | J23: =SUM(J8:J22) -> 0 | K23: =SUM(K8:K22) -> 0 | L23: =SUM(L8:L22) -> 0 | M23: =SUM(M8:M22) -> 0 | N23: =SUM(N8:N22) -> 0 | O23: =SUM(I23:N23) -> 0 | P23: =SUM(P8:P22) -> 0 | Q23: =SUM(Q8:Q22) -> 0 | R23: =SUM(R8:R22) -> 0 | S23: =SUM(S8:S22) -> 0 | T23: =SUM(T8:T22) -> 0 | U23: =SUM(U8:U22) -> 0 | V23: =SUM(P23:U23) -> 0 | W23: =SUM(W8:W22) -> 0 | X23: =SUM(X8:X22) -> 0 | Y23: =SUM(Y8:Y22) -> 0 | Z23: =SUM(Z8:Z22) -> 0 | AA23: =SUM(AA8:AA22) -> 0 | AB23: =SUM(AB8:AB22) -> 0 | AC23: =SUM(W23:AB23) -> 0 | AD23: =SUM(AD8:AD22) -> 0 | AG23: =SUM(AG8:AG22) -> 0 | AH23: =SUM(AD23:AG23) -> 0 | AI23: =SUM(AI8:AI22) -> 0
A24: 1 | B24: Gustavo Tellez Ugarte | C24: Santa Cruz | H24: =SUM(D24:G24) -> 0 | O24: =SUM(I24:N24) -> 0 | V24: =SUM(P24:U24) -> 0 | AC24: =SUM(W24:AB24) -> 0 | AH24: =SUM(AD24:AG24) -> 0 | AI24: =H24+O24+V24+AC24+AH24 -> 0
A25: =1+A24 -> 2 | B25: Cristhian Murillo | C25: Sucre | H25: =SUM(D25:G25) -> 0 | O25: =SUM(I25:N25) -> 0 | V25: =SUM(P25:U25) -> 0 | AC25: =SUM(W25:AB25) -> 0 | AH25: =SUM(AD25:AG25) -> 0 | AI25: =H25+O25+V25+AC25+AH25 -> 0
A26: =1+A25 -> 3 | B26: Orlando Aldunate M. | C26: Tarija | H26: =SUM(D26:G26) -> 0 | O26: =SUM(I26:N26) -> 0 | V26: =SUM(P26:U26) -> 0 | AC26: =SUM(W26:AB26) -> 0 | AH26: =SUM(AD26:AG26) -> 0 | AI26: =H26+O26+V26+AC26+AH26 -> 0
A27: =1+A26 -> 4 | B27: Ventas Directas de Fabrica | C27: Sucre | H27: =SUM(D27:G27) -> 0 | O27: =SUM(I27:N27) -> 0 | V27: =SUM(P27:U27) -> 0 | AC27: =SUM(W27:AB27) -> 0 | AG27: 115313.5 | AH27: =SUM(AD27:AG27) -> 115313.5 | AI27: =H27+O27+V27+AC27+AH27 -> 115313.5
A28: =1+A27 -> 5 | B28: Carlos Eduardo Gutierrez - Ambulante | C28: Sucre | H28: =SUM(D28:G28) -> 0 | O28: =SUM(I28:N28) -> 0 | V28: =SUM(P28:U28) -> 0 | AC28: =SUM(W28:AB28) -> 0 | AG28: 5240 | AH28: =SUM(AD28:AG28) -> 5240 | AI28: =H28+O28+V28+AC28+AH28 -> 5240
A29: =1+A28 -> 6 | B29: Supermercado SAS | C29: Sucre | H29: =SUM(D29:G29) -> 0 | O29: =SUM(I29:N29) -> 0 | V29: =SUM(P29:U29) -> 0 | AC29: =SUM(W29:AB29) -> 0 | AG29: 4915 | AH29: =SUM(AD29:AG29) -> 4915 | AI29: =H29+O29+V29+AC29+AH29 -> 4915
A30: =1+A29 -> 7 | B30: SOLAR Supermercado | C30: Sucre | H30: =SUM(D30:G30) -> 0 | O30: =SUM(I30:N30) -> 0 | V30: =SUM(P30:U30) -> 0 | AC30: =SUM(W30:AB30) -> 0 | AG30: 4038 | AH30: =SUM(AD30:AG30) -> 4038 | AI30: =H30+O30+V30+AC30+AH30 -> 4038
A31: =1+A30 -> 8 | B31: LIDER Supermercado | C31: Sucre | H31: =SUM(D31:G31) -> 0 | O31: =SUM(I31:N31) -> 0 | V31: =SUM(P31:U31) -> 0 | AC31: =SUM(W31:AB31) -> 0 | AG31: 1978 | AH31: =SUM(AD31:AG31) -> 1978 | AI31: =H31+O31+V31+AC31+AH31 -> 1978
A32: =1+A31 -> 9 | B32: Farmacia San Agustin | C32: Sucre | H32: =SUM(D32:G32) -> 0 | O32: =SUM(I32:N32) -> 0 | V32: =SUM(P32:U32) -> 0 | AC32: =SUM(W32:AB32) -> 0 | AG32: 2812 | AH32: =SUM(AD32:AG32) -> 2812 | AI32: =H32+O32+V32+AC32+AH32 -> 2812
A33: =1+A32 -> 10 | B33: Supermercado POMPEYA | C33: Sucre | H33: =SUM(D33:G33) -> 0 | O33: =SUM(I33:N33) -> 0 | V33: =SUM(P33:U33) -> 0 | AC33: =SUM(W33:AB33) -> 0 | AH33: =SUM(AD33:AG33) -> 0 | AI33: =H33+O33+V33+AC33+AH33 -> 0
A34: =1+A33 -> 11 | B34: Inocencio Cruz | C34: Sucre | H34: =SUM(D34:G34) -> 0 | O34: =SUM(I34:N34) -> 0 | V34: =SUM(P34:U34) -> 0 | AC34: =SUM(W34:AB34) -> 0 | AG34: 268692 | AH34: =SUM(AD34:AG34) -> 268692 | AI34: =H34+O34+V34+AC34+AH34 -> 268692
A35: =1+A34 -> 12 | B35: Ruth Zarate | C35: Sucre | H35: =SUM(D35:G35) -> 0 | O35: =SUM(I35:N35) -> 0 | V35: =SUM(P35:U35) -> 0 | AC35: =SUM(W35:AB35) -> 0 | AG35: 186627.5 | AH35: =SUM(AD35:AG35) -> 186627.5 | AI35: =H35+O35+V35+AC35+AH35 -> 186627.5
A36: =1+A35 -> 13 | B36: Victor Hugo Zarate | C36: Provinci Sucre | H36: =SUM(D36:G36) -> 0 | O36: =SUM(I36:N36) -> 0 | V36: =SUM(P36:U36) -> 0 | AC36: =SUM(W36:AB36) -> 0 | AG36: 45000 | AH36: =SUM(AD36:AG36) -> 45000 | AI36: =H36+O36+V36+AC36+AH36 -> 45000
A37: =1+A36 -> 14 | B37: Fausto Condori | C37: Cochabamba | H37: =SUM(D37:G37) -> 0 | O37: =SUM(I37:N37) -> 0 | V37: =SUM(P37:U37) -> 0 | AC37: =SUM(W37:AB37) -> 0 | AH37: =SUM(AD37:AG37) -> 0 | AI37: =H37+O37+V37+AC37+AH37 -> 0
A38: =1+A37 -> 15 | B38: Beker Rosa Cruz - Carmen | C38: Potosí | AG38: 123529.5 | AH38: =SUM(AD38:AG38) -> 123529.5 | AI38: =H38+O38+V38+AC38+AH38 -> 123529.5
A39: =1+A38 -> 16 | B39: Gobierno Autonomo Municipal de Sucre - Desarrollo Productivo | C39: Sucre | AH39: =SUM(AD39:AG39) -> 0 | AI39: =H39+O39+V39+AC39+AH39 -> 0
A40: =1+A39 -> 17 | B40: Gobierno Autonomo Municipal de Sucre - Dirección Administrativa | C40: Sucre | AH40: =SUM(AD40:AG40) -> 0 | AI40: =H40+O40+V40+AC40+AH40 -> 0
A41: =1+A40 -> 18 | B41: Jenrry | C41: Chile | AH41: =SUM(AD41:AG41) -> 0 | AI41: =H41+O41+V41+AC41+AH41 -> 0
A42: =1+A41 -> 19 | B42: Eddy | C42: Chile | AH42: =SUM(AD42:AG42) -> 0 | AI42: =H42+O42+V42+AC42+AH42 -> 0
A43: =1+A42 -> 20 | B43: Jhaneth Miriam Toroya Gabriel | C43: Oruro | AG43: 119774 | AH43: =SUM(AD43:AG43) -> 119774 | AI43: =H43+O43+V43+AC43+AH43 -> 119774
A44: =1+A43 -> 21 | B44: Miguel Zurita | C44: Tupiza Villazon | AG44: 54712 | AH44: =SUM(AD44:AG44) -> 54712 | AI44: =H44+O44+V44+AC44+AH44 -> 54712
A45: =1+A44 -> 22 | AH45: =SUM(AD45:AG45) -> 0 | AI45: =H45+O45+V45+AC45+AH45 -> 0
A46: =1+A45 -> 23 | AH46: =SUM(AD46:AG46) -> 0 | AI46: =H46+O46+V46+AC46+AH46 -> 0
A47: =1+A46 -> 24 | H47: =SUM(D47:G47) -> 0 | O47: =SUM(I47:N47) -> 0 | V47: =SUM(P47:U47) -> 0 | AC47: =SUM(W47:AB47) -> 0 | AH47: =SUM(AD47:AG47) -> 0 | AI47: =H47+O47+V47+AC47+AH47 -> 0
A48: =1+A47 -> 25 | B48: Ventas en FABRICA | C48: Sucre | H48: =SUM(D48:G48) -> 0 | O48: =SUM(I48:N48) -> 0 | V48: =SUM(P48:U48) -> 0 | AC48: =SUM(W48:AB48) -> 0 | AG48: 19091 | AH48: =SUM(AD48:AG48) -> 19091 | AI48: =H48+O48+V48+AC48+AH48 -> 19091
A49: TOTALE CLIENTES ACTIVOS | G49: =SUM(G24:G48) -> 0 | H49: =SUM(D49:G49) -> 0 | I49: =SUM(I24:I48) -> 0 | J49: =SUM(J24:J48) -> 0 | K49: =SUM(K24:K48) -> 0 | L49: =SUM(L24:L48) -> 0 | M49: =SUM(M24:M48) -> 0 | N49: =SUM(N24:N48) -> 0 | O49: =SUM(I49:N49) -> 0 | P49: =SUM(P24:P48) -> 0 | Q49: =SUM(Q24:Q48) -> 0 | R49: =SUM(R24:R48) -> 0 | S49: =SUM(S24:S48) -> 0 | T49: =SUM(T24:T48) -> 0 | U49: =SUM(U24:U48) -> 0 | V49: =SUM(P49:U49) -> 0 | W49: =SUM(W24:W48) -> 0 | X49: =SUM(X24:X48) -> 0 | Y49: =SUM(Y24:Y48) -> 0 | Z49: =SUM(Z24:Z48) -> 0 | AA49: =SUM(AA24:AA48) -> 0 | AB49: =SUM(AB24:AB48) -> 0 | AC49: =SUM(W49:AB49) -> 0 | AD49: =SUM(AD24:AD48) -> 0 | AE49: =SUM(AE24:AE48) -> 0 | AF49: =SUM(AF24:AF48) -> 0 | AG49: =SUM(AG24:AG48) -> 951722.5 | AH49: =SUM(AD49:AG49) -> 951722.5 | AI49: =SUM(AI24:AI48) -> 951722.5
A50: TOTALE CLIENTES | D50: =+D23+D49 -> 0 | E50: =+E23+E49 -> 0 | F50: =+F23+F49 -> 0 | G50: =+G23+G49 -> 0 | H50: =SUM(D50:G50) -> 0 | I50: =+I23+I49 -> 0 | J50: =+J23+J49 -> 0 | K50: =+K23+K49 -> 0 | L50: =+L23+L49 -> 0 | M50: =+M23+M49 -> 0 | N50: =+N23+N49 -> 0 | O50: =SUM(I50:N50) -> 0 | P50: =+P23+P49 -> 0 | Q50: =+Q23+Q49 -> 0 | R50: =+R23+R49 -> 0 | S50: =+S23+S49 -> 0 | T50: =+T23+T49 -> 0 | U50: =+U23+U49 -> 0 | V50: =SUM(P50:U50) -> 0 | W50: =+W23+W49 -> 0 | X50: =+X23+X49 -> 0 | Y50: =+Y23+Y49 -> 0 | Z50: =+Z23+Z49 -> 0 | AA50: =+AA23+AA49 -> 0 | AB50: =+AB23+AB49 -> 0 | AC50: =SUM(W50:AB50) -> 0 | AD50: =+AD23+AD49 -> 0 | AH50: =SUM(AD50:AG50) -> 0 | AI50: =SUM(AI49,AI23) -> 951722.5

Sheet RECAU. ENERO 2026
A3: CUENTAS POR COBRAR A CLIENTES
A4: GESTION 2024 - 2025
A5: ENERO- 2026
A6: Nº | B6: DISTRIBUIDOR | C6: DEPARTAMENTO | AI6: TOTAL MES
D7: 1 | E7: 2 | F7: 3 | G7: 4 | H7: Semana 1 | I7: 6 | J7: 7 | K7: 8 | L7: 9 | M7: 10 | N7: 11 | O7: Semana 2 | P7: 13 | Q7: 14 | R7: 15 | S7: 16 | T7: 17 | U7: 18 | V7: Semana 3 | W7: 20 | X7: 21 | Y7: 22 | Z7: 23 | AA7: 24 | AB7: 25 | AC7: Semana 4 | AD7: 27 | AE7: 28 | AF7: 29 | AG7: 31 | AH7: Semana 4
A8: 1 | B8: Fabricio Tapia Castedo | C8: Cochabamba | H8: =SUM(D8:G8) -> 0 | O8: =SUM(I8:N8) -> 0 | V8: =SUM(P8:U8) -> 0 | AC8: =SUM(W8:AB8) -> 0 | AH8: =SUM(AD8:AG8) -> 0 | AI8: =+H8+O8+V8+AH8 -> 0
A9: =1+A8 -> 2 | B9: Edwin Fernandez Chirinos | C9: El Alto | H9: =SUM(D9:G9) -> 0 | O9: =SUM(I9:N9) -> 0 | V9: =SUM(P9:U9) -> 0 | AC9: =SUM(W9:AB9) -> 0 | AH9: =SUM(AD9:AG9) -> 0 | AI9: =+H9+O9+V9+AH9 -> 0
A10: =1+A9 -> 3 | B10: Javier Caceres | C10: Cochabamba | H10: =SUM(D10:G10) -> 0 | O10: =SUM(I10:N10) -> 0 | V10: =SUM(P10:U10) -> 0 | AC10: =SUM(W10:AB10) -> 0 | AH10: =SUM(AD10:AG10) -> 0 | AI10: =+H10+O10+V10+AH10 -> 0
A11: =1+A10 -> 4 | B11: Juan Carlos Torrez Ayarde | C11: Tarija | H11: =SUM(D11:G11) -> 0 | O11: =SUM(I11:N11) -> 0 | V11: =SUM(P11:U11) -> 0 | AC11: =SUM(W11:AB11) -> 0 | AH11: =SUM(AD11:AG11) -> 0 | AI11: =+H11+O11+V11+AH11 -> 0
A12: =1+A11 -> 5 | B12: Carol Alejandra Noya | C12: Tarija | H12: =SUM(D12:G12) -> 0 | O12: =SUM(I12:N12) -> 0 | V12: =SUM(P12:U12) -> 0 | AC12: =SUM(W12:AB12) -> 0 | AH12: =SUM(AD12:AG12) -> 0 | AI12: =+H12+O12+V12+AH12 -> 0
A13: =1+A12 -> 6 | B13: Luis Alberto Chipana Peña | C13: Cochabamba | H13: =SUM(D13:G13) -> 0 | O13: =SUM(I13:N13) -> 0 | V13: =SUM(P13:U13) -> 0 | AC13: =SUM(W13:AB13) -> 0 | AH13: =SUM(AD13:AG13) -> 0 | AI13: =+H13+O13+V13+AH13 -> 0
A14: =1+A13 -> 7 | B14: Franz Carlos Alanez Flores | C14: El Alto | H14: =SUM(D14:G14) -> 0 | O14: =SUM(I14:N14) -> 0 | V14: =SUM(P14:U14) -> 0 | AC14: =SUM(W14:AB14) -> 0 | AH14: =SUM(AD14:AG14) -> 0 | AI14: =+H14+O14+V14+AH14 -> 0
A15: =1+A14 -> 8 | B15: Andrés Miguel Paniagua | C15: Oruro | H15: =SUM(D15:G15) -> 0 | O15: =SUM(I15:N15) -> 0 | V15: =SUM(P15:U15) -> 0 | AC15: =SUM(W15:AB15) -> 0 | AH15: =SUM(AD15:AG15) -> 0 | AI15: =+H15+O15+V15+AH15 -> 0
A16: =1+A15 -> 9 | B16: Alex Rolando Fernandez H. | C16: Oruro | H16: =SUM(D16:G16) -> 0 | O16: =SUM(I16:N16) -> 0 | V16: =SUM(P16:U16) -> 0 | AC16: =SUM(W16:AB16) -> 0 | AH16: =SUM(AD16:AG16) -> 0 | AI16: =+H16+O16+V16+AH16 -> 0
A17: =1+A16 -> 10 | B17: Franklin Ever Viveros | C17: Potosí | H17: =SUM(D17:G17) -> 0 | O17: =SUM(I17:N17) -> 0 | V17: =SUM(P17:U17) -> 0 | AC17: =SUM(W17:AB17) -> 0 | AH17: =SUM(AD17:AG17) -> 0 | AI17: =+H17+O17+V17+AH17 -> 0
A18: =1+A17 -> 11 | B18: Teofilo Ibañez Soliz | C18: Tarija | H18: =SUM(D18:G18) -> 0 | O18: =SUM(I18:N18) -> 0 | V18: =SUM(P18:U18) -> 0 | AC18: =SUM(W18:AB18) -> 0 | AH18: =SUM(AD18:AG18) -> 0 | AI18: =+H18+O18+V18+AH18 -> 0
A19: =1+A18 -> 12 | B19: Elsa Romay Padilla | C19: Uyuni | H19: =SUM(D19:G19) -> 0 | O19: =SUM(I19:N19) -> 0 | V19: =SUM(P19:U19) -> 0 | AC19: =SUM(W19:AB19) -> 0 | AH19: =SUM(AD19:AG19) -> 0 | AI19: =+H19+O19+V19+AH19 -> 0
A20: =1+A19 -> 13 | B20: Jorge Luis Vedia Arancibia | C20: Chuquisaca - Prov | H20: =SUM(D20:G20) -> 0 | O20: =SUM(I20:N20) -> 0 | V20: =SUM(P20:U20) -> 0 | AC20: =SUM(W20:AB20) -> 0 | AH20: =SUM(AD20:AG20) -> 0 | AI20: =+H20+O20+V20+AH20 -> 0
A21: =1+A20 -> 14 | B21: Celina Cruz Mendez | C21: Chuquisaca - Prov | H21: =SUM(D21:G21) -> 0 | O21: =SUM(I21:N21) -> 0 | V21: =SUM(P21:U21) -> 0 | AC21: =SUM(W21:AB21) -> 0 | AH21: =SUM(AD21:AG21) -> 0 | AI21: =+H21+O21+V21+AH21 -> 0
A22: 15 | B22: Marlene Paicho | C22: Ruta Colquechaca | H22: =SUM(D22:G22) -> 0 | O22: =SUM(I22:N22) -> 0 | V22: =SUM(P22:U22) -> 0 | AC22: =SUM(W22:AB22) -> 0 | AH22: =SUM(AD22:AG22) -> 0 | AI22: =H22+O22+V22+AH22 -> 0
A23: TOTAL CLIENTES MOROSOS | G23: =SUM(G8:G22) -> 0 | H23: =SUM(D23:G23) -> 0 | I23: =SUM(I8:I22) -> 0 | J23: =SUM(J8:J22) -> 0 | K23: =SUM(K8:K22) -> 0 | L23: =SUM(L8:L22) -> 0 | M23: =SUM(M8:M22) -> 0 | N23: =SUM(N8:N22) -> 0 | O23: =SUM(I23:N23) -> 0 | P23: =SUM(P8:P22) -> 0 | Q23: =SUM(Q8:Q22) -> 0 | R23: =SUM(R8:R22) -> 0 | S23: =SUM(S8:S22) -> 0 | T23: =SUM(T8:T22) -> 0 | U23: =SUM(U8:U22) -> 0 | V23: =SUM(P23:U23) -> 0 | W23: =SUM(W8:W22) -> 0 | X23: =SUM(X8:X22) -> 0 | Y23: =SUM(Y8:Y22) -> 0 | Z23: =SUM(Z8:Z22) -> 0 | AA23: =SUM(AA8:AA22) -> 0 | AB23: =SUM(AB8:AB22) -> 0 | AC23: =SUM(W23:AB23) -> 0 | AD23: =SUM(AD8:AD22) -> 0 | AG23: =SUM(AG8:AG22) -> 0 | AH23: =SUM(AD23:AG23) -> 0 | AI23: =SUM(AI8:AI22) -> 0
A24: 1 | B24: Gustavo Tellez Ugarte | C24: Santa Cruz | H24: =SUM(D24:G24) -> 0 | O24: =SUM(I24:N24) -> 0 | V24: =SUM(P24:U24) -> 0 | AC24: =SUM(W24:AB24) -> 0 | AH24: =SUM(AD24:AG24) -> 0 | AI24: =H24+O24+V24+AC24+AH24 -> 0
A25: =1+A24 -> 2 | B25: Cristhian Murillo | C25: Sucre | H25: =SUM(D25:G25) -> 0 | O25: =SUM(I25:N25) -> 0 | V25: =SUM(P25:U25) -> 0 | AC25: =SUM(W25:AB25) -> 0 | AH25: =SUM(AD25:AG25) -> 0 | AI25: =H25+O25+V25+AC25+AH25 -> 0
A26: =1+A25 -> 3 | B26: Orlando Aldunate M. | C26: Tarija | H26: =SUM(D26:G26) -> 0 | O26: =SUM(I26:N26) -> 0 | V26: =SUM(P26:U26) -> 0 | AC26: =SUM(W26:AB26) -> 0 | AH26: =SUM(AD26:AG26) -> 0 | AI26: =H26+O26+V26+AC26+AH26 -> 0
A27: =1+A26 -> 4 | B27: Ventas Directas de Fabrica | C27: Sucre | H27: =SUM(D27:G27) -> 0 | O27: =SUM(I27:N27) -> 0 | V27: =SUM(P27:U27) -> 0 | AC27: =SUM(W27:AB27) -> 0 | AG27: 81828 | AH27: =SUM(AD27:AG27) -> 81828 | AI27: =H27+O27+V27+AC27+AH27 -> 81828
A28: =1+A27 -> 5 | B28: Carlos Eduardo Gutierrez - Ambulante | C28: Sucre | H28: =SUM(D28:G28) -> 0 | O28: =SUM(I28:N28) -> 0 | V28: =SUM(P28:U28) -> 0 | AC28: =SUM(W28:AB28) -> 0 | AG28: 4160 | AH28: =SUM(AD28:AG28) -> 4160 | AI28: =H28+O28+V28+AC28+AH28 -> 4160
A29: =1+A28 -> 6 | B29: Supermercado SAS | C29: Sucre | H29: =SUM(D29:G29) -> 0 | O29: =SUM(I29:N29) -> 0 | V29: =SUM(P29:U29) -> 0 | AC29: =SUM(W29:AB29) -> 0 | AG29: 20153 | AH29: =SUM(AD29:AG29) -> 20153 | AI29: =H29+O29+V29+AC29+AH29 -> 20153
A30: =1+A29 -> 7 | B30: SOLAR Supermercado | C30: Sucre | H30: =SUM(D30:G30) -> 0 | O30: =SUM(I30:N30) -> 0 | V30: =SUM(P30:U30) -> 0 | AC30: =SUM(W30:AB30) -> 0 | AH30: =SUM(AD30:AG30) -> 0 | AI30: =H30+O30+V30+AC30+AH30 -> 0
A31: =1+A30 -> 8 | B31: LIDER Supermercado | C31: Sucre | H31: =SUM(D31:G31) -> 0 | O31: =SUM(I31:N31) -> 0 | V31: =SUM(P31:U31) -> 0 | AC31: =SUM(W31:AB31) -> 0 | AG31: 764 | AH31: =SUM(AD31:AG31) -> 764 | AI31: =H31+O31+V31+AC31+AH31 -> 764
A32: =1+A31 -> 9 | B32: Farmacia San Agustin | C32: Sucre | H32: =SUM(D32:G32) -> 0 | O32: =SUM(I32:N32) -> 0 | V32: =SUM(P32:U32) -> 0 | AC32: =SUM(W32:AB32) -> 0 | AH32: =SUM(AD32:AG32) -> 0 | AI32: =H32+O32+V32+AC32+AH32 -> 0
A33: =1+A32 -> 10 | B33: Supermercado POMPEYA | C33: Sucre | H33: =SUM(D33:G33) -> 0 | O33: =SUM(I33:N33) -> 0 | V33: =SUM(P33:U33) -> 0 | AC33: =SUM(W33:AB33) -> 0 | AH33: =SUM(AD33:AG33) -> 0 | AI33: =H33+O33+V33+AC33+AH33 -> 0
A34: =1+A33 -> 11 | B34: Inocencio Cruz | C34: Sucre | H34: =SUM(D34:G34) -> 0 | O34: =SUM(I34:N34) -> 0 | V34: =SUM(P34:U34) -> 0 | AC34: =SUM(W34:AB34) -> 0 | AG34: 169673 | AH34: =SUM(AD34:AG34) -> 169673 | AI34: =H34+O34+V34+AC34+AH34 -> 169673
A35: =1+A34 -> 12 | B35: Christian Churqui Ortega | C35: Sucre | H35: =SUM(D35:G35) -> 0 | O35: =SUM(I35:N35) -> 0 | V35: =SUM(P35:U35) -> 0 | AC35: =SUM(W35:AB35) -> 0 | AG35: 135412.5 | AH35: =SUM(AD35:AG35) -> 135412.5 | AI35: =H35+O35+V35+AC35+AH35 -> 135412.5
A36: =1+A35 -> 13 | B36: Victor Hugo Zarate | C36: Provinci Sucre | H36: =SUM(D36:G36) -> 0 | O36: =SUM(I36:N36) -> 0 | V36: =SUM(P36:U36) -> 0 | AC36: =SUM(W36:AB36) -> 0 | AH36: =SUM(AD36:AG36) -> 0 | AI36: =H36+O36+V36+AC36+AH36 -> 0
A37: =1+A36 -> 14 | B37: Oscar Hugo Garzofino Catacora (Paceña) | C37: Sucre | H37: =SUM(D37:G37) -> 0 | O37: =SUM(I37:N37) -> 0 | V37: =SUM(P37:U37) -> 0 | AC37: =SUM(W37:AB37) -> 0 | AG37: 1650 | AH37: =SUM(AD37:AG37) -> 1650 | AI37: =H37+O37+V37+AC37+AH37 -> 1650
A38: =1+A37 -> 15 | B38: Beker Rosa Cruz - Carmen | C38: Potosí | AG38: 204775 | AH38: =SUM(AD38:AG38) -> 204775 | AI38: =H38+O38+V38+AC38+AH38 -> 204775
A39: =1+A38 -> 16 | B39: Gobierno Autonomo Municipal de Sucre - Desarrollo Productivo | C39: Sucre | AH39: =SUM(AD39:AG39) -> 0 | AI39: =H39+O39+V39+AC39+AH39 -> 0
A40: =1+A39 -> 17 | B40: Gobierno Autonomo Municipal de Sucre - Dirección Administrativa | C40: Sucre | AH40: =SUM(AD40:AG40) -> 0 | AI40: =H40+O40+V40+AC40+AH40 -> 0
A41: =1+A40 -> 18 | B41: Jenrry | C41: Chile | AH41: =SUM(AD41:AG41) -> 0 | AI41: =H41+O41+V41+AC41+AH41 -> 0
A42: =1+A41 -> 19 | B42: Eddy | C42: Chile | AH42: =SUM(AD42:AG42) -> 0 | AI42: =H42+O42+V42+AC42+AH42 -> 0
A43: =1+A42 -> 20 | B43: Jhaneth Miriam Toroya Gabriel | C43: Oruro | AG43: 234444 | AH43: =SUM(AD43:AG43) -> 234444 | AI43: =H43+O43+V43+AC43+AH43 -> 234444
A44: =1+A43 -> 21 | B44: Miguel Zurita | C44: Tupiza Villazon | AH44: =SUM(AD44:AG44) -> 0 | AI44: =H44+O44+V44+AC44+AH44 -> 0
A45: =1+A44 -> 22 | B45: Marco | C45: Uyuni | AG45: 25714 | AH45: =SUM(AD45:AG45) -> 25714 | AI45: =H45+O45+V45+AC45+AH45 -> 25714
A46: =1+A45 -> 23 | B46: Luis Fernando Zuna Rodriguez | C46: La Paz | AG46: 77007.15 | AH46: =SUM(AD46:AG46) -> 77007.15 | AI46: =H46+O46+V46+AC46+AH46 -> 77007.15
A47: =1+A46 -> 24 | B47: Alexander Vides Garzon | C47: Tarija | H47: =SUM(D47:G47) -> 0 | O47: =SUM(I47:N47) -> 0 | V47: =SUM(P47:U47) -> 0 | AC47: =SUM(W47:AB47) -> 0 | AG47: 222815 | AH47: =SUM(AD47:AG47) -> 222815 | AI47: =H47+O47+V47+AC47+AH47 -> 222815
A48: =1+A47 -> 25 | B48: Ventas en FABRICA | C48: Sucre | H48: =SUM(D48:G48) -> 0 | O48: =SUM(I48:N48) -> 0 | V48: =SUM(P48:U48) -> 0 | AC48: =SUM(W48:AB48) -> 0 | AG48: 31761.5 | AH48: =SUM(AD48:AG48) -> 31761.5 | AI48: =H48+O48+V48+AC48+AH48 -> 31761.5
A49: TOTALE CLIENTES ACTIVOS | G49: =SUM(G24:G48) -> 0 | H49: =SUM(D49:G49) -> 0 | I49: =SUM(I24:I48) -> 0 | J49: =SUM(J24:J48) -> 0 | K49: =SUM(K24:K48) -> 0 | L49: =SUM(L24:L48) -> 0 | M49: =SUM(M24:M48) -> 0 | N49: =SUM(N24:N48) -> 0 | O49: =SUM(I49:N49) -> 0 | P49: =SUM(P24:P48) -> 0 | Q49: =SUM(Q24:Q48) -> 0 | R49: =SUM(R24:R48) -> 0 | S49: =SUM(S24:S48) -> 0 | T49: =SUM(T24:T48) -> 0 | U49: =SUM(U24:U48) -> 0 | V49: =SUM(P49:U49) -> 0 | W49: =SUM(W24:W48) -> 0 | X49: =SUM(X24:X48) -> 0 | Y49: =SUM(Y24:Y48) -> 0 | Z49: =SUM(Z24:Z48) -> 0 | AA49: =SUM(AA24:AA48) -> 0 | AB49: =SUM(AB24:AB48) -> 0 | AC49: =SUM(W49:AB49) -> 0 | AD49: =SUM(AD24:AD48) -> 0 | AE49: =SUM(AE24:AE48) -> 0 | AF49: =SUM(AF24:AF48) -> 0 | AG49: =SUM(AG24:AG48) -> 1210157.1 | AH49: =SUM(AD49:AG49) -> 1210157.1 | AI49: =SUM(AI24:AI48) -> 1210157.1
A50: TOTALE CLIENTES | D50: =+D23+D49 -> 0 | E50: =+E23+E49 -> 0 | F50: =+F23+F49 -> 0 | G50: =+G23+G49 -> 0 | H50: =SUM(D50:G50) -> 0 | I50: =+I23+I49 -> 0 | J50: =+J23+J49 -> 0 | K50: =+K23+K49 -> 0 | L50: =+L23+L49 -> 0 | M50: =+M23+M49 -> 0 | N50: =+N23+N49 -> 0 | O50: =SUM(I50:N50) -> 0 | P50: =+P23+P49 -> 0 | Q50: =+Q23+Q49 -> 0 | R50: =+R23+R49 -> 0 | S50: =+S23+S49 -> 0 | T50: =+T23+T49 -> 0 | U50: =+U23+U49 -> 0 | V50: =SUM(P50:U50) -> 0 | W50: =+W23+W49 -> 0 | X50: =+X23+X49 -> 0 | Y50: =+Y23+Y49 -> 0 | Z50: =+Z23+Z49 -> 0 | AA50: =+AA23+AA49 -> 0 | AB50: =+AB23+AB49 -> 0 | AC50: =SUM(W50:AB50) -> 0 | AD50: =+AD23+AD49 -> 0 | AH50: =SUM(AD50:AG50) -> 0 | AI50: =SUM(AI49,AI23) -> 1210157.1

Sheet RECAU. FEBRERO 2026
A3: CUENTAS POR COBRAR A CLIENTES
A4: GESTION 2024 - 2025
A5: ENERO- 2026
A6: Nº | B6: DISTRIBUIDOR | C6: DEPARTAMENTO | AI6: TOTAL MES
D7: 1 | E7: 2 | F7: 3 | G7: 4 | H7: Semana 1 | I7: 6 | J7: 7 | K7: 8 | L7: 9 | M7: 10 | N7: 11 | O7: Semana 2 | P7: 13 | Q7: 14 | R7: 15 | S7: 16 | T7: 17 | U7: 18 | V7: Semana 3 | W7: 20 | X7: 21 | Y7: 22 | Z7: 23 | AA7: 24 | AB7: 25 | AC7: Semana 4 | AD7: 27 | AE7: 28 | AF7: 29 | AG7: 31 | AH7: Semana 4
A8: 1 | B8: Fabricio Tapia Castedo | C8: Cochabamba | H8: =SUM(D8:G8) -> 0 | O8: =SUM(I8:N8) -> 0 | V8: =SUM(P8:U8) -> 0 | AC8: =SUM(W8:AB8) -> 0 | AH8: =SUM(AD8:AG8) -> 0 | AI8: =+H8+O8+V8+AH8 -> 0
A9: =1+A8 -> 2 | B9: Edwin Fernandez Chirinos | C9: El Alto | H9: =SUM(D9:G9) -> 0 | O9: =SUM(I9:N9) -> 0 | V9: =SUM(P9:U9) -> 0 | AC9: =SUM(W9:AB9) -> 0 | AH9: =SUM(AD9:AG9) -> 0 | AI9: =+H9+O9+V9+AH9 -> 0
A10: =1+A9 -> 3 | B10: Javier Caceres | C10: Cochabamba | H10: =SUM(D10:G10) -> 0 | O10: =SUM(I10:N10) -> 0 | V10: =SUM(P10:U10) -> 0 | AC10: =SUM(W10:AB10) -> 0 | AH10: =SUM(AD10:AG10) -> 0 | AI10: =+H10+O10+V10+AH10 -> 0
A11: =1+A10 -> 4 | B11: Juan Carlos Torrez Ayarde | C11: Tarija | H11: =SUM(D11:G11) -> 0 | O11: =SUM(I11:N11) -> 0 | V11: =SUM(P11:U11) -> 0 | AC11: =SUM(W11:AB11) -> 0 | AH11: =SUM(AD11:AG11) -> 0 | AI11: =+H11+O11+V11+AH11 -> 0
A12: =1+A11 -> 5 | B12: Carol Alejandra Noya | C12: Tarija | H12: =SUM(D12:G12) -> 0 | O12: =SUM(I12:N12) -> 0 | V12: =SUM(P12:U12) -> 0 | AC12: =SUM(W12:AB12) -> 0 | AH12: =SUM(AD12:AG12) -> 0 | AI12: =+H12+O12+V12+AH12 -> 0
A13: =1+A12 -> 6 | B13: Luis Alberto Chipana Peña | C13: Cochabamba | H13: =SUM(D13:G13) -> 0 | O13: =SUM(I13:N13) -> 0 | V13: =SUM(P13:U13) -> 0 | AC13: =SUM(W13:AB13) -> 0 | AH13: =SUM(AD13:AG13) -> 0 | AI13: =+H13+O13+V13+AH13 -> 0
A14: =1+A13 -> 7 | B14: Franz Carlos Alanez Flores | C14: El Alto | H14: =SUM(D14:G14) -> 0 | O14: =SUM(I14:N14) -> 0 | V14: =SUM(P14:U14) -> 0 | AC14: =SUM(W14:AB14) -> 0 | AH14: =SUM(AD14:AG14) -> 0 | AI14: =+H14+O14+V14+AH14 -> 0
A15: =1+A14 -> 8 | B15: Andrés Miguel Paniagua | C15: Oruro | H15: =SUM(D15:G15) -> 0 | O15: =SUM(I15:N15) -> 0 | V15: =SUM(P15:U15) -> 0 | AC15: =SUM(W15:AB15) -> 0 | AH15: =SUM(AD15:AG15) -> 0 | AI15: =+H15+O15+V15+AH15 -> 0
A16: =1+A15 -> 9 | B16: Alex Rolando Fernandez H. | C16: Oruro | H16: =SUM(D16:G16) -> 0 | O16: =SUM(I16:N16) -> 0 | V16: =SUM(P16:U16) -> 0 | AC16: =SUM(W16:AB16) -> 0 | AH16: =SUM(AD16:AG16) -> 0 | AI16: =+H16+O16+V16+AH16 -> 0
A17: =1+A16 -> 10 | B17: Franklin Ever Viveros | C17: Potosí | H17: =SUM(D17:G17) -> 0 | O17: =SUM(I17:N17) -> 0 | V17: =SUM(P17:U17) -> 0 | AC17: =SUM(W17:AB17) -> 0 | AH17: =SUM(AD17:AG17) -> 0 | AI17: =+H17+O17+V17+AH17 -> 0
A18: =1+A17 -> 11 | B18: Teofilo Ibañez Soliz | C18: Tarija | H18: =SUM(D18:G18) -> 0 | O18: =SUM(I18:N18) -> 0 | V18: =SUM(P18:U18) -> 0 | AC18: =SUM(W18:AB18) -> 0 | AH18: =SUM(AD18:AG18) -> 0 | AI18: =+H18+O18+V18+AH18 -> 0
A19: =1+A18 -> 12 | B19: Elsa Romay Padilla | C19: Uyuni | H19: =SUM(D19:G19) -> 0 | O19: =SUM(I19:N19) -> 0 | V19: =SUM(P19:U19) -> 0 | AC19: =SUM(W19:AB19) -> 0 | AH19: =SUM(AD19:AG19) -> 0 | AI19: =+H19+O19+V19+AH19 -> 0
A20: =1+A19 -> 13 | B20: Jorge Luis Vedia Arancibia | C20: Chuquisaca - Prov | H20: =SUM(D20:G20) -> 0 | O20: =SUM(I20:N20) -> 0 | V20: =SUM(P20:U20) -> 0 | AC20: =SUM(W20:AB20) -> 0 | AH20: =SUM(AD20:AG20) -> 0 | AI20: =+H20+O20+V20+AH20 -> 0
A21: =1+A20 -> 14 | B21: Celina Cruz Mendez | C21: Chuquisaca - Prov | H21: =SUM(D21:G21) -> 0 | O21: =SUM(I21:N21) -> 0 | V21: =SUM(P21:U21) -> 0 | AC21: =SUM(W21:AB21) -> 0 | AH21: =SUM(AD21:AG21) -> 0 | AI21: =+H21+O21+V21+AH21 -> 0
A22: 15 | B22: Marlene Paicho | C22: Ruta Colquechaca | H22: =SUM(D22:G22) -> 0 | O22: =SUM(I22:N22) -> 0 | V22: =SUM(P22:U22) -> 0 | AC22: =SUM(W22:AB22) -> 0 | AH22: =SUM(AD22:AG22) -> 0 | AI22: =H22+O22+V22+AH22 -> 0
A23: TOTAL CLIENTES MOROSOS | G23: =SUM(G8:G22) -> 0 | H23: =SUM(D23:G23) -> 0 | I23: =SUM(I8:I22) -> 0 | J23: =SUM(J8:J22) -> 0 | K23: =SUM(K8:K22) -> 0 | L23: =SUM(L8:L22) -> 0 | M23: =SUM(M8:M22) -> 0 | N23: =SUM(N8:N22) -> 0 | O23: =SUM(I23:N23) -> 0 | P23: =SUM(P8:P22) -> 0 | Q23: =SUM(Q8:Q22) -> 0 | R23: =SUM(R8:R22) -> 0 | S23: =SUM(S8:S22) -> 0 | T23: =SUM(T8:T22) -> 0 | U23: =SUM(U8:U22) -> 0 | V23: =SUM(P23:U23) -> 0 | W23: =SUM(W8:W22) -> 0 | X23: =SUM(X8:X22) -> 0 | Y23: =SUM(Y8:Y22) -> 0 | Z23: =SUM(Z8:Z22) -> 0 | AA23: =SUM(AA8:AA22) -> 0 | AB23: =SUM(AB8:AB22) -> 0 | AC23: =SUM(W23:AB23) -> 0 | AD23: =SUM(AD8:AD22) -> 0 | AG23: =SUM(AG8:AG22) -> 0 | AH23: =SUM(AD23:AG23) -> 0 | AI23: =SUM(AI8:AI22) -> 0
A24: 1 | B24: Gustavo Tellez Ugarte | C24: Santa Cruz | H24: =SUM(D24:G24) -> 0 | O24: =SUM(I24:N24) -> 0 | V24: =SUM(P24:U24) -> 0 | AC24: =SUM(W24:AB24) -> 0 | AH24: =SUM(AD24:AG24) -> 0 | AI24: =H24+O24+V24+AC24+AH24 -> 0
A25: =1+A24 -> 2 | B25: Cristhian Murillo | C25: Sucre | H25: =SUM(D25:G25) -> 0 | O25: =SUM(I25:N25) -> 0 | V25: =SUM(P25:U25) -> 0 | AC25: =SUM(W25:AB25) -> 0 | AH25: =SUM(AD25:AG25) -> 0 | AI25: =H25+O25+V25+AC25+AH25 -> 0
A26: =1+A25 -> 3 | B26: Orlando Aldunate M. | C26: Tarija | H26: =SUM(D26:G26) -> 0 | O26: =SUM(I26:N26) -> 0 | V26: =SUM(P26:U26) -> 0 | AC26: =SUM(W26:AB26) -> 0 | AH26: =SUM(AD26:AG26) -> 0 | AI26: =H26+O26+V26+AC26+AH26 -> 0
A27: =1+A26 -> 4 | B27: Ventas Directas de Fabrica | C27: Sucre | H27: =SUM(D27:G27) -> 0 | O27: =SUM(I27:N27) -> 0 | V27: =SUM(P27:U27) -> 0 | AC27: =SUM(W27:AB27) -> 0 | AG27: =+#REF! -> #REF! | AH27: =SUM(AD27:AG27) -> #REF! | AI27: =H27+O27+V27+AC27+AH27 -> #REF!
A28: =1+A27 -> 5 | B28: Carlos Eduardo Gutierrez - Ambulante | C28: Sucre | H28: =SUM(D28:G28) -> 0 | O28: =SUM(I28:N28) -> 0 | V28: =SUM(P28:U28) -> 0 | AC28: =SUM(W28:AB28) -> 0 | AH28: =SUM(AD28:AG28) -> 0 | AI28: =H28+O28+V28+AC28+AH28 -> 0
A29: =1+A28 -> 6 | B29: Supermercado SAS | C29: Sucre | H29: =SUM(D29:G29) -> 0 | O29: =SUM(I29:N29) -> 0 | V29: =SUM(P29:U29) -> 0 | AC29: =SUM(W29:AB29) -> 0 | AG29: =+'Supermencado SAS'!F23+'Supermencado SAS'!F22+'Supermencado SAS'!F24+'Supermencado SAS'!F25+'Supermencado SAS'!F26 -> 23553 | AH29: =SUM(AD29:AG29) -> 23553 | AI29: =H29+O29+V29+AC29+AH29 -> 23553
A30: =1+A29 -> 7 | B30: SOLAR Supermercado | C30: Sucre | H30: =SUM(D30:G30) -> 0 | O30: =SUM(I30:N30) -> 0 | V30: =SUM(P30:U30) -> 0 | AC30: =SUM(W30:AB30) -> 0 | AG30: =+'SOLAR Supermercado'!F12 -> 2034 | AH30: =SUM(AD30:AG30) -> 2034 | AI30: =H30+O30+V30+AC30+AH30 -> 2034
A31: =1+A30 -> 8 | B31: LIDER Supermercado | C31: Sucre | H31: =SUM(D31:G31) -> 0 | O31: =SUM(I31:N31) -> 0 | V31: =SUM(P31:U31) -> 0 | AC31: =SUM(W31:AB31) -> 0 | AG31: =+'LIDER Supermercado'!F14 -> 1344 | AH31: =SUM(AD31:AG31) -> 1344 | AI31: =H31+O31+V31+AC31+AH31 -> 1344
A32: =1+A31 -> 9 | B32: Farmacia San Agustin | C32: Sucre | H32: =SUM(D32:G32) -> 0 | O32: =SUM(I32:N32) -> 0 | V32: =SUM(P32:U32) -> 0 | AC32: =SUM(W32:AB32) -> 0 | AG32: =+'FARMACIA SAN AGUSTIN'!F13 -> 1798 | AH32: =SUM(AD32:AG32) -> 1798 | AI32: =H32+O32+V32+AC32+AH32 -> 1798
A33: =1+A32 -> 10 | B33: Supermercado POMPEYA | C33: Sucre | H33: =SUM(D33:G33) -> 0 | O33: =SUM(I33:N33) -> 0 | V33: =SUM(P33:U33) -> 0 | AC33: =SUM(W33:AB33) -> 0 | AG33: =+'Supermercado POMPEYA'!F11+'Supermercado POMPEYA'!F12 -> 10990 | AH33: =SUM(AD33:AG33) -> 10990 | AI33: =H33+O33+V33+AC33+AH33 -> 10990
A34: =1+A33 -> 11 | B34: Inocencio Cruz | C34: Sucre | H34: =SUM(D34:G34) -> 0 | O34: =SUM(I34:N34) -> 0 | V34: =SUM(P34:U34) -> 0 | AC34: =SUM(W34:AB34) -> 0 | AG34: =+#REF! -> #REF! | AH34: =SUM(AD34:AG34) -> #REF! | AI34: =H34+O34+V34+AC34+AH34 -> #REF!
A35: =1+A34 -> 12 | B35: Christian Churqui Ortega | C35: Sucre | H35: =SUM(D35:G35) -> 0 | O35: =SUM(I35:N35) -> 0 | V35: =SUM(P35:U35) -> 0 | AC35: =SUM(W35:AB35) -> 0 | AG35: =+#REF! -> #REF! | AH35: =SUM(AD35:AG35) -> #REF! | AI35: =H35+O35+V35+AC35+AH35 -> #REF!
A36: =1+A35 -> 13 | B36: MERCAMAX | C36: Provinci Sucre | H36: =SUM(D36:G36) -> 0 | O36: =SUM(I36:N36) -> 0 | V36: =SUM(P36:U36) -> 0 | AC36: =SUM(W36:AB36) -> 0 | AG36: =+'MERCAMAX SRL'!F11 -> 1257 | AH36: =SUM(AD36:AG36) -> 1257 | AI36: =H36+O36+V36+AC36+AH36 -> 1257
A37: =1+A36 -> 14 | B37: Oscar Hugo Garzofino Catacora (Paceña) | C37: Sucre | H37: =SUM(D37:G37) -> 0 | O37: =SUM(I37:N37) -> 0 | V37: =SUM(P37:U37) -> 0 | AC37: =SUM(W37:AB37) -> 0 | AG37: =+'Oscar G. Paceña SUCRE'!K12 -> 1650 | AH37: =SUM(AD37:AG37) -> 1650 | AI37: =H37+O37+V37+AC37+AH37 -> 1650
A38: =1+A37 -> 15 | B38: Beker Rosa Cruz - Carmen | C38: Potosí | AG38: =+#REF! -> #REF! | AH38: =SUM(AD38:AG38) -> #REF! | AI38: =H38+O38+V38+AC38+AH38 -> #REF!
A39: =1+A38 -> 16 | B39: Gobierno Autonomo Municipal de Sucre - Desarrollo Productivo | C39: Sucre | AH39: =SUM(AD39:AG39) -> 0 | AI39: =H39+O39+V39+AC39+AH39 -> 0
A40: =1+A39 -> 17 | B40: Gobierno Autonomo Municipal de Sucre - Dirección Administrativa | C40: Sucre | AH40: =SUM(AD40:AG40) -> 0 | AI40: =H40+O40+V40+AC40+AH40 -> 0
A41: =1+A40 -> 18 | B41: Jenrry | C41: Chile | AG41: =+#REF! -> #REF! | AH41: =SUM(AD41:AG41) -> #REF! | AI41: =H41+O41+V41+AC41+AH41 -> #REF!
A42: =1+A41 -> 19 | B42: Jorge Saavedra | C42: Chile | AG42: =+#REF! -> #REF! | AH42: =SUM(AD42:AG42) -> #REF! | AI42: =H42+O42+V42+AC42+AH42 -> #REF!
A43: =1+A42 -> 20 | B43: Jhaneth Miriam Toroya Gabriel | C43: Oruro | AG43: =+#REF! -> #REF! | AH43: =SUM(AD43:AG43) -> #REF! | AI43: =H43+O43+V43+AC43+AH43 -> #REF!
A44: =1+A43 -> 21 | B44: Pulperia USFX | C44: Tupiza Villazon | AG44: =+'Pulperia USFX'!F11 -> 2595 | AH44: =SUM(AD44:AG44) -> 2595 | AI44: =H44+O44+V44+AC44+AH44 -> 2595
A45: =1+A44 -> 22 | B45: Marco - Ismael de Uyuni | C45: Uyuni | AH45: =SUM(AD45:AG45) -> 0 | AI45: =H45+O45+V45+AC45+AH45 -> 0
A46: =1+A45 -> 23 | B46: Luis Fernando Zuna Rodriguez | C46: La Paz | AH46: =SUM(AD46:AG46) -> 0 | AI46: =H46+O46+V46+AC46+AH46 -> 0
A47: =1+A46 -> 24 | B47: Alexander Vides Garzon | C47: Tarija | H47: =SUM(D47:G47) -> 0 | O47: =SUM(I47:N47) -> 0 | V47: =SUM(P47:U47) -> 0 | AC47: =SUM(W47:AB47) -> 0 | AH47: =SUM(AD47:AG47) -> 0 | AI47: =H47+O47+V47+AC47+AH47 -> 0
A48: =1+A47 -> 25 | B48: Ventas en FABRICA | C48: Sucre | H48: =SUM(D48:G48) -> 0 | O48: =SUM(I48:N48) -> 0 | V48: =SUM(P48:U48) -> 0 | AC48: =SUM(W48:AB48) -> 0 | AG48: 38730 | AH48: =SUM(AD48:AG48) -> 38730 | AI48: =H48+O48+V48+AC48+AH48 -> 38730
A49: TOTALE CLIENTES ACTIVOS | G49: =SUM(G24:G48) -> 0 | H49: =SUM(D49:G49) -> 0 | I49: =SUM(I24:I48) -> 0 | J49: =SUM(J24:J48) -> 0 | K49: =SUM(K24:K48) -> 0 | L49: =SUM(L24:L48) -> 0 | M49: =SUM(M24:M48) -> 0 | N49: =SUM(N24:N48) -> 0 | O49: =SUM(I49:N49) -> 0 | P49: =SUM(P24:P48) -> 0 | Q49: =SUM(Q24:Q48) -> 0 | R49: =SUM(R24:R48) -> 0 | S49: =SUM(S24:S48) -> 0 | T49: =SUM(T24:T48) -> 0 | U49: =SUM(U24:U48) -> 0 | V49: =SUM(P49:U49) -> 0 | W49: =SUM(W24:W48) -> 0 | X49: =SUM(X24:X48) -> 0 | Y49: =SUM(Y24:Y48) -> 0 | Z49: =SUM(Z24:Z48) -> 0 | AA49: =SUM(AA24:AA48) -> 0 | AB49: =SUM(AB24:AB48) -> 0 | AC49: =SUM(W49:AB49) -> 0 | AD49: =SUM(AD24:AD48) -> 0 | AE49: =SUM(AE24:AE48) -> 0 | AF49: =SUM(AF24:AF48) -> 0 | AG49: =SUM(AG24:AG48) -> #REF! | AH49: =SUM(AD49:AG49) -> #REF! | AI49: =SUM(AI24:AI48) -> #REF!
A50: TOTALE CLIENTES | D50: =+D23+D49 -> 0 | E50: =+E23+E49 -> 0 | F50: =+F23+F49 -> 0 | G50: =+G23+G49 -> 0 | H50: =SUM(D50:G50) -> 0 | I50: =+I23+I49 -> 0 | J50: =+J23+J49 -> 0 | K50: =+K23+K49 -> 0 | L50: =+L23+L49 -> 0 | M50: =+M23+M49 -> 0 | N50: =+N23+N49 -> 0 | O50: =SUM(I50:N50) -> 0 | P50: =+P23+P49 -> 0 | Q50: =+Q23+Q49 -> 0 | R50: =+R23+R49 -> 0 | S50: =+S23+S49 -> 0 | T50: =+T23+T49 -> 0 | U50: =+U23+U49 -> 0 | V50: =SUM(P50:U50) -> 0 | W50: =+W23+W49 -> 0 | X50: =+X23+X49 -> 0 | Y50: =+Y23+Y49 -> 0 | Z50: =+Z23+Z49 -> 0 | AA50: =+AA23+AA49 -> 0 | AB50: =+AB23+AB49 -> 0 | AC50: =SUM(W50:AB50) -> 0 | AD50: =+AD23+AD49 -> 0 | AH50: =SUM(AD50:AG50) -> 0 | AI50: =SUM(AI49,AI23) -> #REF!

Sheet GAMS
B2: CUENTAS POR COBRAR
B3: GESTION 2025 - 2026
C5: CLIENTE: | D5: Gobierno Autonomo Municipal de Sucre - Desarrollo Productivo
C6: CONTACTO | D6: NEISSA
C7: CELULAR: | D7: 60303650
C8: DESTINO: | D8: Sucre
B10: NOTA DE VENTA | C10: NOTA DE ENTREGA | D10: FECHA DE DESPACHO | E10: MONTO P/COBRAR | F10: DEPÓSITO en Bs | G10: FECHA DE DEPÓSITO | H10: SALDO | I10: DIAS DE MORA | J10: OBSERVACION
B11: 250407 | C11: 1700 | D11: 45756 | E11: 19980 | F11: 19980 | G11: 45764 | H11: =+E11-F11 -> 0
B12: 250721 | C12: 1817 | D12: 45853 | E12: 11745 | F12: 11745 | G12: 45866 | H12: =+H11+E12-F12 -> 0
B13: 250831 | C13: 18 | D13: 45901 | E13: 8091 | H13: =+H12+E13-F13 -> 8091
B14: 250936 | C14: 1916 | D14: 45930 | E14: 4350 | H14: =+H13+E14-F14 -> 12441
B15: 251016 | C15: 1943 | D15: 45941 | E15: 2900 | H15: =+H14+E15-F15 -> 15341
B16: 251035 | C16: 1974 | D16: 45954 | E16: 2291 | F16: 17632 | G16: 45982 | H16: =+H15+E16-F16 -> 0 | M16: =79*29 -> 2291
B17: 260114 | C17: 2230 | D17: 46028 | E17: 2500 | H17: =+H16+E17-F17 -> 2500
B18: 260182 | C18: 2305 | D18: 46038 | E18: 5000 | H18: =+H17+E18-F18 -> 7500
B19: 260253 | C19: 2440 | D19: 46064 | E19: 12792 | H19: =+H18+E19-F19 -> 20292
D20: AJUSTE DE PRECIO DE MESES ANTERIORES | E20: -300 | F20: 19992 | G20: 46090 | H20: =+H19+E20-F20 -> 0 | L20: =SUM(E17:E19) -> 20292 | M20: 19992 | N20: =+L20-M20 -> 300
B21: 2604 | C21: 233 | D21: 46127 | E21: 17411 | F21: 17411 | G21: 46134 | H21: =+H20+E21-F21 -> 0
C22: 480 | D22: 46210 | E22: 5750 | H22: =+H21+E22-F22 -> 5750
C23: 549 | D23: 46231 | E23: 1150 | H23: =+H22+E23-F23 -> 6900
C24: 559 | D24: 46233 | E24: 5750 | F24: 12650 | G24: 46246 | H24: =+H23+E24-F24 -> 0
H25: =+H24+E25-F25 -> 0
H26: =+H25+E26-F26 -> 0
H27: =+H26+E27-F27 -> 0
H28: =+H27+E28-F28 -> 0
H29: =+H24+E29-F29 -> 0
B30: TOTALES | E30: =SUM(E11:E29) -> 99410 | F30: =SUM(F11:F29) -> 99410
F31: =+E30-F30 -> 0
B36: CUENTAS POR COBRAR
B37: GESTION 2025 - 2026
C39: CLIENTE: | D39: Gobierno Autonomo Municipal de Sucre - Direccion Administrativa
C40: CONTACTO | D40: Olivia Ruiz
C41: CELULAR: | D41: 73826859
C42: DESTINO: | D42: Sucre
B44: NOTA DE VENTA | C44: NOTA DE ENTREGA | D44: FECHA DE DESPACHO | E44: MONTO P/COBRAR | F44: DEPÓSITO en Bs | G44: FECHA DE DEPÓSITO | H44: SALDO | I44: DIAS DE MORA | J44: OBSERVACION
B45: 250220 | C45: 1607 | D45: 45699 | E45: 2100 | H45: =+E45-F45 -> 2100
B46: 250321 | C46: 1662 | D46: 45733 | E46: 2100 | F46: 4200 | G46: 45742 | H46: =+H45+E46-F46 -> 0
B47: 250808 | C47: 1848 | D47: 45881 | E47: 783 | F47: 783 | G47: 45897 | H47: =+H46+E47-F47 -> 0
B48: 250911 | C48: 1889 | D48: 45912 | E48: 6960 | F48: 6960 | G48: 45926 | H48: =+H47+E48-F48 -> 0
H49: =+H48+E49-F49 -> 0
H50: =+H49+E50-F50 -> 0
H51: =+H50+E51-F51 -> 0
H52: =+H51+E52-F52 -> 0
H53: =+H52+E53-F53 -> 0 | L53: =+F50+F51+F52 -> 0
H54: =+H53+E54-F54 -> 0
H55: =+H54+E55-F55 -> 0
H56: =+H55+E56-F56 -> 0
H57: =+H56+E57-F57 -> 0
H58: =+H57+E58-F58 -> 0
H59: =+H58+E59-F59 -> 0
H60: =+H59+E60-F60 -> 0
B61: TOTALES | E61: =SUM(E45:E60) -> 11943 | F61: =SUM(F45:F60) -> 11943
F62: =+E61-F61 -> 0

Sheet Gustavo Tellez
B2: CUENTAS POR COBRAR
B3: GESTION 2023 - 2024
C5: CLIENTE: | D5: Gustavo Tellez Ugarte
C6: CELULAR: | D6: 68320858
C7: DESTINO: | D7: Santa Cruz
C8: LINEA DE CREDITO: | D8: -
B10: NOTA DE VENTA | C10: NOTA DE ENTREGA | D10: FECHA DE DESPACHO | E10: MONTO P/COBRAR | F10: DEPÓSITO en Bs | G10: FECHA DE DEPÓSITO | H10: SALDO | I10: DIAS DE MORA | J10: OBSERVACION
B11: SALDO AL 31/03/25 | H11: 817
B12: 250604 | C12: 1778 | D12: 45814 | E12: 85974 | F12: 50000 | G12: 45814 | H12: =+H11+E12-F12 -> 36791 | K12: BNB
F13: 35974 | G13: 45817 | H13: =+H12+E13-F13 -> 817 | K13: BNB | M13: =SUM(F12:F13) -> 85974
B14: 250817 | C14: 1858 | D14: 45880 | E14: 83884 | F14: 60000 | G14: 45880 | H14: =+H13+E14-F14 -> 24701 | J14: Transferencia
F15: 15000 | G15: 45880 | H15: =+H14+E15-F15 -> 9701 | J15: Recibo20080 | K15: BU
F16: 9701 | G16: 45888 | H16: =+H15+E16-F16 -> 5.8207661e-11 | J16: Transferencia | M16: =SUM(F14:F16) -> 84701
H17: =+H16+E17-F17 -> 5.8207661e-11
H18: =+H17+E18-F18 -> 5.8207661e-11
H19: =+H18+E19-F19 -> 5.8207661e-11
H20: =+H19+E20-F20 -> 5.8207661e-11
H21: =+H20+E21-F21 -> 5.8207661e-11
H22: =+H21+E22-F22 -> 5.8207661e-11
H23: =+H22+E23-F23 -> 5.8207661e-11
H24: =+H23+E24-F24 -> 5.8207661e-11
H25: =+H24+E25-F25 -> 5.8207661e-11
H26: =+H25+E26-F26 -> 5.8207661e-11
H27: =+H26+E27-F27 -> 5.8207661e-11
H28: =+H27+E28-F28 -> 5.8207661e-11
... H68: =+H67+E68-F68 -> 5.8207661e-11
B69: TOTALES | E69: =SUM(E11:E68)+H11 -> 170675 | F69: =SUM(F11:F68) -> 170675
B70: SALDO POR COBRAR | F70: =+E69-F69 -> 0
B71: LINEA DE CREDITO | F71: 0
B72: SALDO DESPUES DE LA LINEA DE CREDITO | F72: =+F70-F71 -> 0

Sheet Ambulante EDUARDO
B2: CUENTAS POR COBRAR
B3: GESTION 2025 - 2026
C5: CLIENTE: | D5: Carlos Eduardo Gutierrez Salazar
C6: CELULAR:
C7: DESTINO: | D7: Sucre
C8: A CREDITO: | D8: SI
B10: NOTA DE VENTA | C10: NOTA DE ENTREGA | D10: FECHA DE DESPACHO | E10: MONTO P/COBRAR | F10: DEPÓSITO en Bs | G10: FECHA DE DEPÓSITO | H10: SALDO | I10: OBSERVACION
B11: 251250 | C11: 2130 | D11: 46007 | E11: 2550 | F11: 1200 | G11: 46013 | H11: =+E11-F11 -> 1350 | I11: Efectivo Recibo #1293
B12: 251278 | C12: 2165 | D12: 46011 | E12: 2690 | F12: 1350 | G12: 46015 | H12: =+H11+E12-F12 -> 2690 | I12: Efectivo Recibo #1300
F13: 2590 | G13: 46022 | H13: =+H12+E13-F13 -> 100 | I13: Efectivo Recibo #1331
F14: 100 | G14: 46022 | H14: =+H13+E14-F14 -> 0 | I14: Qr | K14: =SUM(F11:F14) -> 5240
B15: 260101 | C15: 2217 | D15: 46025 | E15: 870 | F15: 870 | G15: 46028 | H15: =+H14+E15-F15 -> 0 | I15: Efectivo Recibo #1353
B16: 260115 | C16: 2231 | D16: 46028 | E16: 1450 | F16: 1450 | G16: 46035 | H16: =+H15+E16-F16 -> 0 | I16: Efectivo Recibo #1381
B17: 260149 | C17: 2267 | D17: 46034 | E17: 580 | F17: 580 | G17: 46043 | H17: =+H16+E17-F17 -> 0 | I17: Efectivo Recibo #1417
B18: 2601107 | C18: 2328 | D18: 46042 | E18: 1260 | F18: 1260 | G18: 46049 | H18: =+H17+E18-F18 -> 0 | I18: Efectivo Recibo #1430 | K18: =SUM(F15:F18) -> 4160
B19: 2601127 | C19: 2350 | D19: 46048 | E19: 1160 | F19: 1160 | G19: 46056 | H19: =+H18+E19-F19 -> 0 | I19: Efectivo Recibo #1448
B20: 260203 | C20: 2386 | D20: 46055 | E20: 1160 | F20: 1050 | G20: 46064 | H20: =+H19+E20-F20 -> 110 | I20: Qr
F21: =192-82 -> 110 | G21: 46064 | H21: =+H20+E21-F21 -> 0 | I21: Efectivo Recibo #4936
B22: 260271 | C22: 2459 | D22: 46071 | E22: 540 | F22: 540 | G22: 46077 | H22: =+H21+E22-F22 -> 0 | I22: Efectivo Recibo #18 | K22: =SUM(F19:F22) -> 2860
B23: 260298 | C23: 2489 | D23: 46076 | E23: 1080 | F23: 1080 | G23: 46084 | H23: =+H22+E23-F23 -> 0 | I23: Efectivo Recibo #40
B24: 260303 | C24: 33 | D24: 46083 | E24: 540 | F24: 540 | G24: 46092 | H24: =+H23+E24-F24 -> 0 | I24: Efectivo Recibo #87
B25: 260343 | C25: 71 | D25: 46091 | E25: 884 | F25: 602 | G25: 46099 | H25: =+H24+E25-F25 -> 282 | I25: Efectivo Recibo #114
B26: 2603 | C26: 100 | D26: 46098 | E26: 810 | F26: 282 | G26: 46099 | H26: =+H25+E26-F26 -> 810 | I26: QR
B27: 2603 | C27: 139 | D27: 46105 | E27: 810 | F27: 810 | G27: 46106 | H27: =+H26+E27-F27 -> 810 | I27: Efectivo Recibo #151
B28: 2603 | C28: 172 | D28: 46112 | E28: 810 | F28: 510 | G28: 46112 | H28: =+H27+E28-F28 -> 1110 | I28: Efectivo Recibo #177
B29: 260420 | C29: 198 | D29: 46119 | E29: 540 | F29: 300 | G29: 46112 | H29: =+H28+E29-F29 -> 1350 | I29: QR
B30: 260451 | C30: 228 | D30: 46126 | E30: 540 | F30: 810 | G30: 46120 | H30: =+H29+E30-F30 -> 1080 | I30: Efectivo Recibo #213
B31: 260490 | C31: 267 | D31: 46140 | E31: 500 | F31: 540 | G31: 46128 | H31: =+H30+E31-F31 -> 1040 | I31: Efectivo Recibo #269
C32: 282 | D32: 46146 | E32: 750 | F32: 540 | G32: 46135 | H32: =+H31+E32-F32 -> 1250 | I32: Efectivo Recibo #301
C33: 327 | D33: 46161 | E33: 750 | F33: 400 | G33: 46161 | H33: =+H32+E33-F33 -> 1600 | I33: Efectivo Recibo #421
C34: 346 | D34: 46168 | E34: 750 | F34: 100 | G34: 46161 | H34: =+H33+E34-F34 -> 2250 | I34: QR
C35: 364 | D35: 46174 | E35: 750 | F35: 750 | G35: 46168 | H35: =+H34+E35-F35 -> 2250 | I35: Efectivo Recibo #450
C36: 490 | D36: 46213 | E36: 540 | F36: 750 | G36: 46174 | H36: =+H35+E36-F36 -> 2040 | I36: Efectivo Recibo #489
C37: 525 | D37: 46224 | E37: 540 | F37: 750 | G37: 46181 | H37: =+H36+E37-F37 -> 1830 | I37: Efectivo Recibo #557
C38: 546 | D38: 46231 | E38: 540 | F38: 600 | G38: 46189 | H38: =+H37+E38-F38 -> 1770 | I38: Efectivo Recibo #608
C39: 594 | D39: 46245 | E39: 540 | F39: 150 | G39: 46189 | H39: =+H38+E39-F39 -> 2160 | I39: Efectivo Recibo #608
C40: 636 | D40: 46258 | E40: 540 | F40: 540 | G40: 46224 | H40: =+H39+E40-F40 -> 2160 | I40: QR REC.741
C41: 657 | D41: 46265 | E41: 540 | F41: 320 | G41: 46232 | H41: =+H40+E41-F41 -> 2380 | I41: Efectivo Recibo #765
F42: 220 | G42: 46232 | H42: =+H41+E42-F42 -> 2160 | I42: QR
F43: 540 | G43: 46246 | H43: =+H42+E43-F43 -> 1620 | I43: Efectivo Recibo #807
F44: 540 | G44: 46260 | H44: =+H43+E44-F44 -> 1080 | I44: Efectivo Recibo #877
F45: 200 | G45: 46266 | H45: =+H44+E45-F45 -> 880 | I45: Efectivo Recibo #908
F46: 340 | G46: 46266 | H46: =+H45+E46-F46 -> 540 | I46: QR
H47: =+H46+E47-F47 -> 540
H48: =+H47+E48-F48 -> 540
H49: =+E50-F50 -> 540
B50: TOTALES | E50: =SUM(E11:E49) -> 25014 | F50: =SUM(F11:F49) -> 24474
B51: SALDO POR COBRAR | F51: =+E50-F50 -> 540

Sheet Oscar G. Paceña SUCRE
B2: CUENTAS POR COBRAR
B3: GESTION 2025 - 2026
C5: CLIENTE: | D5: Oscar Hugo Garzofino Catacora (Paceña)
C6: CELULAR:
C7: DESTINO: | D7: Sucre
C8: A CREDITO: | D8: 1 semana
B10: NOTA DE VENTA | C10: NOTA DE ENTREGA | D10: FECHA DE DESPACHO | E10: MONTO P/COBRAR | F10: DEPÓSITO en Bs | G10: FECHA DE DEPÓSITO | H10: SALDO | I10: OBSERVACION
B11: 260172 | C11: 2294 | D11: 46036 | E11: 1650 | F11: 1650 | G11: 46048 | H11: =+E11-F11 -> 0 | I11: Efectivo Recibo #1424
B12: 260216 | C12: 2404 | D12: 46057 | E12: 1650 | F12: 1650 | G12: 46065 | H12: =+H11+E12-F12 -> 0 | I12: Efectivo Recibo #4940 | K12: =SUM(F12) -> 1650
B13: 2603127 | C13: 163 | D13: 46111 | E13: 4600 | F13: 4600 | G13: 46126 | H13: =+H12+E13-F13 -> 0 | I13: Efectivo Recibo #256
B14: 260480 | C14: 256 | D14: 46134 | E14: 3100 | F14: 3100 | G14: 46142 | H14: =+H13+E14-F14 -> 0 | I14: Efectivo Recibo #326
C15: 302 | D15: 46155 | E15: 6400 | F15: 6400 | G15: 46170 | H15: =+H14+E15-F15 -> 0 | I15: Efectivo Recibo #475
H16: =+H15+E16-F16 -> 0
H17: =+H16+E17-F17 -> 0
H18: =+H17+E18-F18 -> 0
H19: =+H18+E19-F19 -> 0
H20: =+H19+E20-F20 -> 0
H21: =+H20+E21-F21 -> 0
H22: =+H21+E22-F22 -> 0
H23: =+H22+E23-F23 -> 0
B24: TOTALES | E24: =SUM(E11:E23) -> 17400 | F24: =SUM(F11:F23) -> 17400
B25: SALDO POR COBRAR | F25: =+E24-F24 -> 0

Sheet Supermencado SAS
B2: CUENTAS POR COBRAR
B3: GESTION 2025 - 2026
C5: CLIENTE: | D5: Supermercado SAS
C6: CELULAR:
C7: DESTINO: | D7: Sucre
C8: A CREDITO: | D8: A 1 mes de credito
B10: NOTA DE VENTA | C10: NOTA DE ENTREGA | D10: FECHA DE DESPACHO | E10: MONTO P/COBRAR | F10: DEPÓSITO en Bs | G10: FECHA DE DEPÓSITO | H10: SALDO | I10: OBSERVACION
B11: 251031 | C11: 1970 | D11: 45952 | E11: 7480 | F11: 7480 | G11: 45985 | H11: =+E11-F11 -> 0 | I11: Transferencia BU
B12: 251103 | C12: 2000 | D12: 45968 | E12: 1555 | F12: 1555 | G12: 46006 | H12: =+H11+E12-F12 -> 0
B13: 251111 | C13: 2024 | D13: 45979 | E13: 2060 | F13: 2060 | G13: 46013 | H13: =+H12+E13-F13 -> 0
B14: 251119 | C14: 2044 | D14: 45985 | E14: 1300 | F14: 1300 | G14: 46020 | H14: =+H13+E14-F14 -> 0 | L14: =SUM(F12:F14) -> 4915
B15: 251201 | C15: 2067 | D15: 45992 | E15: 0 | H15: =+H14+E15-F15 -> 0
B16: 251202 | C16: 2067 | D16: 45992 | E16: 4355 | F16: 4355 | G16: 46027 | H16: =+H15+E16-F16 -> 0 | I16: Transferencia BU
B17: 251217 | C17: 2084 | D17: 45996 | E17: 2910 | H17: =+H16+E17-F17 -> 2910
B18: 251224 | C18: 2099 | D18: 46000 | E18: 2600 | F18: 5510 | G18: 46034 | H18: =+H17+E18-F18 -> 0 | I18: Transferencia BU
B19: 251244 | C19: 2123 | D19: 46006 | E19: 3370 | F19: 3370 | G19: 46041 | H19: =+H18+E19-F19 -> 0 | I19: Transferencia BU
B20: 251261 | C20: 2143 | D20: 46009 | E20: 4020 | H20: =+H19+E20-F20 -> 4020
B21: 251285 | C21: 2173 | D21: 46013 | E21: 2898 | F21: 6918 | G21: 46048 | H21: =+H20+E21-F21 -> 0 | I21: Transferencia BU | L21: =SUM(F15:F21) -> 20153
B22: 2512105 | C22: 2198 | D22: 46020 | E22: 3330 | F22: 3330 | G22: 46055 | H22: =+H21+E22-F22 -> 0
B23: 260106 | C23: 2221 | D23: 46027 | E23: 5600 | F23: 5600 | G23: 46062 | H23: =+H22+E23-F23 -> 0
B24: 260162 | C24: 2282 | D24: 46035 | E24: 5285 | F24: 5285 | G24: 46071 | H24: =+H23+E24-F24 -> 0
B25: 260181 | C25: 2304 | D25: 46038 | E25: 6160 | F25: 6160 | G25: 46076 | H25: =+H24+E25-F25 -> 0 | L25: =SUM(F22:F26) -> 23553
B26: 2601135 | C26: 2355 | D26: 46049 | E26: 3178 | F26: 3178 | G26: 46083 | H26: =+H25+E26-F26 -> 0 | I26: Transferencia BU 5189492499
B27: 260204 | C27: 2387 | D27: 46055 | E27: 3447 | H27: =+H26+E27-F27 -> 3447
B28: 260231 | C28: 2419 | D28: 46060 | E28: 1612 | F28: 5059 | G28: 46090 | H28: =+H27+E28-F28 -> 0 | I28: Transferencia BU 5208852590
B29: 260277 | C29: 2465 | D29: 46072 | E29: 1952 | F29: 1952 | G29: 46104 | H29: =+H28+E29-F29 -> 0 | I29: Transferencia BU 5243609547
B30: 2602105 | C30: 2499 | D30: 46077 | E30: 3424 | F30: 3424 | G30: 46111 | H30: =+H29+E30-F30 -> 0 | I30: Transferencia BU 5260230914
B31: 260304 | C31: 34 | D31: 46083 | E31: 3763 | F31: 3763 | G31: 46118 | H31: =+H30+E31-F31 -> 0 | I31: Transferencia BU 5283531083
B32: 260326 | C32: 55 | D32: 46088 | E32: 6328 | F32: 6328 | G32: 46125 | H32: =+H31+E32-F32 -> 0 | I32: Transferencia BU 5303405112
B33: 260352 | C33: 82 | D33: 46093 | E33: 5546 | F33: 5546 | G33: 46132 | H33: =+H32+E33-F33 -> 0 | I33: Transferencia BU 5322974011
B34: 260387 | C34: 117 | D34: 46100 | E34: 1990 | F34: 1990 | G34: 46139 | H34: =+H33+E34-F34 -> 0 | I34: Transferencia BU 5339422431
B35: 260403 | C35: 181 | D35: 46113 | E35: 8678 | F35: 8678 | G35: 46146 | H35: =+H34+E35-F35 -> 0 | I35: Transferencia BU 5365111545
B36: 260419 | C36: 197 | D36: 46119 | E36: 2178 | F36: 2178 | G36: 46153 | H36: =+H35+E36-F36 -> 0 | I36: Transferencia BU 5385489267
B37: 260450 | C37: 227 | D37: 46126 | E37: 3800 | F37: 3800 | G37: 46160 | H37: =+H36+E37-F37 -> 0 | I37: Transferencia BU 5403609182
B38: 260477 | C38: 253 | D38: 46133 | E38: 6540 | F38: 6540 | G38: 46168 | H38: =+H37+E38-F38 -> 0 | I38: Transferencia BU 5423982559
B39: 260493 | C39: 269 | D39: 46140 | E39: 2200 | F39: 2200 | G39: 46174 | H39: =+H38+E39-F39 -> 0 | I39: Transferencia BU 5447085497
C40: 286 | D40: 46148 | E40: 3256 | F40: 3256 | G40: 46181 | H40: =+H39+E40-F40 -> 0 | I40: Transferencia BU 5467387609
C41: 316 | D41: 46158 | E41: 9198 | F41: 9198 | G41: 46196 | H41: =+H40+E41-F41 -> 0 | I41: Transferencia BU 5508214029
C42: 350 | D42: 46169 | E42: 4490 | F42: 4490 | G42: 46202 | H42: =+H41+E42-F42 -> 0 | I42: Transferencia BU 5524621504
C43: 366 | D43: 46175 | E43: 9894 | F43: 9894 | G43: 46209 | H43: =+H42+E43-F43 -> 0 | I43: Transferencia BU 5550782778
C44: 396 | D44: 46183 | E44: 5936 | F44: 5936 | G44: 46216 | H44: =+H43+E44-F44 -> 0 | I44: Transferencia BU 5571350239
C45: 429 | D45: 46192 | E45: 2264 | F45: 2264 | G45: 46230 | H45: =+H44+E45-F45 -> 0 | I45: Transferencia BU 5611148288
C46: 497 | D46: 46216 | E46: 2316 | F46: 2316 | G46: 46251 | H46: =+H45+E46-F46 -> 0 | I46: Transferencia BU 5680840235
C47: 526 | D47: 46224 | E47: 1612 | F47: 1612 | G47: 46258 | H47: =+H46+E47-F47 -> 0 | I47: Transferencia BU 5700788591
C48: 551 | D48: 46232 | E48: 870 | F48: 870 | G48: 46265 | H48: =+H47+E48-F48 -> 0 | I48: Transferencia BU 5721318607
C49: 575 | D49: 46238 | E49: 2610 | F49: 2610 | G49: 46272 | H49: =+H48+E49-F49 -> 0 | I49: Transferencia BU 5751542571
C50: 593 | D50: 46245 | E50: 6348 | H50: =+H49+E50-F50 -> 6348
C51: 642 | D51: 46259 | E51: 4120 | H51: =+H50+E51-F51 -> 10468
H52: =+H51+E52-F52 -> 10468
H53: =+H52+E53-F53 -> 10468
H54: =+H53+E54-F54 -> 10468
H55: =+H54+E55-F55 -> 10468
H56: =+H55+E56-F56 -> 10468
H57: =+H56+E57-F57 -> 10468
H58: =+H57+E58-F58 -> 10468
H59: =+H58+E59-F59 -> 10468
H60: =+H51+E60-F60 -> 10468
B61: TOTALES | E61: =SUM(E11:E60)+H11 -> 160473 | F61: =SUM(F11:F60) -> 150005
B62: SALDO POR COBRAR | F62: =+E61-F61 -> 10468

Sheet SOLAR Supermercado
B2: CUENTAS POR COBRAR
B3: GESTION 2025 - 2026
C5: CLIENTE: | D5: SOLAR SUPERMERCADO S.R.L.
C6: CELULAR:
C7: DESTINO: | D7: Sucre
C8: A CREDITO: | D8: A 1 mes de credito
B10: NOTA DE VENTA | C10: NOTA DE ENTREGA | D10: FECHA DE DESPACHO | E10: MONTO P/COBRAR | F10: DEPÓSITO en Bs | G10: FECHA DE DEPÓSITO | H10: SALDO | I10: OBSERVACION
B11: 251243 | C11: 2122 | D11: 46006 | E11: 4038 | F11: 4038 | G11: 46018 | H11: =+E11-F11 -> 0 | I11: Transferencia BCP | J11: BU
B12: 260189 | C12: 2312 | D12: 46039 | E12: 2034 | F12: 2034 | G12: 46078 | H12: =+H11+E12-F12 -> 0 | I12: Transferencia BCP | J12: BU
B13: 2602106 | C13: 2 | D13: 46077 | E13: 8350 | F13: 8350 | G13: 46122 | H13: =+H12+E13-F13 -> 0 | I13: Transferencia BCP | J13: BU
B14: 260443 | C14: 220 | D14: 46123 | E14: 2184 | F14: 2184 | G14: 46155 | H14: =+H13+E14-F14 -> 0 | I14: Transferencia BCP | J14: BU
C15: 326 | D15: 46161 | E15: 4288 | F15: 4288 | G15: 46225 | H15: =+H14+E15-F15 -> 0 | I15: Transferencia BCP Nro 9885922 | J15: BU
C16: 369 | D16: 46175 | E16: 3692 | F16: 3692 | G16: 46246 | H16: =+H15+E16-F16 -> 0 | I16: Transferencia BCP Nro 5666544607 | J16: BU
C17: 606 | D17: 46248 | E17: 3300 | H17: =+H16+E17-F17 -> 3300
H18: =+H17+E18-F18 -> 3300
H19: =+H18+E19-F19 -> 3300
H20: =+H19+E20-F20 -> 3300
H21: =+H20+E21-F21 -> 3300
H22: =+H21+E22-F22 -> 3300
H23: =+H22+E23-F23 -> 3300
B24: TOTALES | E24: =SUM(E11:E23) -> 27886 | F24: =SUM(F11:F23) -> 24586
B25: SALDO POR COBRAR | F25: =+E24-F24 -> 3300

Sheet LIDER Supermercado
B2: CUENTAS POR COBRAR
B3: GESTION 2025 - 2026
C5: CLIENTE: | D5: LIDER SUPERMERCADO S.R.L.
C6: CELULAR:
C7: DESTINO: | D7: Sucre
C8: A CREDITO:
B10: NOTA DE VENTA | C10: NOTA DE ENTREGA | D10: FECHA DE DESPACHO | E10: MONTO P/COBRAR | F10: DEPÓSITO en Bs | G10: FECHA DE DEPÓSITO | H10: SALDO | I10: OBSERVACION
B11: 251272 | C11: 2157 | D11: 46010 | E11: 1978 | F11: 1978 | G11: 46009 | H11: =+E11-F11 -> 0 | I11: Transferencia | J11: BU
B12: 2601109 | C12: 2330 | D12: 46042 | E12: 764 | F12: 764 | G12: 46043 | H12: =+H11+E12-F12 -> 0 | I12: Transferencia | L12: =SUM(F12) -> 764
B13: 260278 | C13: 2466 | D13: 46072 | E13: 672 | H13: =+H12+E13-F13 -> 672
B14: 260279 | C14: 2467 | D14: 46072 | E14: 672 | F14: 1344 | G14: 46072 | H14: =+H13+E14-F14 -> 0 | I14: Transferencia | J14: BNB
H15: =+H14+E15-F15 -> 0
H16: =+H15+E16-F16 -> 0
H17: =+H16+E17-F17 -> 0
H18: =+H17+E18-F18 -> 0
H19: =+H18+E19-F19 -> 0
H20: =+H19+E20-F20 -> 0
H21: =+H20+E21-F21 -> 0
H22: =+H21+E22-F22 -> 0
H23: =+H22+E23-F23 -> 0
B24: TOTALES | E24: =SUM(E11:E23) -> 4086 | F24: =SUM(F11:F23) -> 4086
B25: SALDO POR COBRAR | F25: =+E24-F24 -> 0

Sheet MERCAMAX SRL
B2: CUENTAS POR COBRAR
B3: GESTION 2025 - 2026
C5: CLIENTE: | D5: MERCAMAX S.R.L.
C6: CELULAR:
C7: DESTINO: | D7: Sucre
C8: A CREDITO: | D8: A 1 mes de credito
B10: NOTA DE VENTA | C10: NOTA DE ENTREGA | D10: FECHA DE DESPACHO | E10: MONTO P/COBRAR | F10: DEPÓSITO en Bs | G10: FECHA DE DEPÓSITO | H10: SALDO | I10: OBSERVACION
B11: 260198 | C11: 2319 | D11: 46041 | E11: 1257 | F11: 1257 | G11: 46076 | H11: =+E11-F11 -> 0 | I11: Según deposito bancario BNB 726022300103764, por error pagaron a la cuenta del ex distribuidor Cristhian Murillo el 19 de febrero
B12: 260223 | C12: 2411 | D12: 46058 | E12: 3647 | F12: 3647 | G12: 46105 | H12: =+H11+E12-F12 -> 0 | I12: Transferencia BU 5246271793
B13: 260327 | C13: 56 | D13: 46088 | E13: 3744 | F13: 3744 | G13: 46133 | H13: =+H12+E13-F13 -> 0 | I13: Transferencia BU 5325583304
C14: 289 | D14: 46149 | E14: 3418 | F14: 3418 | G14: 46192 | H14: =+H13+E14-F14 -> 0 | I14: Transferencia BU 5499445027
C15: 432 | D15: 46193 | E15: 1330 | F15: 1330 | G15: 46231 | H15: =+H14+E15-F15 -> 0 | I15: Transferencia BU 5614103575
C16: 592 | D16: 46245 | E16: 2544 | H16: =+H15+E16-F16 -> 2544
H17: =+H16+E17-F17 -> 2544
H18: =+H17+E18-F18 -> 2544
H19: =+H18+E19-F19 -> 2544
H20: =+H19+E20-F20 -> 2544
H21: =+H20+E21-F21 -> 2544
H22: =+H21+E22-F22 -> 2544
H23: =+H22+E23-F23 -> 2544
B24: TOTALES | E24: =SUM(E11:E23) -> 15940 | F24: =SUM(F11:F23) -> 13396
B25: SALDO POR COBRAR | F25: =+E24-F24 -> 2544

Sheet FARMACIA SAN AGUSTIN
B2: CUENTAS POR COBRAR
B3: GESTION 2025 - 2026
C5: CLIENTE: | D5: FARMACIA SAN AGUSTIN
C6: CELULAR:
C7: DESTINO: | D7: Sucre
C8: A CREDITO:
B10: NOTA DE VENTA | C10: NOTA DE ENTREGA | D10: FECHA DE DESPACHO | E10: MONTO P/COBRAR | F10: DEPÓSITO en Bs | G10: FECHA DE DEPÓSITO | H10: SALDO | I10: OBSERVACION
B11: 251262 | C11: 2145 | D11: 46009 | E11: 2812 | F11: 2812 | G11: 46010 | H11: =+E11-F11 -> 0 | I11: Efectivo Recibo #1284 | J11: BU
B12: 260290 | C12: 2481 | D12: 46073 | E12: 0 | H12: =+H11+E12-F12 -> 0
B13: 260299A | C13: 2491 | D13: 46076 | E13: 1798 | F13: 1798 | G13: 46076 | H13: =+H12+E13-F13 -> 0 | I13: Efectivo recibo #12 (Victor)
B14: 2603134 | C14: 171 | D14: 46112 | E14: 1910 | F14: 1910 | G14: 46112 | H14: =+H13+E14-F14 -> 0 | I14: Efectivo Recibo #179
C15: 298 | D15: 46153 | E15: 1976 | F15: 1976 | G15: 46154 | H15: =+H14+E15-F15 -> 0 | I15: Efectivo Recibo #402
C16: 367 | D16: 46175 | E16: 1932 | F16: 1932 | G16: 46181 | H16: =+H15+E16-F16 -> 0 | I16: Efectivo Recibo #560
C17: 415 | D17: 46189 | E17: 1204 | F17: 1204 | G17: 46190 | H17: =+H16+E17-F17 -> 0 | I17: Efectivo Recibo #613
H18: =+H17+E18-F18 -> 0
H19: =+H18+E19-F19 -> 0
H20: =+H19+E20-F20 -> 0
H21: =+H20+E21-F21 -> 0
H22: =+H21+E22-F22 -> 0
H23: =+H22+E23-F23 -> 0
H24: =+H23+E24-F24 -> 0
B25: TOTALES | E25: =SUM(E11:E24) -> 11632 | F25: =SUM(F11:F24) -> 11632
B26: SALDO POR COBRAR | F26: =+E25-F25 -> 0

Sheet Supermercado POMPEYA
B2: CUENTAS POR COBRAR
B3: GESTION 2025 - 2026
C5: CLIENTE: | D5: SUPERMERCADO POMPEYA
C6: CELULAR:
C7: DESTINO: | D7: Sucre
C8: A CREDITO: | D8: A 1 mes de credito
B10: NOTA DE VENTA | C10: NOTA DE ENTREGA | D10: FECHA DE DESPACHO | E10: MONTO P/COBRAR | F10: DEPÓSITO en Bs | G10: FECHA DE DEPÓSITO | H10: SALDO | I10: OBSERVACION
B11: 251249 | C11: 2129 | D11: 46007 | E11: 6170 | F11: 6170 | G11: 46056 | H11: =+E11-F11 -> 0 | I11: Transf. Gladys Daza Montalvo | J11: BU
B12: 260105 | C12: 2220 | D12: 46025 | E12: 4820 | F12: 4820 | G12: 46079 | H12: =+H11+E12-F12 -> 0 | I12: transf. | J12: BU
B13: 2602120 | C13: 17 | D13: 46080 | E13: 7316 | F13: 7316 | G13: 46108 | H13: =+H12+E13-F13 -> 0 | I13: Transf. B.U. Gladys Daza Montalvo Comprbnte Nro 54312657512
B14: 2603 | C14: 155 | D14: 46108 | E14: 7230 | F14: 7230 | G14: 46147 | H14: =+H13+E14-F14 -> 0 | I14: Transf. B.U. Gladys Daza Montalvo Comprbnte Nro 54612795897 | J14: B.U.
C15: 287 | D15: 46148 | E15: 9096 | F15: 9096 | G15: 46199 | H15: =+H14+E15-F15 -> 0 | I15: Transf. B.U. Gladys Daza Montalvo Comprbnte Nro 54612984892
C16: 447 | D16: 46200 | E16: 9232 | F16: 9232 | G16: 46248 | H16: =+H15+E16-F16 -> 0 | I16: Transf. B.U. Gladys Daza Montalvo Comprbnte Nro 54713138428
H17: =+H16+E17-F17 -> 0
H18: =+H17+E18-F18 -> 0
H19: =+H18+E19-F19 -> 0
H20: =+H19+E20-F20 -> 0
H21: =+H20+E21-F21 -> 0
H22: =+H21+E22-F22 -> 0
H23: =+H22+E23-F23 -> 0
B24: TOTALES | E24: =SUM(E11:E23) -> 43864 | F24: =SUM(F11:F23) -> 43864
B25: SALDO POR COBRAR | F25: =+E24-F24 -> 0

Sheet RECAU. Noviembre
A3: CUENTAS POR COBRAR A CLIENTES
A4: GESTION 2023 - 2024
A5: Noviembre- 2025
A6: Nº | B6: DISTRIBUIDOR | C6: DEPARTAMENTO | AI6: TOTAL MES
D7: 1 | E7: 2 | F7: 3 | G7: 4 | H7: Semana 1 | I7: 6 | J7: 7 | K7: 8 | L7: 9 | M7: 10 | N7: 11 | O7: Semana 2 | P7: 13 | Q7: 14 | R7: 15 | S7: 16 | T7: 17 | U7: 18 | V7: Semana 3 | W7: 20 | X7: 21 | Y7: 22 | Z7: 23 | AA7: 24 | AB7: 25 | AC7: Semana 4 | AD7: 27 | AE7: 28 | AF7: 29 | AG7: 31 | AH7: Semana 4
A8: 1 | B8: Fabricio Tapia Castedo | C8: Cochabamba | H8: =SUM(D8:G8) -> 0 | O8: =SUM(I8:N8) -> 0 | V8: =SUM(P8:U8) -> 0 | AC8: =SUM(W8:AB8) -> 0 | AH8: =SUM(AD8:AG8) -> 0 | AI8: =+H8+O8+V8+AH8 -> 0
A9: =1+A8 -> 2 | B9: Edwin Fernandez Chirinos | C9: El Alto | H9: =SUM(D9:G9) -> 0 | O9: =SUM(I9:N9) -> 0 | V9: =SUM(P9:U9) -> 0 | AC9: =SUM(W9:AB9) -> 0 | AH9: =SUM(AD9:AG9) -> 0 | AI9: =+H9+O9+V9+AH9 -> 0
A10: =1+A9 -> 3 | B10: Javier Caceres | C10: Cochabamba | H10: =SUM(D10:G10) -> 0 | O10: =SUM(I10:N10) -> 0 | V10: =SUM(P10:U10) -> 0 | AC10: =SUM(W10:AB10) -> 0 | AH10: =SUM(AD10:AG10) -> 0 | AI10: =+H10+O10+V10+AH10 -> 0
A11: =1+A10 -> 4 | B11: Juan Carlos Torrez Ayarde | C11: Tarija | H11: =SUM(D11:G11) -> 0 | O11: =SUM(I11:N11) -> 0 | V11: =SUM(P11:U11) -> 0 | AC11: =SUM(W11:AB11) -> 0 | AH11: =SUM(AD11:AG11) -> 0 | AI11: =+H11+O11+V11+AH11 -> 0
A12: =1+A11 -> 5 | B12: Carol Alejandra Noya | C12: Tarija | H12: =SUM(D12:G12) -> 0 | O12: =SUM(I12:N12) -> 0 | V12: =SUM(P12:U12) -> 0 | AC12: =SUM(W12:AB12) -> 0 | AH12: =SUM(AD12:AG12) -> 0 | AI12: =+H12+O12+V12+AH12 -> 0
A13: =1+A12 -> 6 | B13: Luis Alberto Chipana Peña | C13: Cochabamba | H13: =SUM(D13:G13) -> 0 | O13: =SUM(I13:N13) -> 0 | V13: =SUM(P13:U13) -> 0 | AC13: =SUM(W13:AB13) -> 0 | AH13: =SUM(AD13:AG13) -> 0 | AI13: =+H13+O13+V13+AH13 -> 0
A14: =1+A13 -> 7 | B14: Franz Carlos Alanez Flores | C14: El Alto | H14: =SUM(D14:G14) -> 0 | O14: =SUM(I14:N14) -> 0 | V14: =SUM(P14:U14) -> 0 | AC14: =SUM(W14:AB14) -> 0 | AH14: =SUM(AD14:AG14) -> 0 | AI14: =+H14+O14+V14+AH14 -> 0
A15: =1+A14 -> 8 | B15: Andrés Miguel Paniagua | C15: Oruro | H15: =SUM(D15:G15) -> 0 | O15: =SUM(I15:N15) -> 0 | V15: =SUM(P15:U15) -> 0 | AC15: =SUM(W15:AB15) -> 0 | AH15: =SUM(AD15:AG15) -> 0 | AI15: =+H15+O15+V15+AH15 -> 0
A16: =1+A15 -> 9 | B16: Alex Rolando Fernandez H. | C16: Oruro | H16: =SUM(D16:G16) -> 0 | O16: =SUM(I16:N16) -> 0 | V16: =SUM(P16:U16) -> 0 | AC16: =SUM(W16:AB16) -> 0 | AH16: =SUM(AD16:AG16) -> 0 | AI16: =+H16+O16+V16+AH16 -> 0
A17: =1+A16 -> 10 | B17: Franklin Ever Viveros | C17: Potosí | H17: =SUM(D17:G17) -> 0 | O17: =SUM(I17:N17) -> 0 | V17: =SUM(P17:U17) -> 0 | AC17: =SUM(W17:AB17) -> 0 | AH17: =SUM(AD17:AG17) -> 0 | AI17: =+H17+O17+V17+AH17 -> 0
A18: =1+A17 -> 11 | B18: Teofilo Ibañez Soliz | C18: Tarija | H18: =SUM(D18:G18) -> 0 | O18: =SUM(I18:N18) -> 0 | V18: =SUM(P18:U18) -> 0 | AC18: =SUM(W18:AB18) -> 0 | AH18: =SUM(AD18:AG18) -> 0 | AI18: =+H18+O18+V18+AH18 -> 0
A19: =1+A18 -> 12 | B19: Elsa Romay Padilla | C19: Uyuni | H19: =SUM(D19:G19) -> 0 | O19: =SUM(I19:N19) -> 0 | V19: =SUM(P19:U19) -> 0 | AC19: =SUM(W19:AB19) -> 0 | AH19: =SUM(AD19:AG19) -> 0 | AI19: =+H19+O19+V19+AH19 -> 0
A20: =1+A19 -> 13 | B20: Jorge Luis Vedia Arancibia | C20: Chuquisaca - Prov | H20: =SUM(D20:G20) -> 0 | O20: =SUM(I20:N20) -> 0 | V20: =SUM(P20:U20) -> 0 | AC20: =SUM(W20:AB20) -> 0 | AH20: =SUM(AD20:AG20) -> 0 | AI20: =+H20+O20+V20+AH20 -> 0
A21: =1+A20 -> 14 | B21: Celina Cruz Mendez | C21: Chuquisaca - Prov | H21: =SUM(D21:G21) -> 0 | O21: =SUM(I21:N21) -> 0 | V21: =SUM(P21:U21) -> 0 | AC21: =SUM(W21:AB21) -> 0 | AH21: =SUM(AD21:AG21) -> 0 | AI21: =+H21+O21+V21+AH21 -> 0
A22: =1+#REF! -> #REF! | B22: Marlene Paicho | C22: Ruta Colquechaca | H22: =SUM(D22:G22) -> 0 | O22: =SUM(I22:N22) -> 0 | V22: =SUM(P22:U22) -> 0 | AC22: =SUM(W22:AB22) -> 0 | AH22: =SUM(AD22:AG22) -> 0 | AI22: =H22+O22+V22+AH22 -> 0
A23: TOTAL CLIENTES MOROSOS | G23: =SUM(G8:G22) -> 0 | H23: =SUM(D23:G23) -> 0 | I23: =SUM(I8:I22) -> 0 | J23: =SUM(J8:J22) -> 0 | K23: =SUM(K8:K22) -> 0 | L23: =SUM(L8:L22) -> 0 | M23: =SUM(M8:M22) -> 0 | N23: =SUM(N8:N22) -> 0 | O23: =SUM(I23:N23) -> 0 | P23: =SUM(P8:P22) -> 0 | Q23: =SUM(Q8:Q22) -> 0 | R23: =SUM(R8:R22) -> 0 | S23: =SUM(S8:S22) -> 0 | T23: =SUM(T8:T22) -> 0 | U23: =SUM(U8:U22) -> 0 | V23: =SUM(P23:U23) -> 0 | W23: =SUM(W8:W22) -> 0 | X23: =SUM(X8:X22) -> 0 | Y23: =SUM(Y8:Y22) -> 0 | Z23: =SUM(Z8:Z22) -> 0 | AA23: =SUM(AA8:AA22) -> 0 | AB23: =SUM(AB8:AB22) -> 0 | AC23: =SUM(W23:AB23) -> 0 | AD23: =SUM(AD8:AD22) -> 0 | AG23: =SUM(AG8:AG22) -> 0 | AH23: =SUM(AD23:AG23) -> 0 | AI23: =SUM(AI8:AI22) -> 0
A24: 1 | B24: Gustavo Tellez Ugarte | C24: Santa Cruz | H24: =SUM(D24:G24) -> 0 | O24: =SUM(I24:N24) -> 0 | V24: =SUM(P24:U24) -> 0 | AC24: =SUM(W24:AB24) -> 0 | AH24: =SUM(AD24:AG24) -> 0 | AI24: =H24+O24+V24+AC24+AH24 -> 0
A25: =1+A24 -> 2 | B25: Cristhian Murillo | C25: Sucre | H25: =SUM(D25:G25) -> 0 | O25: =SUM(I25:N25) -> 0 | V25: =SUM(P25:U25) -> 0 | AC25: =SUM(W25:AB25) -> 0 | AG25: 146966 | AH25: =SUM(AD25:AG25) -> 146966 | AI25: =H25+O25+V25+AC25+AH25 -> 146966
A26: =1+A25 -> 3 | B26: Fausto Condori | C26: Cochabamba | H26: =SUM(D26:G26) -> 0 | O26: =SUM(I26:N26) -> 0 | V26: =SUM(P26:U26) -> 0 | AC26: =SUM(W26:AB26) -> 0 | AH26: =SUM(AD26:AG26) -> 0 | AI26: =H26+O26+V26+AC26+AH26 -> 0
A27: =1+A26 -> 4 | B27: GAMS Desarrollo Productivo | C27: Sucre | H27: =SUM(D27:G27) -> 0 | O27: =SUM(I27:N27) -> 0 | V27: =SUM(P27:U27) -> 0 | AC27: =SUM(W27:AB27) -> 0 | AG27: 17632 | AH27: =SUM(AD27:AG27) -> 17632 | AI27: =H27+O27+V27+AC27+AH27 -> 17632
A28: =1+A27 -> 5 | B28: GAMS Direccion Administrativa | C28: Sucre | H28: =SUM(D28:G28) -> 0 | O28: =SUM(I28:N28) -> 0 | V28: =SUM(P28:U28) -> 0 | AC28: =SUM(W28:AB28) -> 0 | AH28: =SUM(AD28:AG28) -> 0 | AI28: =H28+O28+V28+AC28+AH28 -> 0
A29: =1+A28 -> 6 | B29: Carmen Cruz | C29: Potosí | H29: =SUM(D29:G29) -> 0 | O29: =SUM(I29:N29) -> 0 | V29: =SUM(P29:U29) -> 0 | AC29: =SUM(W29:AB29) -> 0 | AG29: 325250 | AH29: =SUM(AD29:AG29) -> 325250 | AI29: =H29+O29+V29+AC29+AH29 -> 325250
A30: =1+A29 -> 7 | B30: Jorge Saavedra | C30: Tupiza | H30: =SUM(D30:G30) -> 0 | O30: =SUM(I30:N30) -> 0 | V30: =SUM(P30:U30) -> 0 | AC30: =SUM(W30:AB30) -> 0 | AH30: =SUM(AD30:AG30) -> 0 | AI30: =H30+O30+V30+AC30+AH30 -> 0
A31: =1+A30 -> 8 | B31: Jenrry | C31: Chile | H31: =SUM(D31:G31) -> 0 | O31: =SUM(I31:N31) -> 0 | V31: =SUM(P31:U31) -> 0 | AC31: =SUM(W31:AB31) -> 0 | AG31: 219099.2 | AH31: =SUM(AD31:AG31) -> 219099.2 | AI31: =H31+O31+V31+AC31+AH31 -> 219099.2
A32: =1+A31 -> 9 | B32: Eddy | C32: Chile | H32: =SUM(D32:G32) -> 0 | O32: =SUM(I32:N32) -> 0 | V32: =SUM(P32:U32) -> 0 | AC32: =SUM(W32:AB32) -> 0 | AG32: 209833 | AH32: =SUM(AD32:AG32) -> 209833 | AI32: =H32+O32+V32+AC32+AH32 -> 209833
A33: =1+A32 -> 10 | B33: Rene Cahuana | C33: La Paz | H33: =SUM(D33:G33) -> 0 | O33: =SUM(I33:N33) -> 0 | V33: =SUM(P33:U33) -> 0 | AC33: =SUM(W33:AB33) -> 0 | AH33: =SUM(AD33:AG33) -> 0 | AI33: =H33+O33+V33+AC33+AH33 -> 0
A34: =1+A33 -> 11 | B34: Ines Aguirre | C34: Provincias Villazon | H34: =SUM(D34:G34) -> 0 | O34: =SUM(I34:N34) -> 0 | V34: =SUM(P34:U34) -> 0 | AC34: =SUM(W34:AB34) -> 0 | AH34: =SUM(AD34:AG34) -> 0 | AI34: =H34+O34+V34+AC34+AH34 -> 0
A35: =1+A34 -> 12 | B35: Yobana Llanos Cruz | C35: Ruta Chapare | H35: =SUM(D35:G35) -> 0 | O35: =SUM(I35:N35) -> 0 | V35: =SUM(P35:U35) -> 0 | AC35: =SUM(W35:AB35) -> 0 | AH35: =SUM(AD35:AG35) -> 0 | AI35: =H35+O35+V35+AC35+AH35 -> 0
A36: =1+A35 -> 13 | B36: Hernan Colque Cruz | C36: Pisiga | H36: =SUM(D36:G36) -> 0 | O36: =SUM(I36:N36) -> 0 | V36: =SUM(P36:U36) -> 0 | AC36: =SUM(W36:AB36) -> 0 | AH36: =SUM(AD36:AG36) -> 0 | AI36: =H36+O36+V36+AC36+AH36 -> 0
A37: =1+A36 -> 14 | B37: Ismael Marca | C37: Uyuni | H37: =SUM(D37:G37) -> 0 | O37: =SUM(I37:N37) -> 0 | V37: =SUM(P37:U37) -> 0 | AC37: =SUM(W37:AB37) -> 0 | AG37: 59350 | AH37: =SUM(AD37:AG37) -> 59350 | AI37: =H37+O37+V37+AC37+AH37 -> 59350
A38: =1+A37 -> 15 | B38: Ruth Gabriela | C38: Pando | AH38: =SUM(AD38:AG38) -> 0 | AI38: =H38+O38+V38+AC38+AH38 -> 0
A39: =1+A38 -> 16 | B39: Jhaneth Miriam Toroya Gabriel | C39: Oruro | AG39: 200614 | AH39: =SUM(AD39:AG39) -> 200614 | AI39: =H39+O39+V39+AC39+AH39 -> 200614
A40: =1+A39 -> 17 | B40: Herctor - Jorge | C40: La Paz | AG40: 74750 | AH40: =SUM(AD40:AG40) -> 74750 | AI40: =H40+O40+V40+AC40+AH40 -> 74750
A41: =1+A40 -> 18 | B41: Alexander Vides | C41: Tarija | AG41: 117175 | AH41: =SUM(AD41:AG41) -> 117175 | AI41: =H41+O41+V41+AC41+AH41 -> 117175
A42: =1+A41 -> 19 | B42: Paul Yamani | C42: Cochabamba | AH42: =SUM(AD42:AG42) -> 0 | AI42: =H42+O42+V42+AC42+AH42 -> 0
A43: =1+A42 -> 20 | B43: Alejandro Luna | C43: Chile | AH43: =SUM(AD43:AG43) -> 0 | AI43: =H43+O43+V43+AC43+AH43 -> 0
A44: =1+A43 -> 21 | B44: Yoelma | C44: Tupiza Villazon | AH44: =SUM(AD44:AG44) -> 0 | AI44: =H44+O44+V44+AC44+AH44 -> 0
A45: =1+A44 -> 22 | B45: SAS | C45: Caracollo | AG45: 7480 | AH45: =SUM(AD45:AG45) -> 7480 | AI45: =H45+O45+V45+AC45+AH45 -> 7480
A46: =1+A45 -> 23 | B46: Miguel Zurita | C46: Caranavi | AG46: 58539 | AH46: =SUM(AD46:AG46) -> 58539 | AI46: =H46+O46+V46+AC46+AH46 -> 58539
A47: =1+A46 -> 24 | B47: Venta colillas y otros | C47: Sucre | H47: =SUM(D47:G47) -> 0 | O47: =SUM(I47:N47) -> 0 | V47: =SUM(P47:U47) -> 0 | AC47: =SUM(W47:AB47) -> 0 | AH47: =SUM(AD47:AG47) -> 0 | AI47: =H47+O47+V47+AC47+AH47 -> 0
A48: =1+A47 -> 25 | B48: Ventas en FABRICA | C48: Sucre | H48: =SUM(D48:G48) -> 0 | O48: =SUM(I48:N48) -> 0 | V48: =SUM(P48:U48) -> 0 | AC48: =SUM(W48:AB48) -> 0 | AG48: =12185+96677 -> 108862 | AH48: =SUM(AD48:AG48) -> 108862 | AI48: =H48+O48+V48+AC48+AH48 -> 108862
A49: TOTALE CLIENTES ACTIVOS | G49: =SUM(G24:G48) -> 0 | H49: =SUM(D49:G49) -> 0 | I49: =SUM(I24:I48) -> 0 | J49: =SUM(J24:J48) -> 0 | K49: =SUM(K24:K48) -> 0 | L49: =SUM(L24:L48) -> 0 | M49: =SUM(M24:M48) -> 0 | N49: =SUM(N24:N48) -> 0 | O49: =SUM(I49:N49) -> 0 | P49: =SUM(P24:P48) -> 0 | Q49: =SUM(Q24:Q48) -> 0 | R49: =SUM(R24:R48) -> 0 | S49: =SUM(S24:S48) -> 0 | T49: =SUM(T24:T48) -> 0 | U49: =SUM(U24:U48) -> 0 | V49: =SUM(P49:U49) -> 0 | W49: =SUM(W24:W48) -> 0 | X49: =SUM(X24:X48) -> 0 | Y49: =SUM(Y24:Y48) -> 0 | Z49: =SUM(Z24:Z48) -> 0 | AA49: =SUM(AA24:AA48) -> 0 | AB49: =SUM(AB24:AB48) -> 0 | AC49: =SUM(W49:AB49) -> 0 | AD49: =SUM(AD24:AD48) -> 0 | AE49: =SUM(AE24:AE48) -> 0 | AF49: =SUM(AF24:AF48) -> 0 | AG49: =SUM(AG24:AG48) -> 1545550.2 | AH49: =SUM(AD49:AG49) -> 1545550.2 | AI49: =SUM(AI24:AI48) -> 1545550.2
A50: TOTALE CLIENTES | D50: =+D23+D49 -> 0 | E50: =+E23+E49 -> 0 | F50: =+F23+F49 -> 0 | G50: =+G23+G49 -> 0 | H50: =SUM(D50:G50) -> 0 | I50: =+I23+I49 -> 0 | J50: =+J23+J49 -> 0 | K50: =+K23+K49 -> 0 | L50: =+L23+L49 -> 0 | M50: =+M23+M49 -> 0 | N50: =+N23+N49 -> 0 | O50: =SUM(I50:N50) -> 0 | P50: =+P23+P49 -> 0 | Q50: =+Q23+Q49 -> 0 | R50: =+R23+R49 -> 0 | S50: =+S23+S49 -> 0 | T50: =+T23+T49 -> 0 | U50: =+U23+U49 -> 0 | V50: =SUM(P50:U50) -> 0 | W50: =+W23+W49 -> 0 | X50: =+X23+X49 -> 0 | Y50: =+Y23+Y49 -> 0 | Z50: =+Z23+Z49 -> 0 | AA50: =+AA23+AA49 -> 0 | AB50: =+AB23+AB49 -> 0 | AC50: =SUM(W50:AB50) -> 0 | AD50: =+AD23+AD49 -> 0 | AH50: =SUM(AD50:AG50) -> 0 | AI50: =SUM(AI49,AI23) -> 1545550.2

Sheet RUTH ZARATE
B2: CUENTAS POR COBRAR
B3: GESTION 2025 - 2026
C5: CLIENTE: | D5: Ruth Zarate Rafaele
C6: CELULAR: | D6: 7516576
C7: DESTINO: | D7: Sucre
C8: CARGO | D8: Vendedor Comisionista
B10: NOTA DE VENTA | C10: NOTA DE ENTREGA | D10: FECHA DE DESPACHO | E10: MONTO P/COBRAR | F10: DEPÓSITO en Bs | G10: FECHA DE DEPÓSITO | H10: SALDO | I10: DIAS DE MORA | J10: OBSERVACION
B11: 251204 | C11: 2060 | D11: 45992 | E11: 6660 | H11: =+E11-F11 -> 6660
B12: 251207 | C12: 2070 | D12: 45993 | E12: 7806 | F12: 6660 | G12: 45993 | H12: =+H11+E12-F12 -> 7806 | J12: Recibo #1210 | L12: NOTA | M12: Creditos | N12: NOTA | O12: Creditos | P12: NOTA | Q12: Creditos
B13: 251210 | C13: 2073 | D13: 45993 | E13: 7370 | F13: 11000 | G13: 45994 | H13: =+H12+E13-F13 -> 4176 | J13: Recibo #1215 | L13: 4006 | M13: 632 | N13: 4026 | O13: 1390
B14: 251211 | C14: 2075 | D14: 45994 | E14: 4280 | F14: 6600 | G14: 45995 | H14: =+H13+E14-F14 -> 1856 | L14: 4013 | M14: 300 | N14: 4027 | O14: 1150
B15: 251215 | C15: 2081 | D15: 45995 | E15: 6410 | F15: 8500 | G15: 45997 | H15: =+H14+E15-F15 -> -234 | L15: 4014 | M15: 1580 | N15: 4039 | O15: 642
B16: 251216 | C16: 2083 | D16: 45996 | E16: 8590 | F16: 1474 | G16: 45997 | H16: =+H15+E16-F16 -> 6882 | J16: QR | L16: 4015 | M16: 230
B17: 251219 | C17: 2086 | D17: 45996 | E17: 860 | F17: 5000 | G17: 45997 | H17: =+H16+E17-F17 -> 2742 | M17: =SUM(M13:M16) -> 2742 | O17: =SUM(O13:O16) -> 3182 | Q17: 9768.5 | R17: 4227.5
F18: 2742 | G18: 45999 | H18: =+H17+E18-F18 -> 0
B19: 251221 | C19: 2090 | D19: 45999 | E19: 6720 | F19: 4900 | G19: 46000 | H19: =+H18+E19-F19 -> 1820 | J19: 1253
F20: 1820 | G20: 46001 | H20: =+H19+E20-F20 -> 0 | J20: Recibo #1256
B21: 251226 | C21: 2096 | D21: 46000 | E21: 6940 | F21: 2180 | G21: 46001 | H21: =+H20+E21-F21 -> 4760 | J21: Recibo #1256
B22: 251228 | C22: 2101 | D22: 46000 | E22: 3790 | H22: =+H21+E22-F22 -> 8550
B23: 251230 | C23: 2104 | D23: 46001 | E23: 4070 | F23: 2100 | G23: 46002 | H23: =+H22+E23-F23 -> 10520 | J23: 1259
B24: 251233 | C24: 2110 | D24: 46002 | E24: 3040 | F24: 4400 | G24: 46003 | H24: =+H23+E24-F24 -> 9160 | J24: 1262
B25: 251236 | C25: 2113 | D25: 46003 | E25: 4600 | F25: 3800 | G25: 46004 | H25: =+H24+E25-F25 -> 9960 | J25: 1265
B26: 251238 | C26: 2117 | D26: 46004 | E26: 1200 | F26: 5000 | G26: 46004 | H26: =+H25+E26-F26 -> 6160 | J26: Qr
F27: 1200 | G27: 46004 | H27: =+H26+E27-F27 -> 4960 | J27: 1266
F28: 4960 | G28: 46006 | H28: =+H27+E28-F28 -> 0
B29: 251242 | C29: 2121 | D29: 46006 | E29: 7010 | F29: 4000 | G29: 46007 | H29: =+H28+E29-F29 -> 3010 | J29: 1274
B30: 251248 | C30: 2128 | D30: 46007 | E30: 6170 | F30: 5200 | G30: 46008 | H30: =+H29+E30-F30 -> 3980 | J30: 1278
B31: 251252 | C31: 2133 | D31: 46007 | E31: 4320 | F31: 3000 | G31: 46009 | H31: =+H30+E31-F31 -> 5300 | J31: 1282
B32: 251253 | C32: 2135 | D32: 46008 | E32: 3380 | F32: 3380 | G32: 46010 | H32: =+H31+E32-F32 -> 5300 | J32: Recibo # 1287
B33: 251254 | C33: 2036 | D33: 46008 | E33: 860 | F33: 860 | G33: 46010 | H33: =+H32+E33-F33 -> 5300 | J33: Recibo # 1287
B34: 251260 | C34: 2140 | D34: 46009 | E34: 8720 | F34: 8720 | G34: 46010 | H34: =+H33+E34-F34 -> 5300 | J34: Recibo # 1287
B35: 251263 | C35: 2146 | D35: 46009 | E35: 7960 | F35: 10040 | G35: 46010 | H35: =+H34+E35-F35 -> 3220 | J35: Recibo # 1287
B36: 251266 | C36: 2151 | D36: 46009 | E36: 10730 | F36: 6300 | G36: 46011 | H36: =+H35+E36-F36 -> 7650
B37: 251267 | C37: 2152 | D37: 46009 | E37: 13692 | F37: 0 | H37: =+H36+E37-F37 -> 21342 | O37: 450000
B38: 251273 | C38: 2159 | D38: 46010 | E38: 3096 | F38: 0 | H38: =+H37+E38-F38 -> 24438 | O38: =+O37*8 -> 3600000
B39: 251275 | C39: 2161 | D39: 46010 | E39: 8642 | F39: 28700 | G39: 46013 | H39: =+H38+E39-F39 -> 4380 | J39: 1294
B40: 251277 | C40: 2163 | D40: 46010 | E40: 10079 | H40: =+H39+E40-F40 -> 14459
B41: 251280 | C41: 2167 | D41: 46011 | E41: 9760 | H41: =+H40+E41-F41 -> 24219
B42: 251282 | C42: 2170 | D42: 46011 | E42: 17225 | H42: =+H41+E42-F42 -> 41444
F43: 10500 | G43: 46014 | H43: =+H42+E43-F43 -> 30944 | J43: 1297
F44: 13500 | G44: 46014 | H44: =+H43+E44-F44 -> 17444 | J44: Qr.
F45: 7150 | G45: 46015 | H45: =+H44+E45-F45 -> 10294 | J45: 1302
B46: 251288 | C46: 2177 | D46: 46014 | E46: 5340 | F46: 3800 | G46: 46018 | H46: =+H45+E46-F46 -> 11834 | J46: DEPOSITO
B47: 251295 | C47: 2185 | D47: 46015 | E47: 6820 | F47: 5020 | G47: 46020 | H47: =+H46+E47-F47 -> 13634 | J47: Qr.
F48: 3850 | G48: 46020 | H48: =+H47+E48-F48 -> 9784 | J48: efectivo
B49: 2512119 | C49: 2209 | D49: 46022 | E49: -5285 | F49: 271.5 | G49: 46022 | H49: =+H48+E49-F49 -> 4227.5
H50: =+H49+E50-F50 -> 4227.5
F51: 4227.5 | G51: Credito a Sra. Sandra | H51: =+H50+E51-F51 -> 0 | J51: descontado de su comision
H52: =+H51+E52-F52 -> 0
H53: =+H52+E53-F53 -> 0
B54: TOTALES | E54: =SUM(E11:E53) -> 190855 | F54: =SUM(F11:F53) -> 190855
E55: SALDO | F55: =+E54-F54 -> 0
E56: CREDITOS | F56: 0
E57: Inventario | F57: 0
E58: SALDO A COBRAR | F58: =+F55-F56-F57 -> 0
E59: Comision del 5% | F59: =+E54*5% -> 9542.75

Sheet Cristhian Murillo
B2: CUENTAS POR COBRAR
B3: GESTION 2025 - 2026
C5: CLIENTE: | D5: Cristhian Murillo
C6: CELULAR: | D6: 73417475
C7: DESTINO: | D7: SUCRE
C8: LINEA DE CREDITO: | D8: 0
B10: NOTA DE VENTA | C10: NOTA DE ENTREGA | D10: FECHA DE DESPACHO | E10: MONTO P/COBRAR | F10: DEPÓSITO en Bs | G10: FECHA DE DEPÓSITO | H10: SALDO | I10: DIAS DE MORA | J10: OBSERVACION
B11: SALDO AL 31/03/25 | H11: 101349.62
B12: 250401 | C12: 1693 | D12: 45751 | E12: 30900 | F12: 17000 | G12: 45749 | H12: =+H11+E12-F12 -> 115249.62 | J12: EFECTIVO recibo 941
B13: 250406 | C13: 1699 | D13: 45756 | E13: 30206.5 | F13: 9000 | G13: 45749 | H13: =+H12+E13-F13 -> 136456.12 | J13: Transferencia Murillo Cristhian
B14: 250409 | C14: 1703 | D14: 45757 | E14: 29950 | F14: 30000 | G14: 45755 | H14: =+H13+E14-F14 -> 136406.12 | J14: EFECTIVO recibo 943
B15: 250415 | C15: 1710 | D15: 45763 | E15: 35356 | F15: 70000 | G15: 45762 | H15: =+H14+E15-F15 -> 101762.12 | J15: Murillo C. Cristhian M. | K15: BNB
B16: 250425 | C16: 1719 | D16: 45769 | E16: 30705 | F16: 32800 | G16: 45770 | H16: =+H15+E16-F16 -> 99667.12 | J16: EFECTIVO recibo 946
B17: 250428 | C17: 1722 | D17: 45772 | E17: 32255 | F17: 13200 | G17: 45770 | H17: =+H16+E17-F17 -> 118722.12 | J17: Transferencia Murillo Cristhian | K17: BNB
B18: 250430 | C18: 1724 | D18: 45773 | E18: 31395 | H18: =+H17+E18-F18 -> 150117.12
B19: 250435 | C19: 1729 | D19: 45775 | E19: 31102 | H19: =+H18+E19-F19 -> 181219.12
B20: TOTAL ABRIL | E20: =SUM(E12:E19) -> 251869.5 | F20: =SUM(F12:F19) -> 172000
F21: 30000 | G21: 45782 | H21: =+H19+E21-F21 -> 151219.12 | J21: EFECTIVO recibo 946
F22: 39000 | G22: 45417 | H22: =+H21+E22-F22 -> 112219.12 | J22: Murillo C. Cristhian M. | K22: BNB | L22: =SUM(F12:F22) -> 413000
B23: 250508 | C23: 1747 | D23: 45790 | E23: 35829 | F23: 35000 | G23: 45785 | H23: =+H22+E23-F23 -> 113048.12 | J23: EFECTIVO recibo 1006
B24: 250509 | C24: 1749 | D24: 45791 | E24: 34311 | F24: 15000 | G24: 45785 | H24: =+H23+E24-F24 -> 132359.12 | J24: Transferencia Murillo Cristhian | K24: BNB
B25: 250516 | C25: 1764 | D25: 45800 | E25: 52463 | F25: 30000 | G25: 45792 | H25: =+H24+E25-F25 -> 154822.12 | J25: Murillo C. Cristhian M. | K25: BNB
B26: 250525 | C26: 1770 | D26: 45806 | E26: 21562.5 | F26: 26000 | G26: 45797 | H26: =+H25+E26-F26 -> 150384.62 | J26: EFECTIVO recibo 1014
F27: 30000 | G27: 45806 | H27: =+H26+E27-F27 -> 120384.62 | J27: EFECTIVO recibo 1022 | L27: =SUM(F21:F27) -> 205000
B28: TOTAL MAYO | E28: =SUM(E21:E27) -> 144165.5 | F28: =SUM(F21:F27) -> 205000
F29: 60000 | G29: 45812 | H29: =+H27+E29-F29 -> 60384.62 | J29: EFECTIVO recibo 1023
B30: 250620 | C30: 1794 | D30: 45838 | E30: 36850 | F30: 40000 | G30: 45838 | H30: =+H29+E30-F30 -> 57234.62 | J30: EFECTIVO recibo 1028 | L30: =SUM(F29:F30) -> 100000
B31: TOTAL JUNIO | E31: =SUM(E29:E30) -> 36850 | F31: =SUM(F29:F30) -> 100000
B32: 250701 | C32: 1795 | D32: 45839 | E32: 38425 | F32: 60000 | G32: 45841 | H32: =+H30+E32-F32 -> 35659.62 | J32: EFECTIVO recibo 1031
B33: 250706 | C33: 1800 | D33: 45841 | E33: 39362.5 | F33: 50000 | G33: 45845 | H33: =+H32+E33-F33 -> 25022.12 | J33: EFECTIVO recibo 1035
B34: 250707 | C34: 1802 | D34: 45845 | E34: 23825 | F34: 40000 | G34: 45846 | H34: =+H33+E34-F34 -> 8847.12 | J34: EFECTIVO recibo 1037
B35: 250710 | C35: 1811 | D35: 45846 | E35: 37970 | F35: 55000 | G35: 45849 | H35: =+H34+E35-F35 -> -8182.88 | J35: EFECTIVO recibo 1039
B36: 250713 | C36: 1808 | D36: 45849 | E36: 38635 | F36: 24940 | G36: 45852 | H36: =+H35+E36-F36 -> 5512.12 | J36: EFECTIVO recibo 1041
B37: 250717 | C37: 1813 | D37: 45852 | E37: 39112.5 | F37: 15060 | G37: 45852 | H37: =+H36+E37-F37 -> 29564.62 | J37: Transferencia Murillo Cristhian | K37: BNB
B38: 250725 | C38: 1823 | D38: 45855 | E38: 37850 | F38: 26000 | G38: 45855 | H38: =+H37+E38-F38 -> 41414.62 | J38: EFECTIVO recibo 1044
B39: 250734 | C39: 1832 | D39: 45862 | E39: 38250 | F39: 34500 | G39: 45861 | H39: =+H38+E39-F39 -> 45164.62 | J39: EFECTIVO recibo 1048
B40: 250737 | C40: 1835 | D40: 45867 | E40: 38698 | F40: 16000 | G40: 45863 | H40: =+H39+E40-F40 -> 67862.62 | J40: Murillo C. Cristhian M. | K40: BU
F41: 4000 | G41: 45863 | H41: =+H40+E41-F41 -> 63862.62 | J41: Transferencia Murillo Cristhian | K41: BU
F42: 16000 | G42: 45867 | H42: =+H41+E42-F42 -> 47862.62 | J42: EFECTIVO recibo 1051 | L42: =SUM(E32:E40) -> 332128 | M42: =+L42/65000 -> 5.1096615
B43: TOTAL JULIO | E43: =SUM(E32:E42) -> 332128 | F43: =SUM(F32:F42) -> 341500
B44: 250801 | C44: 1843 | D44: 45871 | E44: 38362.5 | F44: 23000 | G44: 45871 | H44: =+H42+E44-F44 -> 63225.12
B45: 250805 | C45: 1845 | D45: 45877 | E45: 37735 | F45: 20000 | G45: 45877 | H45: =+H44+E45-F45 -> 80960.12
B46: 250809 | C46: 1849 | D46: 45884 | E46: 37382.5 | F46: 10000 | G46: 45880 | H46: =+H45+E46-F46 -> 108342.62
B47: 250815 | C47: 1855 | D47: 45888 | E47: 37922.5 | F47: 40000 | G47: 45884 | H47: =+H46+E47-F47 -> 106265.12
F48: 40000 | G48: 45888 | H48: =+H47+E48-F48 -> 66265.12
B49: 250819 | C49: 1860 | D49: 45890 | E49: 36810 | F49: 100000 | G49: 45890 | H49: =+H48+E49-F49 -> 3075.12
B50: 250820 | C50: 1861 | D50: 45892 | E50: 36180 | F50: 28360 | G50: 45892 | H50: =+H49+E50-F50 -> 10895.12
F51: 8400 | G51: 45892 | H51: =+H50+E51-F51 -> 2495.12 | J51: Transferencia Murillo Cristhian | K51: BNB
F52: 2495.12 | G52: 45894 | H52: =+H51+E52-F52 -> -4.5474735e-12
B53: 250822 | C53: 1864 | D53: 45897 | E53: 36627.5 | F53: 30000 | G53: 45897 | H53: =+H52+E53-F53 -> 6627.5
B54: 250823 | C54: 1865 | D54: 45898 | E54: 16231.5 | F54: 22859 | G54: 45898 | H54: =+H53+E54-F54 -> 0 | J54: Transferencia Murillo Cristhian | K54: BNB
B55: TOTAL AGOSTO | E55: =SUM(E44:E54) -> 277251.5 | F55: =SUM(F44:F54) -> 325114.12 | L55: =+E20+E28+E31+E43+E55 -> 1042264.5
B56: 250901 | C56: 1877 | D56: 45903 | E56: 36835 | F56: 36000 | G56: 45903 | H56: =+H54+E56-F56 -> 835 | J56: EFECTIVO recibo 1091
B57: 250908 | C57: 1885 | D57: 45909 | E57: 36712.5 | F57: 37627.5 | G57: 45909 | H57: =+H56+E57-F57 -> -80 | J57: EFECTIVO recibo 1104
B58: 250905 | C58: 1881 | D58: 45911 | E58: 14310 | F58: 30900 | G58: 45916 | H58: =+H57+E58-F58 -> -16670 | J58: EFECTIVO recibo 1107
B59: 250920 | C59: 1899 | D59: 45916 | E59: 35236.5 | F59: 29000 | G59: 45919 | H59: =+H58+E59-F59 -> -10433.5 | J59: EFECTIVO recibo 1110
B60: 250923 | C60: 1905 | D60: 45919 | E60: 36081 | F60: 11000 | G60: 45923 | H60: =+H59+E60-F60 -> 14647.5 | J60: Transferencia Murillo Cristhian | K60: BNB
B61: 250929 | C61: 1907 | D61: 45924 | E61: 31750 | F61: 8000 | G61: 45923 | H61: =+H60+E61-F61 -> 38397.5 | J61: Transferencia Murillo Cristhian | K61: BNB
B62: 250934 | C62: 1913 | D62: 45927 | E62: 12775 | F62: 18000 | G62: 45924 | H62: =+H61+E62-F62 -> 33172.5 | J62: EFECTIVO recibo 1111
F63: 17000 | G63: 45926 | H63: =+H62+E63-F63 -> 16172.5 | J63: EFECTIVO recibo 1118
F64: 3397.5 | G64: 45926 | H64: =+H63+E64-F64 -> 12775 | J64: Transferencia Murillo Cristhian | K64: BNB
F65: 10000 | G65: 45927 | H65: =+H64+E65-F65 -> 2775 | J65: EFECTIVO recibo 1119
B66: TOTAL SEPTIEMBRE | E66: =SUM(E56:E65) -> 203700 | F66: =SUM(F56:F65) -> 200925
B67: 251001 | C67: 1921 | D67: 45931 | E67: 34480 | F67: 20000 | G67: 45931 | H67: =+H65+E67-F67 -> 17255 | J67: EFECTIVO recibo 1120
B68: 251005 | C68: 1925 | D68: 45933 | E68: 32440 | F68: 10000 | G68: 45932 | H68: =+H67+E68-F68 -> 39695 | J68: Transferencia Murillo Cristhian | K68: BNB
B69: 251010 | C69: 1932 | D69: 45937 | E69: 33570 | F69: 13600 | G69: 45933 | H69: =+H68+E69-F69 -> 59665 | J69: EFECTIVO recibo 1121
B70: 251013 | C70: 1936 | D70: 45938 | E70: 13635 | F70: 44000 | G70: 45937 | H70: =+H69+E70-F70 -> 29300 | J70: EFECTIVO recibo 1134
B71: 251014 | C71: 1941 | D71: 45940 | E71: 32960 | F71: 13200 | G71: 45938 | H71: =+H70+E71-F71 -> 49060 | J71: Transferencia Murillo Cristhian | K71: BNB
B72: 251015 | C72: 1942 | D72: 45941 | E72: 20859 | F72: 11000 | G72: 45938 | H72: =+H71+E72-F72 -> 58919 | J72: EFECTIVO recibo 1137
B73: 251021 | C73: 1949 | D73: 45944 | E73: 34618 | F73: 20000 | G73: 45940 | H73: =+H72+E73-F73 -> 73537 | J73: EFECTIVO recibo 1141
B74: 251023 | C74: 1953 | D74: 45946 | E74: 13410 | F74: 7700 | G74: 45941 | H74: =+H73+E74-F74 -> 79247 | J74: EFECTIVO recibo 1142
B75: 251024 | C75: 1956 | D75: 45947 | E75: 20685 | F75: 8000 | G75: 45944 | H75: =+H74+E75-F75 -> 91932 | J75: Transferencia Murillo Cristhian | K75: BNB
B76: 251026 | C76: 1963 | D76: 45950 | E76: 34360 | F76: 6000 | G76: 45944 | H76: =+H75+E76-F76 -> 120292 | J76: Transferencia Murillo Cristhian | K76: BNB
B77: 251032 | C77: 1972 | D77: 45952 | E77: 34535 | F77: 24000 | G77: 45944 | H77: =+H76+E77-F77 -> 130827 | J77: EFECTIVO recibo 1140
B78: 251036 | C78: 1977 | D78: 45955 | E78: 13645 | F78: 3900 | G78: 45946 | H78: =+H77+E78-F78 -> 140572 | J78: Transferencia Murillo Cristhian | K78: BNB
B79: 251039 | C79: 1984 | D79: 45958 | E79: 34640 | F79: 8800 | G79: 45946 | H79: =+H78+E79-F79 -> 166412 | J79: EFECTIVO recibo 1144 | N79: =SUM(E67:E79) -> 353837 | O79: =+N79/65000 -> 5.4436462
F80: 5000 | G80: 45947 | H80: =+H79+E80-F80 -> 161412 | J80: Transferencia Murillo Cristhian | K80: BNB
F81: 11000 | G81: 45947 | H81: =+H80+E81-F81 -> 150412 | J81: EFECTIVO recibo 1145
F82: 22000 | G82: 45950 | H82: =+H81+E82-F82 -> 128412 | J82: EFECTIVO recibo 1147
F83: 35000 | G83: 45952 | H83: =+H82+E83-F83 -> 93412 | J83: EFECTIVO recibo 1149
F84: 2000 | G84: 45955 | H84: =+H83+E84-F84 -> 91412 | J84: Transferencia Murillo Cristhian | K84: BNB
F85: 31000 | G85: 45955 | H85: =+H84+E85-F85 -> 60412 | J85: EFECTIVO recibo 1153
F86: 4000 | G86: 45959 | H86: =+H85+E86-F86 -> 56412 | J86: Transferencia Murillo Cristhian | K86: BNB
F87: 36000 | G87: 45959 | H87: =+H86+E87-F87 -> 20412 | J87: EFECTIVO recibo 1149
B88: TOTAL OCTUBRE | E88: =SUM(E67:E87) -> 353837 | F88: =SUM(F67:F87) -> 336200
B89: 251101 | C89: 1996 | D89: 45966 | E89: 36235 | F89: 5000 | G89: 45966 | H89: =+H87+E89-F89 -> 51647 | J89: Transferencia Murillo Cristhian | K89: BNB
B90: 251102 | C90: 1998 | D90: 45968 | E90: 21295 | F90: 2000 | G90: 45966 | H90: =+H89+E90-F90 -> 70942 | J90: Transferencia Murillo Cristhian | K90: BNB
B91: 251105 | C91: 2005 | D91: 45972 | E91: 33890 | F91: 28000 | G91: 45966 | H91: =+H90+E91-F91 -> 76832 | J91: EFECTIVO recibo 1159
B92: 251108 | C92: 2017 | D92: 45975 | E92: 35134 | F92: 14000 | G92: 45968 | H92: =+H91+E92-F92 -> 97966 | J92: EFECTIVO recibo 1160
F93: 23700 | G93: 45972 | H93: =+H92+E93-F93 -> 74266 | J93: EFECTIVO recibo 1180
F94: 27000 | G94: 45975 | H94: =+H93+E94-F94 -> 47266 | J94: EFECTIVO recibo 1181
F95: 46266 | G95: 45985 | H95: =+H94+E95-F95 -> 1000 | J95: EFECTIVO recibo 1195
F96: 1000 | G96: 45986 | H96: =+H95+E96-F96 -> 0 | J96: Transferencia Murillo Cristhian | K96: BNB
B97: TOTAL NOVIEMBRE | E97: =SUM(E89:E96) -> 126554 | F97: =SUM(F89:F96) -> 146966
H98: =+H96+E98-F98 -> 0
H99: =+H98+E99-F99 -> 0
H100: =+H99+E100-F100 -> 0
H101: =+H100+E101-F101 -> 0
H102: =+H101+E102-F102 -> 0
H103: =+H102+E103-F103 -> 0
...

Sheet Sebastian Miranda
B2: CUENTAS POR COBRAR
B3: GESTION 2023 - 2024
C5: DISTRIBUIDOR | D5: Sebastian Miranda
C6: CELULAR: | D6: 68320858
C7: DESTINO: | D7: Oruro
C8: LINEA DE CREDITO LIMITE: | D8: 0
B10: NOTA DE VENTA | C10: NOTA DE ENTREGA | D10: FECHA DE DESPACHO | E10: MONTO P/COBRAR | F10: DEPÓSITO en Bs | G10: FECHA DE DEPÓSITO | H10: SALDO | I10: DIAS DE MORA | J10: OBSERVACION
B11: SALDO AL 31/03/25 | H11: -16.7
H12: =+H11+E12-F12 -> -16.7
H13: =+H12+E13-F13 -> -16.7
H14: =+H13+E14-F14 -> -16.7
H15: =+H14+E15-F15 -> -16.7
H16: =+H15+E16-F16 -> -16.7
H17: =+H16+E17-F17 -> -16.7
H18: =+H17+E18-F18 -> -16.7
H19: =+H18+E19-F19 -> -16.7
H20: =+H19+E20-F20 -> -16.7
H21: =+H20+E21-F21 -> -16.7
H22: =+H21+E22-F22 -> -16.7
H23: =+H22+E23-F23 -> -16.7
... H39: =+H38+E39-F39 -> -16.7
H40: =+H39+E40-F40 -> -16.7 | J40: EN EFECTIVO
H41: =+H40+E41-F41 -> -16.7
H42: =+H41+E42-F42 -> -16.7
H43: =+H42+E43-F43 -> -16.7
H44: =+H43+E44-F44 -> -16.7 | J44: EN EFECTIVO
H45: =+H44+E45-F45 -> -16.7
H46: =+H45+E46-F46 -> -16.7
H47: =+H46+E47-F47 -> -16.7 | J47: EN EFECTIVO
H48: =+H47+E48-F48 -> -16.7
H49: =+H48+E49-F49 -> -16.7
H50: =+H49+E50-F50 -> -16.7
H51: =+H50+E51-F51 -> -16.7
H52: =+H51+E52-F52 -> -16.7
H53: =+H52+E53-F53 -> -16.7
H54: =+H53+E54-F54 -> -16.7
H55: =+H54+E55-F55 -> -16.7
H56: =+H55+E56-F56 -> -16.7
H57: =+H56+E57-F57 -> -16.7
H58: =+H57+E58-F58 -> -16.7
H59: =+H58+E59-F59 -> -16.7
... H61: =+H60+E61-F61 -> -16.7
H62: =+H61+E62-F62 -> -16.7 | J62: transferencia
H63: =+H62+E63-F63 -> -16.7
H64: =+H63+E64-F64 -> -16.7
H65: =+H64+E65-F65 -> -16.7
H66: =+H65+E66-F66 -> -16.7
H67: =+H66+E67-F67 -> -16.7
H68: =+H67+E68-F68 -> -16.7
H69: =+H68+E69-F69 -> -16.7
H70: =+H69+E70-F70 -> -16.7
H71: =+H70+E71-F71 -> -16.7
H72: =+H71+E72-F72 -> -16.7
H73: =+H72+E73-F73 -> -16.7
H74: =+H73+E74-F74 -> -16.7
... H129: =+H128+E129-F129 -> -16.7
H130: =+H129 -> -16.7
B131: TOTALES | E131: =SUM(E11:E130) -> 0 | F131: =SUM(F11:F130) -> 0
B132: TOTAL SALDO POR COBRAR | F132: =+E131-F131 -> 0
B133: LINEA DE CREDITO | F133: 35000
B134: SALDO DESPUES DE LA LINEA DE CREDITO | F134: =+F132-F133 -> -35000

Sheet Norha Choque
B2: CUENTAS POR COBRAR
B3: GESTION 2023 - 2024
C5: CLIENTE: | D5: Norha Choque Talavera
C6: CELULAR: | D6: 74333570
C7: DESTINO: | D7: POTOSI
C8: LINEA DE CREDITO: | D8: 30000
B10: NOTA DE VENTA | C10: NOTA DE ENTREGA | D10: FECHA DE DESPACHO | E10: MONTO P/COBRAR | F10: DEPÓSITO en Bs | G10: FECHA DE DEPÓSITO | H10: SALDO | I10: DIAS DE MORA | J10: OBSERVACION
B11: SALDO AL 31/03/25 | H11: -141.5
H12: =+H11+E12-F12 -> -141.5
H13: =+H12+E13-F13 -> -141.5
H14: =+H13+E14-F14 -> -141.5
H15: =+H14+E15-F15 -> -141.5
H16: =+H15+E16-F16 -> -141.5
H17: =+H16+E17-F17 -> -141.5
H18: =+H17+E18-F18 -> -141.5
H19: =+H18+E19-F19 -> -141.5
H20: =+H19+E20-F20 -> -141.5
H21: =+H20+E21-F21 -> -141.5
H22: =+H21+E22-F22 -> -141.5
H23: =+H22+E23-F23 -> -141.5
... H34: =+H33+E34-F34 -> -141.5
B35: TOTALES | E35: =SUM(E11:E34) -> 0 | F35: =SUM(F11:F34) -> 0
B36: SALDO POR COBRAR | F36: =+E35-F35 -> 0
B37: LINEA DE CREDITO | F37: =+D8 -> 30000
B38: SALDO DESPUES DE LA LINEA DE CREDITO | F38: =+F36-F37 -> -30000

Sheet Marlene Paicho
B2: CUENTAS POR COBRAR
B3: GESTION 2023 - 2024
C5: CLIENTE: | D5: Marlene Paicho
C6: CELULAR: | D6: 64309758
C7: DESTINO: | D7: RUTA SUCRE Y POTOSI - COLQUECHACA
C8: LINEA DE CREDITO: | D8: 80000
B10: NOTA DE VENTA | C10: NOTA DE ENTREGA | D10: FECHA DE DESPACHO | E10: MONTO P/COBRAR | F10: DEPÓSITO en Bs | G10: FECHA DE DEPÓSITO | H10: SALDO | I10: DIAS DE MORA | J10: OBSERVACION
B11: 230816 | C11: 436 | D11: 45149 | E11: 38980 | F11: 38980 | G11: 45155 | H11: =+E11-F11 -> 0
B12: 230827 | C12: 447 | D12: 45155 | E12: 37501.4 | F12: 2445 | G12: 45174 | H12: =+H11+E12-F12 -> 35056.4
B13: 230908 | C13: 481 | D13: 45173 | E13: 2445 | H13: =+H12+E13-F13 -> 37501.4 | M13: 10000 | N13: posible deposito
H14: =+H13+E14-F14 -> 37501.4
H15: =+H14+E15-F15 -> 37501.4
H16: =+H15+E16-F16 -> 37501.4
H17: =+H16+E17-F17 -> 37501.4
H18: =+H17+E18-F18 -> 37501.4
H19: =+H18+E19-F19 -> 37501.4
H20: =+H19+E20-F20 -> 37501.4
H21: =+H20+E21-F21 -> 37501.4
H22: =+H21+E22-F22 -> 37501.4
B23: TOTALES | E23: =SUM(E11:E22) -> 78926.4 | F23: =SUM(F11:F22) -> 41425
B24: TOTAL A COBRAR | F24: =+E23-F23 -> 37501.4

Sheet Orlando Aldunate
B2: CUENTAS POR COBRAR
B3: GESTION 2025 - 2026
C5: CLIENTE: | D5: Orlando Aldunate M.
C6: CELULAR:
C7: DESTINO: | D7: TARIJA
C8: LINEA DE CREDITO:
B10: NOTA DE VENTA | C10: NOTA DE ENTREGA | D10: FECHA DE DESPACHO | E10: MONTO P/COBRAR | F10: DEPÓSITO en Bs | G10: FECHA DE DEPÓSITO | H10: SALDO | I10: DIAS DE MORA | J10: OBSERVACION
B11: 250417 | C11: 1712 | D11: 45763 | E11: 66990.5 | F11: 26990 | G11: 45763 | H11: =+E11-F11 -> 40000.5 | J11: Transf. Ariel Aldunate Marca | K11: BNB
F12: 40000 | G12: 45763 | H12: =+H11+E12-F12 -> 0.5 | J12: Transf. Ariel Aldunate Marca | K12: BNB
B13: 250441 | C13: 1733 | D13: 45775 | E13: 61319.5 | F13: 50000 | G13: 45775 | H13: =+H12+E13-F13 -> 11320 | J13: Orlando Aldunate Marca | K13: BU
F14: 11569.5 | G14: 45410 | H14: =+H13+E14-F14 -> -249.5 | J14: Transf. Ariel Aldunate Marca | K14: BNB | L14: =SUM(F11:F14) -> 128559.5
B15: 250507 | C15: 1746 | D15: 45789 | E15: 58886 | F15: 50000 | G15: 45786 | H15: =+H14+E15-F15 -> 8636.5 | J15: Orlando Aldunate Marca | K15: BU
F16: 8546 | G16: 45789 | H16: =+H15+E16-F16 -> 90.5 | J16: Transf. Ariel Aldunate Marca | K16: BNB
B17: 250517 | C17: 1765 | D17: 45801 | E17: 79464.5 | F17: 45000 | G17: 45801 | H17: =+H16+E17-F17 -> 34555 | J17: Orlando Aldunate Marca | K17: BU
F18: 30000 | G18: 45803 | H18: =+H17+E18-F18 -> 4555 | J18: Transf. Ariel Aldunate Marca | K18: BNB
F19: 4562.5 | G19: 45805 | H19: =+H18+E19-F19 -> -7.5 | J19: Transf. Ariel Aldunate Marca | K19: BNB | L19: =SUM(F15:F19) -> 138108.5
B20: 250714 | C20: 1809 | D20: 45849 | E20: 66825 | F20: 50000 | G20: 45841 | H20: =+H19+E20-F20 -> 16817.5 | J20: Orlando Aldunate Marca | K20: BU
F21: 16825 | G21: 45849 | H21: =+H20+E21-F21 -> -7.5 | J21: Ariel Aldunate Marca | K21: BU
B22: 250736 | C22: 1834 | D22: 45866 | E22: 69932.5 | F22: 44970 | G22: 45866 | H22: =+H21+E22-F22 -> 24955 | J22: Claudia Fernanda Flores. | K22: BU
F23: 24962.5 | G23: 45866 | H23: =+H22+E23-F23 -> -7.5 | J23: Transf. Ariel Aldunate Marca | K23: BNB | L23: =SUM(F20:F23) -> 136757.5
H24: =+H23+E24-F24 -> -7.5
H25: =+H24+E25-F25 -> -7.5
H26: =+H25+E26-F26 -> -7.5
H27: =+H26+E27-F27 -> -7.5
H28: =+H27+E28-F28 -> -7.5
H29: =+H28+E29-F29 -> -7.5
H30: =+H29+E30-F30 -> -7.5
H31: =+H30+E31-F31 -> -7.5
H32: =+H31+E32-F32 -> -7.5
H33: =+H32+E33-F33 -> -7.5
H34: =+H33+E34-F34 -> -7.5
H35: =+H34+E35-F35 -> -7.5
... H131: =+H130+E131-F131 -> -7.5
B132: TOTALES | E132: =SUM(E11:E131) -> 403418 | F132: =SUM(F11:F131) -> 403425.5
F133: =+E132-F132 -> -7.5

Sheet Pulperia USFX
B2: CUENTAS POR COBRAR
B3: GESTION 2025 - 2026
C5: CLIENTE: | D5: Pulperia San Francisco
C6: CELULAR:
C7: DESTINO: | D7: Sucre
C8: A CREDITO:
B10: NOTA DE VENTA | C10: NOTA DE ENTREGA | D10: FECHA DE DESPACHO | E10: MONTO P/COBRAR | F10: DEPÓSITO en Bs | G10: FECHA DE DEPÓSITO | H10: SALDO | I10: OBSERVACION
B11: 260197 | C11: 2318 | D11: 46041 | E11: 2595 | F11: 2595 | G11: 46055 | H11: =+E11-F11 -> 0 | I11: Cheque depositado
B12: 2603 | C12: 115 | D12: 46100 | E12: 1280 | F12: 1280 | G12: 46113 | H12: =+H11+E12-F12 -> 0 | I12: DEPOSITO B.U. NRO 62614836
C13: 303 | D13: 46155 | E13: 2010 | F13: 2010 | G13: 46176 | H13: =+H12+E13-F13 -> 0 | I13: DEPOSITO B.U. NRO 68907429 | L13: =SUM(F12:F13) -> 3290
C14: 574 | D14: 46238 | E14: 4920 | F14: 4920 | G14: 46261 | H14: =+H13+E14-F14 -> 0 | I14: DEPOSITO B.U. NRO 68907429
H15: =+H14+E15-F15 -> 0
H16: =+H15+E16-F16 -> 0 | L16: =SUM(F14:F16) -> 4920
H17: =+H16+E17-F17 -> 0
H18: =+H17+E18-F18 -> 0
H19: =+H18+E19-F19 -> 0
H20: =+H19+E20-F20 -> 0
H21: =+H20+E21-F21 -> 0
H22: =+H21+E22-F22 -> 0
H23: =+H22+E23-F23 -> 0
B24: TOTALES | E24: =SUM(E11:E23) -> 10805 | F24: =SUM(F11:F23) -> 10805
B25: SALDO POR COBRAR | F25: =+E24-F24 -> 0

Sheet RECAU. SEPT 2025
A3: CUENTAS POR COBRAR A CLIENTES
A4: GESTION 2023 - 2024
A5: SEPTIEMBRE - 2025
A6: Nº | B6: DISTRIBUIDOR | C6: DEPARTAMENTO | AI6: TOTAL MES
D7: 1 | E7: 2 | F7: 3 | G7: 4 | H7: Semana 1 | I7: 6 | J7: 7 | K7: 8 | L7: 9 | M7: 10 | N7: 11 | O7: Semana 2 | P7: 13 | Q7: 14 | R7: 15 | S7: 16 | T7: 17 | U7: 18 | V7: Semana 3 | W7: 20 | X7: 21 | Y7: 22 | Z7: 23 | AA7: 24 | AB7: 25 | AC7: Semana 4 | AD7: 27 | AE7: 28 | AF7: 29 | AG7: 31 | AH7: Semana 4
A8: 1 | B8: Fabricio Tapia Castedo | C8: Cochabamba | H8: =SUM(D8:G8) -> 0 | O8: =SUM(I8:N8) -> 0 | V8: =SUM(P8:U8) -> 0 | AC8: =SUM(W8:AB8) -> 0 | AH8: =SUM(AD8:AG8) -> 0 | AI8: =+H8+O8+V8+AH8 -> 0
A9: =1+A8 -> 2 | B9: Edwin Fernandez Chirinos | C9: El Alto | H9: =SUM(D9:G9) -> 0 | O9: =SUM(I9:N9) -> 0 | V9: =SUM(P9:U9) -> 0 | AC9: =SUM(W9:AB9) -> 0 | AH9: =SUM(AD9:AG9) -> 0 | AI9: =+H9+O9+V9+AH9 -> 0
A10: =1+A9 -> 3 | B10: Javier Caceres | C10: Cochabamba | H10: =SUM(D10:G10) -> 0 | O10: =SUM(I10:N10) -> 0 | V10: =SUM(P10:U10) -> 0 | AC10: =SUM(W10:AB10) -> 0 | AH10: =SUM(AD10:AG10) -> 0 | AI10: =+H10+O10+V10+AH10 -> 0
A11: =1+A10 -> 4 | B11: Juan Carlos Torrez Ayarde | C11: Tarija | H11: =SUM(D11:G11) -> 0 | O11: =SUM(I11:N11) -> 0 | V11: =SUM(P11:U11) -> 0 | AC11: =SUM(W11:AB11) -> 0 | AH11: =SUM(AD11:AG11) -> 0 | AI11: =+H11+O11+V11+AH11 -> 0
A12: =1+A11 -> 5 | B12: Carol Alejandra Noya | C12: Tarija | H12: =SUM(D12:G12) -> 0 | O12: =SUM(I12:N12) -> 0 | V12: =SUM(P12:U12) -> 0 | AC12: =SUM(W12:AB12) -> 0 | AH12: =SUM(AD12:AG12) -> 0 | AI12: =+H12+O12+V12+AH12 -> 0
A13: =1+A12 -> 6 | B13: Luis Alberto Chipana Peña | C13: Cochabamba | H13: =SUM(D13:G13) -> 0 | O13: =SUM(I13:N13) -> 0 | V13: =SUM(P13:U13) -> 0 | AC13: =SUM(W13:AB13) -> 0 | AH13: =SUM(AD13:AG13) -> 0 | AI13: =+H13+O13+V13+AH13 -> 0
A14: =1+A13 -> 7 | B14: Franz Carlos Alanez Flores | C14: El Alto | H14: =SUM(D14:G14) -> 0 | O14: =SUM(I14:N14) -> 0 | V14: =SUM(P14:U14) -> 0 | AC14: =SUM(W14:AB14) -> 0 | AH14: =SUM(AD14:AG14) -> 0 | AI14: =+H14+O14+V14+AH14 -> 0
A15: =1+A14 -> 8 | B15: Andrés Miguel Paniagua | C15: Oruro | H15: =SUM(D15:G15) -> 0 | O15: =SUM(I15:N15) -> 0 | V15: =SUM(P15:U15) -> 0 | AC15: =SUM(W15:AB15) -> 0 | AH15: =SUM(AD15:AG15) -> 0 | AI15: =+H15+O15+V15+AH15 -> 0
A16: =1+A15 -> 9 | B16: Alex Rolando Fernandez H. | C16: Oruro | H16: =SUM(D16:G16) -> 0 | O16: =SUM(I16:N16) -> 0 | V16: =SUM(P16:U16) -> 0 | AC16: =SUM(W16:AB16) -> 0 | AH16: =SUM(AD16:AG16) -> 0 | AI16: =+H16+O16+V16+AH16 -> 0
A17: =1+A16 -> 10 | B17: Franklin Ever Viveros | C17: Potosí | H17: =SUM(D17:G17) -> 0 | O17: =SUM(I17:N17) -> 0 | V17: =SUM(P17:U17) -> 0 | AC17: =SUM(W17:AB17) -> 0 | AH17: =SUM(AD17:AG17) -> 0 | AI17: =+H17+O17+V17+AH17 -> 0
A18: =1+A17 -> 11 | B18: Teofilo Ibañez Soliz | C18: Tarija | H18: =SUM(D18:G18) -> 0 | O18: =SUM(I18:N18) -> 0 | V18: =SUM(P18:U18) -> 0 | AC18: =SUM(W18:AB18) -> 0 | AH18: =SUM(AD18:AG18) -> 0 | AI18: =+H18+O18+V18+AH18 -> 0
A19: =1+A18 -> 12 | B19: Elsa Romay Padilla | C19: Uyuni | H19: =SUM(D19:G19) -> 0 | O19: =SUM(I19:N19) -> 0 | V19: =SUM(P19:U19) -> 0 | AC19: =SUM(W19:AB19) -> 0 | AH19: =SUM(AD19:AG19) -> 0 | AI19: =+H19+O19+V19+AH19 -> 0
A20: =1+A19 -> 13 | B20: Jorge Luis Vedia Arancibia | C20: Chuquisaca - Prov | H20: =SUM(D20:G20) -> 0 | O20: =SUM(I20:N20) -> 0 | V20: =SUM(P20:U20) -> 0 | AC20: =SUM(W20:AB20) -> 0 | AH20: =SUM(AD20:AG20) -> 0 | AI20: =+H20+O20+V20+AH20 -> 0
A21: =1+A20 -> 14 | B21: Celina Cruz Mendez | C21: Chuquisaca - Prov | H21: =SUM(D21:G21) -> 0 | O21: =SUM(I21:N21) -> 0 | V21: =SUM(P21:U21) -> 0 | AC21: =SUM(W21:AB21) -> 0 | AH21: =SUM(AD21:AG21) -> 0 | AI21: =+H21+O21+V21+AH21 -> 0
A22: =1+#REF! -> #REF! | B22: Marlene Paicho | C22: Ruta Colquechaca | H22: =SUM(D22:G22) -> 0 | O22: =SUM(I22:N22) -> 0 | V22: =SUM(P22:U22) -> 0 | AC22: =SUM(W22:AB22) -> 0 | AH22: =SUM(AD22:AG22) -> 0 | AI22: =H22+O22+V22+AH22 -> 0
A23: TOTAL CLIENTES MOROSOS | G23: =SUM(G8:G22) -> 0 | H23: =SUM(D23:G23) -> 0 | I23: =SUM(I8:I22) -> 0 | J23: =SUM(J8:J22) -> 0 | K23: =SUM(K8:K22) -> 0 | L23: =SUM(L8:L22) -> 0 | M23: =SUM(M8:M22) -> 0 | N23: =SUM(N8:N22) -> 0 | O23: =SUM(I23:N23) -> 0 | P23: =SUM(P8:P22) -> 0 | Q23: =SUM(Q8:Q22) -> 0 | R23: =SUM(R8:R22) -> 0 | S23: =SUM(S8:S22) -> 0 | T23: =SUM(T8:T22) -> 0 | U23: =SUM(U8:U22) -> 0 | V23: =SUM(P23:U23) -> 0 | W23: =SUM(W8:W22) -> 0 | X23: =SUM(X8:X22) -> 0 | Y23: =SUM(Y8:Y22) -> 0 | Z23: =SUM(Z8:Z22) -> 0 | AA23: =SUM(AA8:AA22) -> 0 | AB23: =SUM(AB8:AB22) -> 0 | AC23: =SUM(W23:AB23) -> 0 | AD23: =SUM(AD8:AD22) -> 0 | AG23: =SUM(AG8:AG22) -> 0 | AH23: =SUM(AD23:AG23) -> 0 | AI23: =SUM(AI8:AI22) -> 0
A24: 1 | B24: Gustavo Tellez Ugarte | C24: Santa Cruz | H24: =SUM(D24:G24) -> 0 | O24: =SUM(I24:N24) -> 0 | V24: =SUM(P24:U24) -> 0 | AC24: =SUM(W24:AB24) -> 0 | AH24: =SUM(AD24:AG24) -> 0 | AI24: =H24+O24+V24+AC24+AH24 -> 0
A25: =1+A24 -> 2 | B25: Cristhian Murillo | C25: Sucre | H25: =SUM(D25:G25) -> 0 | O25: =SUM(I25:N25) -> 0 | V25: =SUM(P25:U25) -> 0 | AC25: =SUM(W25:AB25) -> 0 | AG25: 197527.5 | AH25: =SUM(AD25:AG25) -> 197527.5 | AI25: =H25+O25+V25+AC25+AH25 -> 197527.5
A26: =1+A25 -> 3 | B26: Fausto Condori | C26: Cochabamba | H26: =SUM(D26:G26) -> 0 | O26: =SUM(I26:N26) -> 0 | V26: =SUM(P26:U26) -> 0 | AC26: =SUM(W26:AB26) -> 0 | AG26: 50640 | AH26: =SUM(AD26:AG26) -> 50640 | AI26: =H26+O26+V26+AC26+AH26 -> 50640
A27: =1+A26 -> 4 | B27: GAMS Desarrollo Productivo | C27: Sucre | H27: =SUM(D27:G27) -> 0 | O27: =SUM(I27:N27) -> 0 | V27: =SUM(P27:U27) -> 0 | AC27: =SUM(W27:AB27) -> 0 | AH27: =SUM(AD27:AG27) -> 0 | AI27: =H27+O27+V27+AC27+AH27 -> 0
A28: =1+A27 -> 5 | B28: GAMS Direccion Administrativa | C28: Sucre | H28: =SUM(D28:G28) -> 0 | O28: =SUM(I28:N28) -> 0 | V28: =SUM(P28:U28) -> 0 | AC28: =SUM(W28:AB28) -> 0 | AG28: 6960 | AH28: =SUM(AD28:AG28) -> 6960 | AI28: =H28+O28+V28+AC28+AH28 -> 6960
A29: =1+A28 -> 6 | B29: Carmen Cruz | C29: Potosí | H29: =SUM(D29:G29) -> 0 | O29: =SUM(I29:N29) -> 0 | V29: =SUM(P29:U29) -> 0 | AC29: =SUM(W29:AB29) -> 0 | AG29: 118110 | AH29: =SUM(AD29:AG29) -> 118110 | AI29: =H29+O29+V29+AC29+AH29 -> 118110
A30: =1+A29 -> 7 | B30: Jorge Saavedra | C30: Tupiza | H30: =SUM(D30:G30) -> 0 | O30: =SUM(I30:N30) -> 0 | V30: =SUM(P30:U30) -> 0 | AC30: =SUM(W30:AB30) -> 0 | AH30: =SUM(AD30:AG30) -> 0 | AI30: =H30+O30+V30+AC30+AH30 -> 0
A31: =1+A30 -> 8 | B31: Jenrry | C31: Chile | H31: =SUM(D31:G31) -> 0 | O31: =SUM(I31:N31) -> 0 | V31: =SUM(P31:U31) -> 0 | AC31: =SUM(W31:AB31) -> 0 | AH31: =SUM(AD31:AG31) -> 0 | AI31: =H31+O31+V31+AC31+AH31 -> 0
A32: =1+A31 -> 9 | B32: Eddy | C32: Chile | H32: =SUM(D32:G32) -> 0 | O32: =SUM(I32:N32) -> 0 | V32: =SUM(P32:U32) -> 0 | AC32: =SUM(W32:AB32) -> 0 | AG32: 226388 | AH32: =SUM(AD32:AG32) -> 226388 | AI32: =H32+O32+V32+AC32+AH32 -> 226388
A33: =1+A32 -> 10 | B33: Rene Cahuana | C33: La Paz | H33: =SUM(D33:G33) -> 0 | O33: =SUM(I33:N33) -> 0 | V33: =SUM(P33:U33) -> 0 | AC33: =SUM(W33:AB33) -> 0 | AG33: 58288 | AH33: =SUM(AD33:AG33) -> 58288 | AI33: =H33+O33+V33+AC33+AH33 -> 58288
A34: =1+A33 -> 11 | B34: Ines Aguirre | C34: Provincias Villazon | H34: =SUM(D34:G34) -> 0 | O34: =SUM(I34:N34) -> 0 | V34: =SUM(P34:U34) -> 0 | AC34: =SUM(W34:AB34) -> 0 | AH34: =SUM(AD34:AG34) -> 0 | AI34: =H34+O34+V34+AC34+AH34 -> 0
A35: =1+A34 -> 12 | B35: Yobana Llanos Cruz | C35: Ruta Chapare | H35: =SUM(D35:G35) -> 0 | O35: =SUM(I35:N35) -> 0 | V35: =SUM(P35:U35) -> 0 | AC35: =SUM(W35:AB35) -> 0 | AH35: =SUM(AD35:AG35) -> 0 | AI35: =H35+O35+V35+AC35+AH35 -> 0
A36: =1+A35 -> 13 | B36: Hernan Colque Cruz | C36: Pisiga | H36: =SUM(D36:G36) -> 0 | O36: =SUM(I36:N36) -> 0 | V36: =SUM(P36:U36) -> 0 | AC36: =SUM(W36:AB36) -> 0 | AH36: =SUM(AD36:AG36) -> 0 | AI36: =H36+O36+V36+AC36+AH36 -> 0
A37: =1+A36 -> 14 | B37: Ismael Marca | C37: Uyuni | H37: =SUM(D37:G37) -> 0 | O37: =SUM(I37:N37) -> 0 | V37: =SUM(P37:U37) -> 0 | AC37: =SUM(W37:AB37) -> 0 | AH37: =SUM(AD37:AG37) -> 0 | AI37: =H37+O37+V37+AC37+AH37 -> 0
A38: =1+A37 -> 15 | B38: Ruth Gabriela | C38: Pando | AH38: =SUM(AD38:AG38) -> 0 | AI38: =H38+O38+V38+AC38+AH38 -> 0
A39: =1+A38 -> 16 | B39: Jhaneth Miriam Toroya Gabriel | C39: Oruro | AG39: 137808.5 | AH39: =SUM(AD39:AG39) -> 137808.5 | AI39: =H39+O39+V39+AC39+AH39 -> 137808.5
A40: =1+A39 -> 17 | B40: Grupo ULTRA Sta Cruz | C40: Santa Cruz | AH40: =SUM(AD40:AG40) -> 0 | AI40: =H40+O40+V40+AC40+AH40 -> 0
A41: =1+A40 -> 18 | B41: Alexander Vides | C41: Tarija | AG41: 133103 | AH41: =SUM(AD41:AG41) -> 133103 | AI41: =H41+O41+V41+AC41+AH41 -> 133103
A42: =1+A41 -> 19 | B42: Paul Yamani | C42: Cochabamba | AG42: 48000 | AH42: =SUM(AD42:AG42) -> 48000 | AI42: =H42+O42+V42+AC42+AH42 -> 48000
A43: =1+A42 -> 20 | B43: Alejandro Luna | C43: Chile | AH43: =SUM(AD43:AG43) -> 0 | AI43: =H43+O43+V43+AC43+AH43 -> 0
A44: =1+A43 -> 21 | B44: Yoelma | C44: Tupiza Villazon | AG44: 128148 | AH44: =SUM(AD44:AG44) -> 128148 | AI44: =H44+O44+V44+AC44+AH44 -> 128148
A45: =1+A44 -> 22 | B45: Lina | C45: Caracollo | AG45: 15000 | AH45: =SUM(AD45:AG45) -> 15000 | AI45: =H45+O45+V45+AC45+AH45 -> 15000
A46: =1+A45 -> 23 | B46: Ruth Fajardo | C46: Caranavi | AG46: 50000 | AH46: =SUM(AD46:AG46) -> 50000 | AI46: =H46+O46+V46+AC46+AH46 -> 50000
A47: =1+A46 -> 24 | B47: Venta colillas y otros | C47: Sucre | H47: =SUM(D47:G47) -> 0 | O47: =SUM(I47:N47) -> 0 | V47: =SUM(P47:U47) -> 0 | AC47: =SUM(W47:AB47) -> 0 | AH47: =SUM(AD47:AG47) -> 0 | AI47: =H47+O47+V47+AC47+AH47 -> 0
A48: =1+A47 -> 25 | B48: Ventas en FABRICA | C48: Sucre | H48: =SUM(D48:G48) -> 0 | O48: =SUM(I48:N48) -> 0 | V48: =SUM(P48:U48) -> 0 | AC48: =SUM(W48:AB48) -> 0 | AG48: 22689 | AH48: =SUM(AD48:AG48) -> 22689 | AI48: =H48+O48+V48+AC48+AH48 -> 22689
A49: TOTALE CLIENTES ACTIVOS | G49: =SUM(G24:G48) -> 0 | H49: =SUM(D49:G49) -> 0 | I49: =SUM(I24:I48) -> 0 | J49: =SUM(J24:J48) -> 0 | K49: =SUM(K24:K48) -> 0 | L49: =SUM(L24:L48) -> 0 | M49: =SUM(M24:M48) -> 0 | N49: =SUM(N24:N48) -> 0 | O49: =SUM(I49:N49) -> 0 | P49: =SUM(P24:P48) -> 0 | Q49: =SUM(Q24:Q48) -> 0 | R49: =SUM(R24:R48) -> 0 | S49: =SUM(S24:S48) -> 0 | T49: =SUM(T24:T48) -> 0 | U49: =SUM(U24:U48) -> 0 | V49: =SUM(P49:U49) -> 0 | W49: =SUM(W24:W48) -> 0 | X49: =SUM(X24:X48) -> 0 | Y49: =SUM(Y24:Y48) -> 0 | Z49: =SUM(Z24:Z48) -> 0 | AA49: =SUM(AA24:AA48) -> 0 | AB49: =SUM(AB24:AB48) -> 0 | AC49: =SUM(W49:AB49) -> 0 | AD49: =SUM(AD24:AD48) -> 0 | AE49: =SUM(AE24:AE48) -> 0 | AF49: =SUM(AF24:AF48) -> 0 | AG49: =SUM(AG24:AG48) -> 1192662 | AH49: =SUM(AD49:AG49) -> 1192662 | AI49: =SUM(AI24:AI48) -> 1192662
A50: TOTALE CLIENTES | D50: =+D23+D49 -> 0 | E50: =+E23+E49 -> 0 | F50: =+F23+F49 -> 0 | G50: =+G23+G49 -> 0 | H50: =SUM(D50:G50) -> 0 | I50: =+I23+I49 -> 0 | J50: =+J23+J49 -> 0 | K50: =+K23+K49 -> 0 | L50: =+L23+L49 -> 0 | M50: =+M23+M49 -> 0 | N50: =+N23+N49 -> 0 | O50: =SUM(I50:N50) -> 0 | P50: =+P23+P49 -> 0 | Q50: =+Q23+Q49 -> 0 | R50: =+R23+R49 -> 0 | S50: =+S23+S49 -> 0 | T50: =+T23+T49 -> 0 | U50: =+U23+U49 -> 0 | V50: =SUM(P50:U50) -> 0 | W50: =+W23+W49 -> 0 | X50: =+X23+X49 -> 0 | Y50: =+Y23+Y49 -> 0 | Z50: =+Z23+Z49 -> 0 | AA50: =+AA23+AA49 -> 0 | AB50: =+AB23+AB49 -> 0 | AC50: =SUM(W50:AB50) -> 0 | AD50: =+AD23+AD49 -> 0 | AH50: =SUM(AD50:AG50) -> 0 | AI50: =SUM(AI49,AI23) -> 1192662

Sheet Rene Cahuana
B2: CUENTAS POR COBRAR
B3: GESTION 2025 - 2026
C5: CLIENTE: | D5: Rene Cahuana
C6: CELULAR:
C7: DESTINO: | D7: La Paz
C8: LINEA DE CREDITO: | D8: al contado
B10: NOTA DE VENTA | C10: NOTA DE ENTREGA | D10: FECHA DE DESPACHO | E10: MONTO P/COBRAR | F10: DEPÓSITO en Bs | G10: FECHA DE DEPÓSITO | H10: SALDO | I10: DIAS DE MORA | J10: OBSERVACION
B11: 250402 | C11: 1694 | D11: 45752 | E11: 47812 | F11: 19425 | G11: 45752 | H11: =+E11-F11 -> 28387 | J11: Casas Murillo Ivone | K11: BNB
F12: 28387 | G12: 45752 | H12: =+H11+E12-F12 -> 0 | J12: Transferencia | K12: BU
B13: 250431 | C13: 1725 | D13: 45773 | E13: 71680 | F13: 46600 | G13: 45772 | H13: =+H12+E13-F13 -> 25080 | J13: Casas Murillo Ivone | K13: BU
F14: 25080 | G14: 45773 | H14: =+H13+E14-F14 -> 0 | J14: Transferencia | K14: BU | L14: =SUM(F11:F14) -> 119492
F15: 10000 | G15: 45777 | H15: =+H14+E15-F15 -> -10000 | J15: Transferencia | K15: BU
F16: -10000 | G16: 45798 | H16: =+H15+E16-F16 -> 0 | J16: Devolucion a misma cuenta | K16: BU
B17: 250719 | C17: 1815 | D17: 45852 | E17: 65350 | F17: 28450 | G17: 45852 | H17: =+H16+E17-F17 -> 36900 | J17: Casas Murillo Ivone | K17: BU
F18: 36900 | G18: 45852 | H18: =+H17+E18-F18 -> 0 | J18: Transferencia | K18: BU
B19: 250728 | C19: 1826 | D19: 45859 | E19: 67850 | F19: 33800 | G19: 45859 | H19: =+H18+E19-F19 -> 34050 | J19: Casas Murillo Ivone | K19: BU
F20: 34050 | G20: 45859 | H20: =+H19+E20-F20 -> 0 | J20: Transferencia | K20: BU
B21: 250741 | C21: 1839 | D21: 45869 | E21: 73775 | F21: 30500 | G21: 45869 | H21: =+H20+E21-F21 -> 43275 | J21: Casas Murillo Ivone | K21: BNB
F22: 43275 | G22: 45869 | H22: =+H21+E22-F22 -> 0 | J22: Transferencia | K22: BU | L22: =SUM(F17:F22) -> 206975
B23: 250814 | C23: 1854 | D23: 45887 | E23: 65652 | F23: 49000 | G23: 45887 | H23: =+H22+E23-F23 -> 16652 | J23: Casas Murillo Ivone | K23: BNB
